{
  "metadata": {
    "file_name": "2024-11-06_民生证券_有色金属_海外黄金股观察系列之四：金田黄金：南非金矿巨头，并购走向全球.pdf",
    "file_stem": "2024-11-06_民生证券_有色金属_海外黄金股观察系列之四：金田黄金：南非金矿巨头，并购走向全球",
    "relative_path": "2024-11-06_民生证券_有色金属_海外黄金股观察系列之四：金田黄金：南非金矿巨头，并购走向全球.pdf",
    "source_path": "/Users/macbook/Desktop/黄金/2024-11-06_民生证券_有色金属_海外黄金股观察系列之四：金田黄金：南非金矿巨头，并购走向全球.pdf",
    "page_count": 40,
    "converted_pages": 40,
    "text_chars": 43370,
    "table_count": 46,
    "pdf_metadata": {
      "Author": "json",
      "Creator": "Microsoft® Word 2016",
      "CreationDate": "D:20241106162022+08'00'",
      "ModDate": "D:20241106162022+08'00'",
      "Producer": "Microsoft® Word 2016"
    }
  },
  "pages": [
    {
      "page_number": 1,
      "width": 595.32,
      "height": 841.92,
      "text": "海外黄金股观察系列之四\n金田黄金：南非金矿巨头，并购走向全球 2024 年 11 月 06 日\n➢ 金田黄金是全球第七大黄金企业。（1）公司发展历史悠久，行业地位突出： 推荐 维持评级\n公司前身可追溯至 1887 年，1998 年与南非黄金企业 Gencor 合并，成立 Gold\nFields Limited，之后通过持续并购，成长为全球第七大黄金企业。公司由南非\n起家，在澳大利亚、南非、加纳、智利和秘鲁拥有 10 座矿山。（2）黄金贡献多 [Table_Author]\n数利润，整体经营稳健：从财务指标上看，公司营收利润均随金价波动，2020 年\n金价大幅上涨后公司营收和净利润均有所抬升，后续整体平稳。从营收结构上来\n看，公司主营业务收入来自黄金和铜，其中主要是黄金，占比达到 95%。归母净\n利润方面，2020 年随着金价大幅上涨，公司归母净利润同比增长 347%至 7.23\n亿美元，此后尽管金价仍有所上涨，但由于成本抬升，公司的归母净利润上下波\n动。公司资产负债表健康，未来资本开支稳定。资产负债率稳定在 40%左右，资\n分析师 邱祖学\n本开支近三年维持在 10 亿美金。 执业证书： S0100521120001\n邮箱： qiuzuxue@mszq.com\n➢ 公司非洲起家，资源版图扩张至美澳。资源禀赋来看，公司的矿山主要分布\n分析师 张弋清\n在非洲、澳大利亚、南美洲的秘鲁和智利，旗下共有 9 座矿山有储量（8 座金矿，\n执业证书： S0100523100001\n1 座铜矿），截至 2023 年底，公司的黄金权益储量合计为 44.6 百万盎司（合计 邮箱： zhangyiqing@mszq.com\n1388.7 吨），平均品位为 2.86g/t，铜权益储量合计为 15.24 万吨，平均品位为\n0.34%，白银权益储量合计为 41.9 盎司（1304.5 吨），平均品位为 71.9g/t。 相关研究\n产量来看，公司近几年黄金产量持续下滑，铜产量维持相对稳定。2018-2023 年 1.海外黄金股观察系列之五：埃尔拉多黄金：\n公司黄金权益产量从 63.5 吨提升至 71.5 吨，CAGR 为 2.4%。2018-2022 年， 资产优化不断，发展潜力可期-2024/11/06\n2.有色金属周报 20241102：工业金属价格高\n黄金权益产量持续增加，主要是因为 South Deep 资本投入的增加，2023 年黄\n位震荡，金价续创新高-2024/11/02\n金产量的下降，主要是因为 Damang 矿山寿命的临近。铜权益产量 2.7 万吨均\n3.有色金属周报 20241026：工业金属涨跌不\n来自于秘鲁的 Cerro Corona 金铜矿。成本来看，公司铜金成本近几年持续上行，\n一，黄金价格创新高-2024/10/27\n公司黄金全维持成本（AISC,现金成本加上矿山维护，环境修复等持续性资本开 4.海外黄金股观察系列之三：盎格鲁黄金：迟\n支）从 2018 年的 981 美元/盎司上升至 2023 年 1295 美元/盎司，CAGR 为 暮英雄，尚能饭否？-2024/10/25\n5.7%。分矿山来看，2023 年公司在非洲地区的黄金权益产量占了全公司黄金权 5.海外黄金股观察系列之二：纽蒙特：百年并\n购史，铸就黄金龙头-2024/10/22\n益产量的 47.9%。主要来自于位于加纳的 Tarkwa 金矿（占比 24.3%，公司持股\n90%）和位于南非的 South Deep 金矿（占比 14.2%，公司持股 90.331%）。\n2023 年公司在澳大利亚地区的黄金权益产量占了全公司黄金权益产量的\n46.7%。主要来自于 St lves 金矿（占比 16.4%），Granny Smith 金矿（占比\n12.5%），Agnew 金矿（占比 10.6%）以及 Gruyere（占比 7.1%，公司持股\n50%）。\n➢ 远期展望：我们认为金田黄金作为全球较大的黄金开采公司之一，受部分矿\n山生命周期影响其增量势头有所放缓，公司计划通过勘探和收购来增加矿藏储\n量，确保长期可持续生产能力。目前公司远期产量及资源情况主要表现为以下几\n点： 1）远期增量主要来自智利地区。金田预计 2024-2026 年黄金当量产量为\n243 万盎司、270 万盎司、260 万盎司。远期增量主要来自于智利地区 Salares\nNorte 项目，预计 2025 年到 2029 年平均年产量达到 48.5 万盎司。2）部分地\n区产量将有所下滑。除南非和澳大利亚地区产量将保持稳定外，受资源限制公司\n预计加纳和秘鲁地区远期产量将有所下滑。3）布局优质资源，探矿增储工作仍\n将持续。金田的多个矿山项目均具有较高品位和良好经济可行性。South Deep\n矿山品位超过 6 克/吨，且拥有较长的开采寿命，Windfall 高品位矿山项目现处\n评估规划阶段、Agnew 等矿山持续进行增储工作。\n➢ 风险提示：地缘政治风险，项目投产不及预期的风险，金属价格波动风险。\n本公司具备证券投资咨询业务资格，请务必阅读最后一页免责声明 证券研究报告 1",
      "tables": []
    },
    {
      "page_number": 2,
      "width": 595.32,
      "height": 841.92,
      "text": "行业深度研究/有色金属\n目录\n1 全球第七大黄金生产商，南非金矿巨头走向全球 ...................................................................................................... 3\n1.1 百年黄金企业，加快并购步伐 ......................................................................................................................................................... 3\n1.2 黄金贡献绝大多数利润，整体经营较稳健 .................................................................................................................................... 6\n2 非洲起家，资源版图扩张至全球 ............................................................................................................................... 9\n2.1 全球领先黄金巨头，资源禀赋优异 ................................................................................................................................................ 9\n2.2 产量：近几年公司黄金产量上下波动 .......................................................................................................................................... 12\n2.3 成本：公司铜金成本近几年持续上行 .......................................................................................................................................... 13\n2.4 分矿山来看，公司旗下拥有较多优质资产 .................................................................................................................................. 14\n3 远期增量：主要来源于智利 ................................................................................................................................... 25\n3.1 增量有限，主要来源于智利地区 .................................................................................................................................................. 25\n3.2 项目细览：多地布局，勘探增储为主要工作 .............................................................................................................................. 26\n4 风险提示 .............................................................................................................................................................. 37\n插图目录 .................................................................................................................................................................. 38\n表格目录 .................................................................................................................................................................. 39\n本公司具备证券投资咨询业务资格，请务必阅读最后一页免责声明 证券研究报告 2",
      "tables": []
    },
    {
      "page_number": 3,
      "width": 595.32,
      "height": 841.92,
      "text": "行业深度研究/有色金属\n1 全球第七大黄金生产商，南非金矿巨头走向全球\n1.1 百年黄金企业，加快并购步伐\n金田黄金历史悠久，是南非的黄金矿业巨头。金田黄金公司于 1887 年成立，\n最初公司名字叫做 Gold Fields of South Africa，总部位于南非的约翰内斯堡。\n1968 年在南非约翰内斯堡证券交易所上市，1992 年 7 月 1 日在纽约证券交易所\n上市，1998 年，公司与南非黄金企业 Gencor 合并，成为 Gold Fields Limited。\n1993 年，与加纳政府签署管理合同运营 Tarkwa 金矿。于 1996 年完成了露\n天/堆浸作业的可行性研究。1998 年，Tarkwa 第一阶段的初步开发完成，露天开\n采量为 1450 万吨/年，包括 470 万吨/年的堆浸给矿。1999 年，塔克瓦二期扩建\n工程完工，采矿率提高到 2070 万吨/年，堆浸给矿产量提高到 720 万吨/年。所有\n地下作业和相关加工厂于同年停止生产。2000 年，GFG 收购了 Teberebie 北部\n地区，采矿产量提高到 3600 万吨/年。2011 年，GFG 收购了 Tarkwa18.9%的\nIAMGold 权益，目前持有 90%的股份，其余 10%由加纳政府持有。\n2001 年，收购 St Ives 金矿。\n2003 年，与 Sociedad Minera Corona S.A. 签署了最终协议，购买 Cerro\nCorona 矿床和毗邻的采矿特许权。本次收购秘鲁金铜矿，进军铜板快。\n2006 年 12 月 1 日，从巴里克黄金收购 South Deep50%股权。2007 年 4\n月收购剩余 50%股权，控股 South Deep 金矿。2010 年 South Deep 获得了新\n一轮采矿权，包括被称为 Uncle Harry’s 的地区。2011 年，Newshelf 成立，持\n有 South Deep 金矿的 100%权益。 Newshelf 是金田黄金的 90%子公司，其余\n10%由外部股东持有，属于广泛黑人经济赋权(BBBEE)交易的一部分。\n2008 年，接管芬兰的北极钯铂项目。该项目最初在 2000 年由合作方\nOutokumpu 勘探，金田黄金于 2003 年收购了该合伙公司 100%的股权，并注册\n了 GFAP 作为运营公司。2005 年至 2008 年，GFAP 与 North American Palladium\nLimited (NAP)签订了收购和框架协议，该期权协议于 2008 年到期，当时 NAP 选\n择不履行其权利。Gold Fields 从 2008 年 9 月 1 日起全面管理和控制 GFAP。目\n前还未进行商业开采。\n2012 年，拆分南非子公司上市。金田黄金拆分了其子公司 GFI Mining South\nAfrica Proprietary Limited，后者随后更名为 Sibanye Gold Limited（后来更名\n为 Sibanye Stillwater，由 KDC (以前的 Kloof) 和 Beatrix 矿山以及南非的一\n系列支持服务实体组成。后来该公司成长为全球最大的铂族元素生产商之一。\n2013 年 10 月 1 日，从巴里克黄金收购 Yilgarn South 矿山（包括 Granny\nSmith、Lawlers 和 Darlot 矿）。巴里克出售这些矿山是因为认为它们成本高昂，\n本公司具备证券投资咨询业务资格，请务必阅读最后一页免责声明 证券研究报告 3",
      "tables": []
    },
    {
      "page_number": 4,
      "width": 595.32,
      "height": 841.92,
      "text": "行业深度研究/有色金属\n需要现金来补偿其 Pascua-Lama 黄金项目不断上升的成本。这三个矿山当时占\n巴里克年黄金产量的 6%。金田黄金 以 3 亿美元购买了这些矿山，其中一半必须\n以现金支付，另一半可以发行股票。\n2022 年 5 月底：尝试收购 Yamana Gold 失败。Gold Fields 宣布计划以 67\n亿美元的全股票交易收购加拿大的 Yamana Gold，这将使其成为世界第四大黄金\n生产商，合并后的公司总部将设在约翰内斯堡。2023 年 1 月底：Yamana Gold\n的股东批准了与 Pan American Silver 和 Agnico Eagle Mines 的收购交易，而\n不是 Gold Fields。\n2023 年 3 月，与全球第六大黄金生产公司 AngloGold Ashanti 在加纳成\n立合资公司。以合并管理加纳塔克瓦金矿（Tarkwa）和伊杜瓦普里姆金矿金矿\n（Iduapriem），创建非洲最大的金矿。拟成立的合资企业将在金田加纳公司内成\n立，由金田运营。盎格鲁将把其在伊矿的 100%权益交给金田加纳公司，以换取该\n公司的股权。双方预计，任何一家公司都不需要为建立拟议的合资企业而进行任何\n实质性的额外注资，一旦投入运营，预计将极大地改善其资本强度。不考虑加纳政\n府持有的权益，金田将拥有合资公司 2/3 权益，盎格鲁将拥有剩余 1/3 权益。在\n提交给加纳政府的文件中，双方表示，加纳政府将拥有合资公司 10%股份，获得\n更大的政府参与。\n2024 年 8 月：拟收购 Osisko Mining 以获得全球前十大金矿 Windfall 金\n矿剩余 50%的权益。Gold Fields 宣布已同意约 21.6 亿加元（15.7 亿美元、112\n亿元）全现金交易收购 Osisko Mining Inc.，获得其 Windfall 项目（Windfall 是\n加拿大最大的金矿之一，也是全球十大金矿之一）的 50%权益（其他 50%权益在\nGold Fields 旗下）。根据 Osisko 于 2022 年 12 月开展的可行性研究，Windfall\n预计每年将生产约 300,000 盎司（9.3 吨）黄金，总维持成本（AISC）为 758 美\n元/盎司（2023 年实际值）。这使 Windfall 成为金田投资组合中成本最低的矿山\n之一，金田预计矿山将于 2026 年底或 2027 年底投产，目前预计矿山寿命为 10\n年。该交易需获得 Osisko 股东大会至少三分之二的投票批准，以及 Osisko 股东\n（不包括某些关联方）的简单多数票批准。两家公司的董事会均已批准并支持该交\n易，Osisko 董事建议股东投票支持该交易。\n本公司具备证券投资咨询业务资格，请务必阅读最后一页免责声明 证券研究报告 4",
      "tables": []
    },
    {
      "page_number": 5,
      "width": 595.32,
      "height": 841.92,
      "text": "行业深度研究/有色金属\n图1：金田黄金发展历史\n资料来源：公司公告，民生证券研究院\n金田黄金是 2023 年全球第七大黄金生产商。公司是一家全球多元化黄金生\n产商，注册地在南非，公司在澳大利亚、南非、加纳、智利和秘鲁拥有 10 座矿山。\n2023 年年总黄金当量产量为 230 万盎司（71.5 吨），拥有总黄金资源量为 8514.2\n万盎司（2648 吨），其中黄金储量（证实+可信）4465 万盎司（1388.7 吨），\n其中探明和控制金矿产资源量（不含矿石储量）为 3027.9 万盎司（941.8 吨），\n推断金矿产资源量为 1021.4 万盎司（318 吨）。\n图2：2023 年世界黄金生产商产量排行（单位：吨）\n资料来源：INN，民生证券研究院\n本公司具备证券投资咨询业务资格，请务必阅读最后一页免责声明 证券研究报告 5\n1FA 8i\nef\n8 7\nl d\nr i c\n1\nsa\n年\n成\n8\no\n8\n：f立\nS\n7\nG\no。\n1纳合T\nou\n9 9\n政同\na r k\nl d\nt h\n3府运w\n1\n年\na\n9\n签营\n：\n金\n9\n与\n署\n矿\n3\n管\n1南GGL\n加\n。\n9\neo\ni m\n理\n9\n非\nnl\n8黄c\ndi\nt\n1\n年\no\nF\ne\n9\n金ri\nd\n：\n合e。\n9\n公\nl d\n8\n公\n并\n司\ns\n司\n成\n与\n立\n2S 0t 0I\nv\n1e\n2\n年s\n0\n金\n0\n：\n矿\n1\n收\n。\n购\n2SMS协C矿矿收进 0 0\no ci\nn\n. A议\ne r\n床特购军\n3i\nee\n. 签，\nr o和许秘铜\n2S收D持N其\n2 0\n年 ：\nd a d\nr a C\n署购\nC o\n毗权鲁板\n0 0 6 年 1\no u t h D\n购 剩 余\ne e p 金 矿\n有 S o u\ne w s h e\n余 1 0 %\n0 3\n与\no r o n a\n了 最 终\n买\nr o n a\n邻 的 采\n。 本 次\n金 铜 矿 ，\n快 。\n2\ne5\nt h\nl f由\n月\ne p\n0 %\n。\nD\n是\n外\n1 日\n5 0 %\n股 权\n2 0 1\ne e p\n金 田\n部 股\n2 0 0\n：\n股\n，\n1 年金黄\n东\n6\n从\n权\n控，矿金\n持\n2 0\n芬铂\n巴\n。\n股N的的\n有\n0\n兰项\n里\n2\ne19\n2\n8的目\n克 黄\n0 0 7\nS o u\nw s h\n0 0 %\n0 % 子\n。\n0 0\n年 ：\n北 极\n。\n金\n年 4\nt h\ne l f\n权\n公\n8\n接 管\n钯\n收月\n成益\n司\n购\n立。\n，\n，\n2 0 1\n2南（市\n2从Y山SD\n2\n0\n0 1 3 年\n巴 里 克\ni l g a r n\n（ 包 括\nm i t h 、\na r l o t 矿\n2\n1 2 年 ：\n非 子 公\nS i b a n y\n。\n1 0黄\nS oG\nL a\n）\n0\n拆\n司e\n）\n1\n月 1\n金 收\nu t h\nr a n\nw l e\n。\n3\n分\n上\n日\n矿nr\n购\nys\n：\n和\n2\n2尝Y失\n0\n0\na\n2\n2\n试m败\n2\n2收a。 年\nn\n购a\n2与黄AA成\n5\n0\nns\n月\nG\n2\n全金\ngh立\no\n3 年\n球 第\n生 产\nl o G\na n t\n合 资\n2 0\n底 ：\nl d\n3\no\ni 在\n2\n月六公l\nd加\n公\n3\n：大司\n司\n纳\n2G已加元全OIW55F\n。\n0 2 4\no l d\n同 意\n元 （\n、 1\n现 金\ns i s k\nn c . ，\ni n d\n0 % 权\n0 % 权\ni e l d\n2\ns\n0\n年F\ni约1\n1 2交\no获f\na益益\n旗\n2 4\n8 月 ：\ne l d s 宣 布\n2 1 . 6 亿\n5 . 7 亿 美\n亿 元 ）\n易 收 购\nM i n i n g\n得 其\nl l 项 目 的\n（ 其 他\n在 G o l\n下 ） 。\nd\n200\n180\n160\n140\n120\n100\n80\n60\n40\n20\n0",
      "tables": []
    },
    {
      "page_number": 6,
      "width": 595.32,
      "height": 841.92,
      "text": "行业深度研究/有色金属\n图3：金田黄金资产布局图\n资料来源：金田黄金官网，民生证券研究院\n1.2 黄金贡献绝大多数利润，整体经营较稳健\n公司营收利润均随金价波动，2020 年金价大幅上涨后公司营收和净利润均有\n所抬升，后续整体平稳。营收方面， 2019-2023 年复合增速为 8.7%，2024 年上\n半年公司实现营收 21.2 亿美元，同比下降 6%。从营收结构上来看，公司主营业\n务收入来自黄金和铜，其中主要是黄金，占比达到 95%。归母净利润方面， 2019-\n2023 年复合增速为 34.2%，主要为 2019-2020 年的利润涨幅。2024 年上半年\n公司实现归母净利润 3.89 亿美元，同比减少 15%。\n图4：公司营收情况 图5：公司盈利情况\n营收（亿美元） 同比（%，右轴） 归母净利润（亿美元） 同比（%，右轴）\n50 40% 10 400%\n40 30% 8 300%\n30 20% 6 200%\n20 10% 4 100%\n10 0% 2 0%\n0 -10% 0 -100%\n2019 2020 2021 2022 2023 2024H1 2019 2020 2021 2022 2023 2024H1\n资料来源：ifind，民生证券研究院 资料来源：ifind，民生证券研究院\n本公司具备证券投资咨询业务资格，请务必阅读最后一页免责声明 证券研究报告 6",
      "tables": []
    },
    {
      "page_number": 7,
      "width": 595.32,
      "height": 841.92,
      "text": "行业深度研究/有色金属\n图7：公司营收结构中黄金是主要收入来源（单位：百万\n图6：黄金价格走势\n美元）（2023 年）\ncomex黄金价格（美元/盎司） 同比（%）-右轴\n2,500 30%\n25%\n2,000\n20%\n1,500\n15%\n1,000\n10%\n500\n5%\n0 0%\n2018 2019 2020 2021 2022 2023\n资料来源：ifind，民生证券研究院 资料来源：ifind，民生证券研究院\n毛利率和费用较稳定。公司毛利率整体较为稳定，2020 年以来有所下滑主要\n系成本上升所致，净利率方面整体走势跟毛利率类似。费用方面，随着金价高位，\n盈利改善，公司财务费用逐年下降，使得费用占比也逐步走低，销售、管理和其他\n费用整体维持稳定。\n图8：公司毛利率净利率情况 图9：公司三费情况\n资料来源：ifind，民生证券研究院 资料来源：ifind，民生证券研究院\n资产负债率稳定在 40%左右，资本开支近三年维持在 10 亿美金。公司资产\n负债率 19 年后逐步改善，近几年稳定在 40%左右。资本开支方面，2021 年明显\n抬升后维持稳定，一年资本性支出在 10 亿美元左右，每年的折旧摊销 8 亿美元左\n右，资本开支/折旧摊销维持在 1.25。\n本公司具备证券投资咨询业务资格，请务必阅读最后一页免责声明 证券研究报告 7\n2 0 8 ,\n4\n5\n2\n%\n9 3 , 9 5 %\n黄\n铜\n金\n毛利率（%） 净利率（%） 销售、管理和其他费用（亿美元）\n财务费用（亿美元）\n50%\n三费占比（右轴）\n4 15%\n40%\n3\n30%\n10%\n2\n20%\n5%\n1\n10%\n0% 0 0%\n2019 2020 2021 2022 2023 2024H1 2019 2020 2021 2022 2023",
      "tables": [
        [
          [
            "",
            ""
          ],
          [
            "",
            ""
          ]
        ],
        [
          [
            "",
            ""
          ],
          [
            "",
            ""
          ]
        ],
        [
          [
            "",
            ""
          ],
          [
            "",
            ""
          ]
        ],
        [
          [
            "",
            ""
          ],
          [
            "",
            ""
          ]
        ],
        [
          [
            "",
            ""
          ],
          [
            "",
            ""
          ]
        ]
      ]
    },
    {
      "page_number": 8,
      "width": 595.32,
      "height": 841.92,
      "text": "行业深度研究/有色金属\n图10：公司资本开支情况 图11：公司资产负债率\n资本性支出（亿美元） 同比（%，右轴） 资产负债率（%）\n12 100% 60%\n43%\n10 80%\n40%\n8 60%\n6 40% 20%\n4 20%\n0%\n2 0%\n0 -20%\n2019 2020 2021 2022 2023 2024H1\n资料来源：ifind，民生证券研究院 资料来源：ifind，民生证券研究院\n图12：公司折旧与摊销情况\n折旧摊销（亿美元) 同比（%）-右轴\n9 20%\n8\n15%\n7\n10%\n6\n5 5%\n4 0%\n3\n-5%\n2\n-10%\n1\n0 -15%\n2019 2020 2021 2022 2023\n资料来源：ifind，民生证券研究院\n本公司具备证券投资咨询业务资格，请务必阅读最后一页免责声明 证券研究报告 8",
      "tables": []
    },
    {
      "page_number": 9,
      "width": 595.32,
      "height": 841.92,
      "text": "行业深度研究/有色金属\n2 非洲起家，资源版图扩张至全球\n2.1 全球领先黄金巨头，资源禀赋优异\n从资源量来看，公司旗下共有 10 座矿山有资源量（含储量，9 座金矿，1 座\n铜矿），截至 2023 年底，公司的黄金权益资源量（探明+控制+推断，含储量）\n合计为 85.1 百万盎司（合计 2648.2 吨），平均品位为 3.14g/t，其中剔除推断的\n部分，仅保留探明+控制部分资源量和全部储量合计为 74.9 百万盎司（合计 2330.5\n吨），平均品位为 3.00g/t。铜权益资源量合计为 15.24 万吨，平均品位为 0.34%；\n白银权益资源量合计为 44.1 百万盎司（1371.9 吨），平均品位为 67.3g/t。\n从储量来看，公司旗下共有 9 座矿山有储量（8 座金矿，1 座铜矿），截至\n2023 年底，公司的黄金权益储量合计为 44.6 百万盎司（合计 1388.7 吨），平均\n品位为 2.86g/t，铜权益储量合计为 15.24 万吨，平均品位为 0.34%，白银权益储\n量合计为 41.9 盎司（1304.5 吨），平均品位为 71.9g/t。\n表1：截至 2023 年末，公司储量和资源量情况汇总\n权益储量（证实+可信） 权益资源量（探明+控制，含储量） 权益资源量（探明+控制+推断，含储量）\n品种\n矿石量（百万吨） 品位 金属量 矿石量（百万吨） 品位 金属量 矿石量（百万吨） 品位 金属量\n金 486.3 2.86 1388.7 778.1 3.00 2330.5 843.4 3.14 2648.2\n铜 45.4 0.34 15.24 45.4 0.34 15.24 45.4 0.34 15.24\n银 18.1 71.9 1304.5 20.4 67.3 1371.9 20.6 66.73 1374.6\n资料来源：公司公告，民生证券研究院\n注：品位的单位：铜为%，黄金和白银为 g/t。金属量的单位：铜为万吨，黄金和白银为吨。\n表2：储量和资源量价格假设\n储量价格假设 资源量价格假设\n品种\n2022 2023 2022 2023\n金 $1,400/oz $1,400/oz $1,600/oz $1,600/oz\n铜 $3.40/lb $3.40/lb $3.60/lb $3.60/lb\n银 $17.50/oz $17.50/oz $20.00/oz $20.00/oz\n资料来源：公司公告，民生证券研究院\n黄金板块储量细分来看，澳大利亚地区、非洲地区、美洲地区分别有 4、3、\n2 座矿山，黄金权益储量分别为 7.7、32.8、4.2 百万盎司（239.6、1019.6、129.5\n吨），占比分别为 17.3%、73.4%、9.3%。分矿山来看，公司体内前 5 大矿山分\n别为 South Deep、Tarkwa、Salares Norte、St lves、Granny Smith，储量占比\n分别为 63.3%、9.7%、7.7%、5.8%、5.4%，合计为 91.8%\n本公司具备证券投资咨询业务资格，请务必阅读最后一页免责声明 证券研究报告 9",
      "tables": [
        [
          [
            "品种",
            "",
            "权益储量（证实+可信）",
            "",
            "",
            "",
            "",
            "",
            "",
            "",
            "",
            "权益资源量（探明+控制，含储量）",
            "",
            "",
            "",
            "",
            "",
            "",
            "",
            "",
            "权益资源量（探明+控制+推断，含储量）",
            "",
            "",
            "",
            "",
            "",
            "",
            ""
          ],
          [
            "",
            "",
            "矿石量（百万吨）",
            "",
            "",
            "品位",
            "",
            "",
            "金属量",
            "",
            "",
            "矿石量（百万吨）",
            "",
            "",
            "品位",
            "",
            "",
            "金属量",
            "",
            "",
            "矿石量（百万吨）",
            "",
            "",
            "品位",
            "",
            "",
            "金属量",
            ""
          ]
        ],
        [
          [
            "",
            "铜",
            "",
            "",
            "45.4",
            "",
            "",
            "0.34",
            "",
            "",
            "15.24",
            "",
            "",
            "45.4",
            "",
            "",
            "0.34",
            "",
            "",
            "15.24",
            "",
            "",
            "45.4",
            "",
            "",
            "0.34",
            "",
            "",
            "15.24",
            ""
          ]
        ],
        [
          [
            "品种",
            "",
            "储量价格假设",
            "",
            "",
            "",
            "",
            "",
            "资源量价格假设",
            "",
            "",
            "",
            ""
          ],
          [
            "",
            "",
            "2022",
            "",
            "",
            "2023",
            "",
            "",
            "2022",
            "",
            "",
            "2023",
            ""
          ]
        ],
        [
          [
            "",
            "铜",
            "",
            "",
            "$3.40/lb",
            "",
            "",
            "$3.40/lb",
            "",
            "",
            "$3.60/lb",
            "",
            "",
            "$3.60/lb",
            ""
          ]
        ]
      ]
    },
    {
      "page_number": 10,
      "width": 595.32,
      "height": 841.92,
      "text": "行业深度研究/有色金属\n表3：截至 2023 年底，公司的黄金权益储量合计为 4464.9 万盎司（1388.7 吨）\n证实储量 可信储量 合计\n项目 矿石量 品位 金属量 矿石量 品位 金属量 矿石量 品位 金属量\n百万吨 g/t 万盎司 百万吨 g/t 万盎司 百万吨 g/t 万盎司\n澳大利亚地区\nOpen pit,Gruyere 7.35 1.2 28.6 35.52 1.3 148.2 42.87 1.3 176.8\nStockpile,Gruyere 2.77 0.7 6.3 - - - 2.77 0.7 6.3\nTotal Gruyere(50%)（1） 10.13 1.1 35 35.52 1.3 148.2 45.65 1.2 183.2\nUnderground,GrannySmith 1.49 5.7 27.1 10.46 6.3 211.6 11.95 6.2 238.6\nStockpile,GrannySmith 0.02 5.7 0.4 - - - 0.02 5.7 0.4\nTotal GrannySmith（100%） 1.51 5.7 27.5 10.46 6.3 211.6 11.97 6.2 239\nUnderground,St lves 1.64 4.6 24.1 15.49 4.0 196.8 17.13 4.0 220.9\nOpen pit,St lves 0.26 3.8 3.2 3.97 2.1 27.2 4.23 2.2 30.4\nStockpile,St lves 2.75 1.1 9.7 - - - 2.75 1.1 9.7\nTotal St lves（100%） 4.65 2.5 3.7 19.46 3.6 223.9 24.10 3.4 261\nUnderground,Agnew - - - 3.86 6.9 85.5 3.86 6.9 85.5\nOpen pit,Agnew - - - 0.09 3.4 1 0.09 3.4 1\nStockpile,Agnew 0.03 7.7 0.7 - - - 0.03 7.7 0.7\nTotal Agnew（100%） 0.03 7.7 0.7 3.95 6.8 86.5 3.98 6.8 87.2\n澳大利亚地区合计 16.31 - 100.2 69.39 - 670.2 85.70 2.8 770.4\n非洲地区\nSouth Deep(90.331%)（2） 9.26 5.8 172.3 168.91 4.9 2651.6 178.17 4.9 2823.9\nDamang(90%)（3） 7.26 0.8 19.4 - - - 7.26 0.8 19.4\nOpen pits, Tarkwa 26.94 1.3 108.7 58.78 1.2 337 85.72 1.2 337\nStockpiles, Tarkwa 11.95 0.7 28.4 53.96 0.4 69.4 65.92 0.5 97.8\nTotal Tarkwa (90%)（4） 38.89 1.1 137.1 112.75 0.8 297.6 151.63 0.9 434.8\n非洲地区合计 55.41 - 328.8 281.66 - 2949.2 337.06 - 3278.1\n美洲地区\nOpen pit,Salares Norte - - - 15.88 5.6 285.9 15.88 5.6 285.9\nStockpile,Salares Norte - - - 2.26 7.7 55.7 2.26 7.7 55.7\nTotal Salares Norte（100%） - - - 18.14 5.9 341.6 18.14 5.9 341.6\nOpen pit,Cerro Corona 23.80 0.5 40.6 2.06 0.5 3.4 25.86 0.5 44.1\nStockpile,Cerro Corona 19.58 0.5 30.8 - - - 19.58 0.5 30.8\nTotal Cerro Corona（99.53%）（5） 43.39 0.5 71.5 2.06 0.5 3.4 45.44 0.5 74.9\n美洲地区合计 43.39 0.5 71.5 20.19 - 345 63.58 2.04 416.5\n全公司共计 115.10 1.4 500.5 371.24 3.3 3964.4 486.34 2.86 4464.9\n资料来源：公司公告，民生证劵研究院\n注：各矿山均为权益量，且资源量不包含储量。\n（1）Gruyere 由金田公司持有 50%，金路资源持有 50%。\n（2）South Deep 由金田公司持有 90.331%，South Deep Education 和 South Deep Community Trusts 持有剩余部分。\n（3）Damang 由金田持有 90%，加纳政府持有 10%。\n（4）Tarkwa 由金田持有 90%，加纳政府持有 10%。\n（5）Cerro Corona 由金田持有 99.53%，剩下部分由私人持有。\n本公司具备证券投资咨询业务资格，请务必阅读最后一页免责声明 证券研究报告 10",
      "tables": [
        [
          [
            "项目",
            "",
            "证实储量",
            "",
            "",
            "",
            "",
            "",
            "",
            "",
            "",
            "可信储量",
            "",
            "",
            "",
            "",
            "",
            "",
            "",
            "",
            "合计",
            "",
            "",
            "",
            "",
            "",
            "",
            ""
          ],
          [
            "",
            "",
            "矿石量",
            "",
            "",
            "品位",
            "",
            "",
            "金属量",
            "",
            "",
            "矿石量",
            "",
            "",
            "品位",
            "",
            "",
            "金属量",
            "",
            "",
            "矿石量",
            "",
            "",
            "品位",
            "",
            "",
            "金属量",
            ""
          ],
          [
            "",
            "",
            "百万吨",
            "",
            "",
            "g/t",
            "",
            "",
            "万盎司",
            "",
            "",
            "百万吨",
            "",
            "",
            "g/t",
            "",
            "",
            "万盎司",
            "",
            "",
            "百万吨",
            "",
            "",
            "g/t",
            "",
            "",
            "万盎司",
            ""
          ]
        ],
        [
          [
            "",
            "澳大利亚地区合计",
            "",
            "",
            "16.31",
            "",
            "",
            "-",
            "",
            "",
            "100.2",
            "",
            "",
            "69.39",
            "",
            "",
            "-",
            "",
            "",
            "670.2",
            "",
            "",
            "85.70",
            "",
            "",
            "2.8",
            "",
            "",
            "770.4",
            ""
          ]
        ],
        [
          [
            "",
            "非洲地区合计",
            "",
            "",
            "55.41",
            "",
            "",
            "-",
            "",
            "",
            "328.8",
            "",
            "",
            "281.66",
            "",
            "",
            "-",
            "",
            "",
            "2949.2",
            "",
            "",
            "337.06",
            "",
            "",
            "-",
            "",
            "",
            "3278.1",
            ""
          ]
        ],
        [
          [
            "",
            "美洲地区合计",
            "",
            "",
            "43.39",
            "",
            "",
            "0.5",
            "",
            "",
            "71.5",
            "",
            "",
            "20.19",
            "",
            "",
            "-",
            "",
            "",
            "345",
            "",
            "",
            "63.58",
            "",
            "",
            "2.04",
            "",
            "",
            "416.5",
            ""
          ],
          [
            "",
            "全公司共计",
            "",
            "",
            "115.10",
            "",
            "",
            "1.4",
            "",
            "",
            "500.5",
            "",
            "",
            "371.24",
            "",
            "",
            "3.3",
            "",
            "",
            "3964.4",
            "",
            "",
            "486.34",
            "",
            "",
            "2.86",
            "",
            "",
            "4464.9",
            ""
          ]
        ]
      ]
    },
    {
      "page_number": 11,
      "width": 595.32,
      "height": 841.92,
      "text": "行业深度研究/有色金属\n铜板块储量来看，全部来自秘鲁的 Cerro Corona 矿山，2023 年底，公司权\n益储量为336百万磅，合计15.241吨。白银板块储量来看，全部来自智利的Salares\nNort 矿山，2023 年底，公司权益量为 41.941 百万盎司，合计 1304.5 吨。\n表4：截至 2023 年底，公司的铜与白银权益储量分别为 336 百万磅（15.24 万吨）和 41.9 百万盎司（1304.5 吨）\n证实储量 可信储量 合计\n项目 矿石量 品位 金属量 矿石量 品位 金属量 矿石量 品位 金属量\n百万吨 百万吨 百万吨\nOpen pit Cerro Corona 23.80 0.36 8.6 2.51 0.36 0.7 25.86 0.36 9.3\nStockpile Cerro Corona 19.58 0.3 5.9 - - - 19.58 0.3 5.9\nTotal Cerro Corona （99.53%）（1） 43.39 0.33 14.5 2.06 0.35 0.7 45.44 0.34 15.2\n铜合计 43.39 0.33 14.5 2.06 0.35 0.7 45.44 0.34 15.2\nOpen pit,Salares Nort - - - 15.88 71.7 36.6 15.88 71.7 36.6\nStockpile,Salares Nort - - - 2.26 73.4 5.3 2.26 73.4 5.3\nTotal Salares Nort（100%） - - - 18.14 71.9 41.9 18.14 71.9 41.9\n白银合计 - - - 18.14 71.9 41.9 18.14 71.9 41.9\n资料来源：公司公告，民生证劵研究院\n注：各矿山均为权益量，品位的单位：铜为%，白银为 g/t。金属量的单位：铜为万吨，白银为百万盎司。\n（1）Cerro Corona 由金田持有 99.53%，剩下部分由私人持有。\n黄金板块资源量（探明+控制）细分来看，澳大利亚地区、非洲地区、美洲地\n区分别有 4、3、1 座矿山，黄金权益资源量分别为 4.71、25.4、0.17 百万盎司\n（146.5、790、5.3 吨），占比分别为 15.6%、83.9%、0.56%。分矿山来看，公\n司体内黄金资源量前 5 大矿山分别为 South Deep、Tarkwa、GrannySmith、\nDamang、St lves，资源量占比分别为 66%、11.2 %、7.5%、6.7%、3.3%，合\n计为 94.7%。由于 Cerro Corona 矿内尾矿放置的限制，2023 年没有铜资源量声\n明，此处的资源量不含储量。\n表5：截至 2023 年底，公司的黄金权益资源量合计为 3027.9 万盎司（941.8 吨）\n探明的 控制的 探明+控制的\n项目 国家 矿石量 品位 金属量 矿石量 品位 金属量 矿石量 品位 金属量\n百万吨 g/t 万盎司 百万吨 g/t 万盎司 百万吨 g/t 万盎司\n澳大利亚地区\nOpen pit,Gruyere 0.05 1 0.2 12.06 1.4 53.1 12.11 1.4 53.3\nTotal Gruyere(50%) 0.05 1 0.2 12.06 1.4 53.1 12.11 1.4 53.3\nUnderground,GrannySmith 2.16 5.2 35.9 13.16 4.6 192.5 15.32 4.6 228.4\nTotal GrannySmith（100%） 2.16 5.2 35.9 13.16 4.6 192.5 15.32 4.6 228.4\nUnderground,St lves 澳大利亚 0.13 4.4 1.8 4.98 4.1 65.8 5.10 4.1 67.6\nOpen pit,St lves 0.48 2.8 4.4 3.17 2.7 27.5 3.65 2.7 31.8\nTotal St lves（100%） 0.61 3.1 6.1 8.15 3.6 93.2 8.76 3.5 99.4\nUnderground,Agnew 0.09 5.5 1.7 4.87 5.0 77.7 4.97 5.0 79.4\nOpen pit,Agnew - - - 1.31 2.5 10.5 1.31 2.5 10.5\nTotal Agnew（100%） 0.09 5.5 1.7 6.18 4.4 88.3 6.28 4.5 89.9\n本公司具备证券投资咨询业务资格，请务必阅读最后一页免责声明 证券研究报告 11",
      "tables": [
        [
          [
            "项目",
            "",
            "证实储量",
            "",
            "",
            "",
            "",
            "",
            "",
            "",
            "",
            "可信储量",
            "",
            "",
            "",
            "",
            "",
            "",
            "",
            "",
            "合计",
            "",
            "",
            "",
            "",
            "",
            "",
            ""
          ],
          [
            "",
            "",
            "矿石量",
            "",
            "",
            "品位",
            "",
            "",
            "金属量",
            "",
            "",
            "矿石量",
            "",
            "",
            "品位",
            "",
            "",
            "金属量",
            "",
            "",
            "矿石量",
            "",
            "",
            "品位",
            "",
            "",
            "金属量",
            ""
          ],
          [
            "",
            "",
            "百万吨",
            "",
            "",
            "",
            "",
            "",
            "",
            "",
            "",
            "百万吨",
            "",
            "",
            "",
            "",
            "",
            "",
            "",
            "",
            "百万吨",
            "",
            "",
            "",
            "",
            "",
            "",
            ""
          ]
        ],
        [
          [
            "",
            "Total Cerro Corona （99.53%）（1）",
            "",
            "43.39",
            "",
            "",
            "0.33",
            "",
            "",
            "14.5",
            "",
            "",
            "2.06",
            "",
            "",
            "0.35",
            "",
            "",
            "0.7",
            "",
            "",
            "45.44",
            "",
            "",
            "0.34",
            "",
            "",
            "15.2",
            ""
          ],
          [
            "",
            "铜合计",
            "",
            "43.39",
            "",
            "",
            "0.33",
            "",
            "",
            "14.5",
            "",
            "",
            "2.06",
            "",
            "",
            "0.35",
            "",
            "",
            "0.7",
            "",
            "",
            "45.44",
            "",
            "",
            "0.34",
            "",
            "",
            "15.2",
            ""
          ]
        ],
        [
          [
            "",
            "Total Salares Nort（100%）",
            "",
            "-",
            "",
            "",
            "-",
            "",
            "",
            "-",
            "",
            "",
            "18.14",
            "",
            "",
            "71.9",
            "",
            "",
            "41.9",
            "",
            "",
            "18.14",
            "",
            "",
            "71.9",
            "",
            "",
            "41.9",
            ""
          ],
          [
            "",
            "白银合计",
            "",
            "-",
            "",
            "",
            "-",
            "",
            "",
            "-",
            "",
            "",
            "18.14",
            "",
            "",
            "71.9",
            "",
            "",
            "41.9",
            "",
            "",
            "18.14",
            "",
            "",
            "71.9",
            "",
            "",
            "41.9",
            ""
          ]
        ],
        [
          [
            "项目",
            "国家",
            "",
            "探明的",
            "",
            "",
            "",
            "",
            "",
            "",
            "",
            "",
            "控制的",
            "",
            "",
            "",
            "",
            "",
            "",
            "",
            "",
            "探明+控制的",
            "",
            "",
            "",
            "",
            "",
            "",
            ""
          ],
          [
            "",
            "",
            "",
            "矿石量",
            "",
            "",
            "品位",
            "",
            "",
            "金属量",
            "",
            "",
            "矿石量",
            "",
            "",
            "品位",
            "",
            "",
            "金属量",
            "",
            "",
            "矿石量",
            "",
            "",
            "品位",
            "",
            "",
            "金属量",
            ""
          ],
          [
            "",
            "",
            "",
            "百万吨",
            "",
            "",
            "g/t",
            "",
            "",
            "万盎司",
            "",
            "",
            "百万吨",
            "",
            "",
            "g/t",
            "",
            "",
            "万盎司",
            "",
            "",
            "百万吨",
            "",
            "",
            "g/t",
            "",
            "",
            "万盎司",
            ""
          ]
        ]
      ]
    },
    {
      "page_number": 12,
      "width": 595.32,
      "height": 841.92,
      "text": "行业深度研究/有色金属\n澳大利亚 地区合计 2.91 - 43.9 39.55 - 427.1 42.46 - 471\n非洲地区\nUnderground,South Deep 14.93 6.5 314.1 78.37 6.6 1652.8 93.30 6.6 1966.9\nSurface Mineral Resource(TSF),South Deep 南非 42.61 0.2 31 - - - 42.61 0.2 31\nTotal South Deep(90.331%) 57.54 1.9 345.1 78.37 6.6 1652.8 135.91 4.6 1998\nOpen pit,Damang 4.95 1.7 26.6 27.78 2.0 175.3 32.72 1.9 201.9\nTotal Damang(90%) 4.95 1.7 26.6 27.78 2.0 175.3 32.72 1.9 201.9\nOpen pits, Tarkwa 加纳 10.76 1.5 51.5 67.62 1.3 288.3 78.38 1.3 339.9\nStockpiles, Tarkwa 0.08 0.3 0.09 - - - 0.08 0.3 0.09\nTotal Tarkwa (90%) 10.84 1.5 51.6 67.62 1.3 288.3 78.46 1.3 340\n非洲地区合计 73.33 - 423.3 173.77 - 2116.4 247.09 - 2539.9\n美洲地区\nTotal Salares Norte（100%） 智利 - - - 2.29 2.3 17 2.29 2.3 17\n美洲地区合计 - - - 2.29 2.3 17 2.29 2.3 17\n全公司共计 76.24 1.91 467.2 215.61 3.7 2560.5 291.84 3.23 3027.9\n资料来源：公司公告，民生证劵研究院\n注：各矿山均为权益量，且资源量不包含储量。\n白银板块资源量（探明+控制）来看，全部来自智利的 Salares Norte 矿，且\n该矿山为金银矿。\n表6：截至 2023 年底，公司的白银权益资源量合计为 216.8 万盎司（67.4 吨）\n探明的 控制的 探明+控制的\n项目 国家 矿石量 品位 金属量 矿石量 品位 金属量 矿石量 品位 金属量\n万吨 g/t 万盎司 万吨 g/t 万盎司 万吨 g/t 万盎司\nSalares Norte 智利 - - - 229.4 29.4 216.8 229.4 29.4 216.8\n全公司合计 - - - 229.4 29.4 216.8 229.4 29.4 216.8\n资料来源：公司公告，民生证劵研究院\n注：各矿山均为权益量，且资源量不包含储量。\n2.2 产量：近几年公司黄金产量上下波动\n公司进入成熟发展阶段，黄金产量近几年上下波动，铜产量维持相对稳定。从\n黄金产量来看，2018-2023 年公司黄金权益产量从 63.5 吨提升至 71.5 吨，CAGR\n为 2.4%。2023 年公司共生产 71.5 吨黄金（权益量），同比减少 4.1%，2018 年\n-2022 年公司黄金权益产量持续增加，主要是因为 South Deep 资本投入的增加，\n2023 年黄金产量的下降，主要是因为 Damang 矿山寿命的临近。从铜权益产量\n来看，2023 年公司共生产 2.67 万吨，同比减少 1.1%。从 2020 年以来，公司铜\n权益产量总体维持在 2.6 万吨左右。\n本公司具备证券投资咨询业务资格，请务必阅读最后一页免责声明 证券研究报告 12",
      "tables": [
        [
          [
            "",
            "澳大利亚 地区合计",
            "",
            "",
            "",
            "",
            "2.91",
            "",
            "",
            "-",
            "",
            "",
            "43.9",
            "",
            "",
            "39.55",
            "",
            "",
            "-",
            "",
            "",
            "427.1",
            "",
            "",
            "42.46",
            "",
            "",
            "-",
            "",
            "",
            "471",
            ""
          ]
        ],
        [
          [
            "",
            "非洲地区合计",
            "",
            "",
            "",
            "",
            "73.33",
            "",
            "",
            "-",
            "",
            "",
            "423.3",
            "",
            "",
            "173.77",
            "",
            "",
            "-",
            "",
            "",
            "2116.4",
            "",
            "",
            "247.09",
            "",
            "",
            "-",
            "",
            "",
            "2539.9",
            ""
          ]
        ],
        [
          [
            "",
            "美洲地区合计",
            "",
            "",
            "",
            "",
            "-",
            "",
            "",
            "-",
            "",
            "",
            "-",
            "",
            "",
            "2.29",
            "",
            "",
            "2.3",
            "",
            "",
            "17",
            "",
            "",
            "2.29",
            "",
            "",
            "2.3",
            "",
            "",
            "17",
            ""
          ],
          [
            "",
            "全公司共计",
            "",
            "",
            "",
            "",
            "76.24",
            "",
            "",
            "1.91",
            "",
            "",
            "467.2",
            "",
            "",
            "215.61",
            "",
            "",
            "3.7",
            "",
            "",
            "2560.5",
            "",
            "",
            "291.84",
            "",
            "",
            "3.23",
            "",
            "",
            "3027.9",
            ""
          ]
        ],
        [
          [
            "项目",
            "国家",
            "",
            "探明的",
            "",
            "",
            "",
            "",
            "",
            "",
            "",
            "控制的",
            "",
            "",
            "",
            "",
            "",
            "",
            "",
            "",
            "探明+控制的",
            "",
            "",
            "",
            "",
            "",
            "",
            ""
          ],
          [
            "",
            "",
            "",
            "矿石量",
            "",
            "",
            "品位",
            "",
            "金属量",
            "",
            "",
            "矿石量",
            "",
            "",
            "品位",
            "",
            "",
            "金属量",
            "",
            "",
            "矿石量",
            "",
            "",
            "品位",
            "",
            "",
            "金属量",
            ""
          ],
          [
            "",
            "",
            "",
            "万吨",
            "",
            "",
            "g/t",
            "",
            "万盎司",
            "",
            "",
            "万吨",
            "",
            "",
            "g/t",
            "",
            "",
            "万盎司",
            "",
            "",
            "万吨",
            "",
            "",
            "g/t",
            "",
            "",
            "万盎司",
            ""
          ]
        ],
        [
          [
            "",
            "全公司合计",
            "",
            "",
            "",
            "",
            "",
            "-",
            "",
            "",
            "-",
            "",
            "-",
            "",
            "",
            "229.4",
            "",
            "",
            "29.4",
            "",
            "",
            "216.8",
            "",
            "",
            "229.4",
            "",
            "",
            "29.4",
            "",
            "",
            "216.8",
            ""
          ]
        ]
      ]
    },
    {
      "page_number": 13,
      "width": 595.32,
      "height": 841.92,
      "text": "行业深度研究/有色金属\n图13：近几年公司黄金权益产量上下波动 图14：近几年公司铜权益产量维持 2.5 万吨左右\n铜权益产量（万吨）\n4 10%\n黄金权益产量（吨） 增速（%）-右轴 增速（%）-右轴\n76 10%\n74 5%\n72 3\n5%\n70 0%\n68\n66 0% 2 -5%\n64\n62 -10%\n-5% 1\n60\n-15%\n58\n56 -10%\n0 -20%\n2018 2019 2020 2021 2022 2023\n2018 2019 2020 2021 2022 2023\n资料来源：公司公告，民生证券研究院 资料来源：公司公告，民生证券研究院\n表7：2018-2023 年公司细分矿山的黄金产量\n黄金产量（吨） 2018 2019 2020 2021 2022 2023\nGruyere(50%) 0.00 1.56 4.01 3.83 4.88 5.01\nGranny Smith 8.71 8.55 8.40 8.68 8.96 8.83\nSt lves 11.41 11.54 11.97 12.22 11.73 11.57\nAgnew 7.43 6.81 7.25 6.94 7.43 7.46\nSouth Deep 4.88 6.90 7.06 9.11 10.20 10.02\nDamang 5.63 6.47 6.94 7.90 7.15 4.76\nTarkwa 16.33 16.14 16.36 16.24 16.55 17.14\nAsanko(45%) 1.40 3.51 3.48 2.95 2.39 1.87\nCerro Corona 4.67 4.85 3.70 3.51 4.01 3.79\n金田黄金共计 60.47 66.34 69.17 71.38 73.31 70.45\n资料来源：公司公告，民生证劵研究院\n注：各矿山均为权益量\n2.3 成本：公司铜金成本近几年持续上行\n公司铜金成本近几年持续上行。黄金板块，公司全维持成本（AISC,现金成本\n加上矿山维护，环境修复等持续性资本开支，即满足当期开采+维持矿山持续运营\n的费用）从 2018 年的 981 美元/盎司上升至 2023 年 1295 美元/盎司，主要或由\n于金价上涨后矿石入选品位有所下降。铜金属板块，2020-2022 年由于产量持续\n增长，铜产品的折算黄金价值的总投入成本下滑。但是 2022 年开始，公司总投入\n成本（AIC，全维持成本+增加企业远期扩产所需的费用，即满足当期开采+维持矿\n山持续运营+远期进一步扩产的费用）从 998 美元/盎司上涨至 2023 年的 1146\n美元/盎司。\n2022 年公司黄金产量上升，同时全维持成本也在增加，主要是由于澳大利亚\n与南非政府宽松货币政策以及 Salares Norte 地区资本支出的推迟。但 South\n本公司具备证券投资咨询业务资格，请务必阅读最后一页免责声明 证券研究报告 13",
      "tables": [
        [
          [
            "",
            "黄金产量（吨）",
            "",
            "",
            "2018",
            "",
            "",
            "2019",
            "",
            "",
            "2020",
            "",
            "2021",
            "",
            "",
            "2022",
            "",
            "",
            "2023",
            ""
          ]
        ],
        [
          [
            "",
            "Granny Smith",
            "",
            "",
            "8.71",
            "",
            "",
            "8.55",
            "",
            "",
            "8.40",
            "",
            "8.68",
            "",
            "",
            "8.96",
            "",
            "",
            "8.83",
            ""
          ]
        ],
        [
          [
            "",
            "Agnew",
            "",
            "",
            "7.43",
            "",
            "",
            "6.81",
            "",
            "",
            "7.25",
            "",
            "6.94",
            "",
            "",
            "7.43",
            "",
            "",
            "7.46",
            ""
          ]
        ],
        [
          [
            "",
            "Damang",
            "",
            "",
            "5.63",
            "",
            "",
            "6.47",
            "",
            "",
            "6.94",
            "",
            "7.90",
            "",
            "",
            "7.15",
            "",
            "",
            "4.76",
            ""
          ]
        ],
        [
          [
            "",
            "Asanko(45%)",
            "",
            "",
            "1.40",
            "",
            "",
            "3.51",
            "",
            "",
            "3.48",
            "",
            "2.95",
            "",
            "",
            "2.39",
            "",
            "",
            "1.87",
            ""
          ]
        ]
      ]
    },
    {
      "page_number": 14,
      "width": 595.32,
      "height": 841.92,
      "text": "行业深度研究/有色金属\nDeep 由于开采技术的改进与管理效率的提高，入选品位提升，产量增长明显，成\n本有所下降。\n图15：20 年以来公司黄金成本持续上行 图16：22 年以来公司黄金当量的铜全成本持续上行\n1600 全部成本（AIC）（美元/盎司）\n1200 黄金当量-全部成本（美元/盎司）\n全维持成本（AISC）（美元/盎司）\n1400\n1000\n1200\n1000 800\n800\n600\n600 2018 2019 2020 2021 2022 2023\n2018 2019 2020 2021 2022 2023\n资料来源：公司公告，民生证券研究院 资料来源：公司公告，民生证券研究院\n表8：2018-2023 年公司细分矿山的黄金总投入成本\n黄金全部成本（AIC）（美元/盎司） 2018 2019 2020 2021 2022 2023\nGruyere(50%) 2900 931 1158 991 1190\nGranny Smith 925 922 1010 1161 1171 1196\nSt lves 902 963 873 1040 1104 1301\nAgnew 1026 1152 1053 1308 1298 1288\nSouth Deep 2012 1259 1260 1379 1356 1349\nDamang 1506 1147 1035 852 1083 1679\nTarkwa 951 958 1017 1155 1248 1293\nAsanko(45%) 1175 1214 1316 1559 1435 1672\nCerro Corona 282 472 715 230 444 536\n金田黄金共计 1173 1064 1079 1297 1320 1512\n资料来源：公司公告，民生证劵研究院\n2.4 分矿山来看，公司旗下拥有较多优质资产\n2.4.1 非洲地区：核心资产为加纳的 Tarkwa 金矿和南非的 South\nDeep 金矿\n2023 年公司在非洲地区的黄金权益产量占了全公司黄金权益产量的\n47.9%。主要来自于位于加纳的 Tarkwa 金矿（占比 24.3%，公司持股 90%，\n其余 10%股权由加纳政府持有）和位于南非的 South Deep 金矿（占比 14.2%，\n公司持股 90.331%，其余 9.669%股权由 South Deep Education 和 South\nDeep Community Trusts，两者为金田公司（Gold Fields）为支持社区发展\n和教育而设立的信托基金。此外还有一座位于加纳的 Asanko 金矿，在 2024\n年 3 月金田出售其 45%股份给合资伙伴 Galiano Gold。\n本公司具备证券投资咨询业务资格，请务必阅读最后一页免责声明 证券研究报告 14",
      "tables": [
        [
          [
            "",
            "黄金全部成本（AIC）（美元/盎司）",
            "",
            "",
            "2018",
            "",
            "",
            "2019",
            "",
            "",
            "2020",
            "",
            "",
            "2021",
            "",
            "",
            "2022",
            "",
            "",
            "2023",
            ""
          ]
        ],
        [
          [
            "",
            "Granny Smith",
            "",
            "",
            "925",
            "",
            "",
            "922",
            "",
            "",
            "1010",
            "",
            "",
            "1161",
            "",
            "",
            "1171",
            "",
            "",
            "1196",
            ""
          ]
        ],
        [
          [
            "",
            "Agnew",
            "",
            "",
            "1026",
            "",
            "",
            "1152",
            "",
            "",
            "1053",
            "",
            "",
            "1308",
            "",
            "",
            "1298",
            "",
            "",
            "1288",
            ""
          ]
        ],
        [
          [
            "",
            "Damang",
            "",
            "",
            "1506",
            "",
            "",
            "1147",
            "",
            "",
            "1035",
            "",
            "",
            "852",
            "",
            "",
            "1083",
            "",
            "",
            "1679",
            ""
          ]
        ],
        [
          [
            "",
            "Asanko(45%)",
            "",
            "",
            "1175",
            "",
            "",
            "1214",
            "",
            "",
            "1316",
            "",
            "",
            "1559",
            "",
            "",
            "1435",
            "",
            "",
            "1672",
            ""
          ]
        ]
      ]
    },
    {
      "page_number": 15,
      "width": 595.32,
      "height": 841.92,
      "text": "行业深度研究/有色金属\n此外，公司在非洲地区还拥有以下重要资产：\nDamang：位于加纳，公司持股 90%，当地政府持股 10%。\n图17：公司在加纳地区布局\n资料来源：公司公告，民生证券研究院\n加纳的 Tarkwa 金矿是非洲地区的一流黄金资产（Tier One gold mines），\n是一座由金田主导生产的露天矿，公司持股 90%，剩余 10%股份由当地政府持有。\n产量端，该矿山近几年回收率基本不变、入选品位略有抬升，因此黄金产量 21-23\n年逐步增加，2023 年黄金产量较上年增加 3.7%。成本端，尽管黄金产量小幅度\n增加，但由于原辅料、能源等成本增加，公司的 AIC 逐年增加，由于 2022 和 2023\n年的产量增长，成本增速减缓。\n本公司具备证券投资咨询业务资格，请务必阅读最后一页免责声明 证券研究报告 15",
      "tables": []
    },
    {
      "page_number": 16,
      "width": 595.32,
      "height": 841.92,
      "text": "行业深度研究/有色金属\n图18：Tarkwa 金矿 2018-2023 年黄金权益产量（单 图19：Tarkwa 金矿 2018-2023 年黄金总投入成本（单\n位：吨） 位：美元/盎司）\n黄金权益产量（吨）\n总投入成本（美元/盎司）\n17.5 增长率---右轴(%) 4% 1400 15%\n增长率---右轴(%)\n3% 1200\n17\n2% 1000\n10%\n16.5 1% 800\n16 0% 600\n5%\n-1% 400\n15.5 -2% 200\n0 0%\n15 -3%\n2018 2019 2020 2021 2022 2023\n2018 2019 2020 2021 2022 2023\n资料来源：公司公告，民生证券研究院 资料来源：公司公告，民生证券研究院\n图20：Tarkwa 金矿近几年入选品位增长明显\n入选品位（g/t） 回收率\n1.22 100.0%\n1.2\n99.0%\n1.18\n98.0%\n1.16\n97.0%\n1.14\n96.0%\n1.12\n1.1 95.0%\n2018 2019 2020 2021 2022 2023\n资料来源：公司公告，民生证券研究院\n本公司具备证券投资咨询业务资格，请务必阅读最后一页免责声明 证券研究报告 16",
      "tables": []
    },
    {
      "page_number": 17,
      "width": 595.32,
      "height": 841.92,
      "text": "行业深度研究/有色金属\n图21：公司在南非地区布局\n资料来源：公司公告，民生证券研究院\n注：2023 年数据\n南非的 South Deep 是非洲地区的一流黄金资产（Tier One gold mines）。\n是一座由金田主导生产的地下金矿，公司持股 90.331%，剩余 9.669%股权由\nSouth Deep Education 和 South Deep Community Trusts，金田公司（Gold\nFields）为支持社区发展和教育而设立的信托基金。产量端，2020-2022 年，尽\n管回收率在下降，但该矿山受入选品位上升等因素影响，黄金产量逐渐增加，2023\n年相比 2022 年，回收率有所增加，但受到入选品位下降以及地下珊瑚礁产量较低\n等因素的影响，产量下降 1.8%。成本端，2021 年以来，该矿山的成本基本不变，\n主要是因为通货膨胀抵消了增长的产量与销量带来的成本下降的影响。\n本公司具备证券投资咨询业务资格，请务必阅读最后一页免责声明 证券研究报告 17",
      "tables": []
    },
    {
      "page_number": 18,
      "width": 595.32,
      "height": 841.92,
      "text": "行业深度研究/有色金属\n图22：Soutn Deep 金矿 2018-2023 年黄金权益产量 图23：South Deep 金矿 2018-2023 年黄金总投入成\n（单位：吨） 本（单位：美元/盎司）\n总投入成本（美元/盎司）\n12 黄金权益产量（吨） 60%\n2500 增长率--右轴（%） 20%\n增长率--右轴（%）\n10 10%\n40% 2000\n8 0%\n1500\n6 20% -10%\n1000\n4 -20%\n0%\n2 500 -30%\n0 -20% 0 -40%\n2018 2019 2020 2021 2022 2023 2018 2019 2020 2021 2022 2023\n资料来源：公司公告，民生证券研究院 资料来源：公司公告，民生证券研究院\n图24：South Deep 金矿近几年回收率持续下滑\n5 入选品位（g/t） 回收率(%) 96.5%\n96.0%\n4\n95.5%\n95.0%\n3\n94.5%\n94.0%\n2\n93.5%\n93.0%\n1\n92.5%\n0 92.0%\n2018 2019 2020 2021 2022 2023\n资料来源：公司公告，民生证券研究院\n其他矿山：Asanko 金矿产量保持相对稳定，成本端由于能源价格和副产品价\n值下跌，导致总投入成本 2018 年以来长期处于持续上涨的趋势；Damang 金矿\n由于开采寿命的临近，2023 年产量减少了将近 30%，成本端由于黄金销量的减少\n和销售成本的增加，2023 年总投入成本增加 55%。\n本公司具备证券投资咨询业务资格，请务必阅读最后一页免责声明 证券研究报告 18",
      "tables": []
    },
    {
      "page_number": 19,
      "width": 595.32,
      "height": 841.92,
      "text": "行业深度研究/有色金属\n2.4.2 澳大利亚地区：核心资产为 St lves 金矿、Granny Smith 金\n矿以及 Agnew 金矿\n2023 年公司在澳大利亚地区的黄金权益产量占了全公司黄金权益产量的\n46.7%。主要来自于位于澳大利亚卡尔古利附近的 St lves 金矿（占比 16.4%），\n位于澳大利亚伊尔加恩克拉顿的金矿 Granny Smith（占比 12.5%），位于澳大利\n亚诺斯曼-威鲁纳绿石带的 Agnew 金矿（占比 10.6%）和位于澳大利亚亚马尔纳\n地的 Gruyere（占比 7.1%，公司持股 50%，剩余股权为金路资源持有）。\n图25：公司澳大利亚地区布局\n资料来源：公司公告，民生证券研究院\n注：2023 年数据\nSt lves 是澳大利亚地区的一流黄金资产（Tier One gold mines）。是一座\n由金田主导生产的露天+地下金矿。产量端，2018-2021 年露天矿坑出矿量逐步\n减少，地下出矿量逐步增加，地下矿品位高于露天矿，整体黄金产量不断增加，\n本公司具备证券投资咨询业务资格，请务必阅读最后一页免责声明 证券研究报告 19",
      "tables": []
    },
    {
      "page_number": 20,
      "width": 595.32,
      "height": 841.92,
      "text": "行业深度研究/有色金属\n2022-2023 年地下矿品位略有下滑，导致黄金产量略有下滑，整体波动不大，过\n去多年黄金权益产量均维持在 11 吨上下。成本端，近几年由于原辅料、人工、能\n源成本上涨，公司的总投入成本逐年增加。\n图26：St lves 金矿 2018-2023 年黄金权益产量（单 图27：St lves 金矿 2018-2023 年黄金总投入成本（单\n位：吨） 位：美元/盎司）\n黄金权益产量（吨） 总投入成本（美元/盎司）\n13 增长速度--右轴（%） 10% 1400 增长速度--右轴（%） 40%\n1200\n11 5% 1000 20%\n800\n9 0% 600\n0%\n400\n7 -5%\n200\n0 -20%\n5 -10% 2018 2019 2020 2021 2022 2023\n2018 2019 2020 2021 2022 2023\n资料来源：公司公告，民生证券研究院 资料来源：公司公告，民生证券研究院\n图28：St lves 金矿近几年正在露天转地下\n露天采矿量（千吨） 地下采矿量（千吨）\n露天矿石品位(g/t，右轴） 地下矿石品位(g/t，右轴)\n4000 综合处理品位（g/t，右轴） 7\n3500 6\n3000\n5\n2500\n4\n2000\n3\n1500\n2\n1000\n500 1\n0 0\n2018 2019 2020 2021 2022 2023\n资料来源：公司公告，民生证券研究院\nGranny Smith 金矿是一座地下金矿，公司持股 100%。产量端 2020-2022\n年，由于入选品位及回收率的增加，该矿山黄金产量增加，2023 年，由于入选品\n位与回收率的骤降，该矿山产量下降 1.4%。成本端近年来销售成本的增加以及通\n货膨胀的影响使得该矿山的总投入成本持续上升。\n本公司具备证券投资咨询业务资格，请务必阅读最后一页免责声明 证券研究报告 20",
      "tables": [
        [
          [
            "",
            "",
            "",
            ""
          ],
          [
            "",
            "",
            "",
            ""
          ],
          [
            "",
            "",
            "",
            ""
          ],
          [
            "",
            "",
            "",
            ""
          ]
        ],
        [
          [
            "",
            ""
          ],
          [
            "",
            ""
          ]
        ],
        [
          [
            "",
            "",
            "",
            ""
          ],
          [
            "",
            "",
            "",
            ""
          ],
          [
            "",
            "",
            "",
            ""
          ]
        ]
      ]
    },
    {
      "page_number": 21,
      "width": 595.32,
      "height": 841.92,
      "text": "行业深度研究/有色金属\n图29：Granny Smith 金矿 2018-2023 年黄金权益产 图30：Granny Smith 金矿 2018-2023 年黄金总投入\n量（单位：吨） 成本（单位：美元/盎司）\n黄金权益产量（吨）\n9.00 增长率--右轴（%） 10% 1400 总投入成本（美元/盎司） 20%\n1200 增长率--右轴（%）\n15%\n8.00 5% 1000\n10%\n800\n7.00 0%\n600\n5%\n400\n6.00 -5% 0%\n200\n0 -5%\n5.00 -10%\n2018 2019 2020 2021 2022 2023\n2018 2019 2020 2021 2022 2023\n资料来源：公司公告，民生证券研究院 资料来源：公司公告，民生证券研究院\n图31：Granny Smith 金矿近几年回收率持续下滑\n入选品位（g/t） 回收率(%)\n5.8 95%\n5.6\n94%\n5.4\n93%\n5.2\n5\n92%\n4.8\n91%\n4.6\n4.4 90%\n2018 2019 2020 2021 2022 2023\n资料来源：公司公告，民生证券研究院\nAgnew 金矿是一座露天+地下金矿，公司持股 100%。产量端，近三年该矿\n山产量持续增加，主要是由于该公司从 2022 年露天矿扩建投产，以及露天矿品位\n的上升。成本端，近三年随着产量的增加，总投入成本企稳略有下降。\n本公司具备证券投资咨询业务资格，请务必阅读最后一页免责声明 证券研究报告 21",
      "tables": []
    },
    {
      "page_number": 22,
      "width": 595.32,
      "height": 841.92,
      "text": "行业深度研究/有色金属\n图32：Agnew 金矿 2018-2023 年黄金权益产量（单 图33：Agnew 金矿 2018-2023 年黄金总投入成本（单\n位：吨） 位：美元/盎司）\n黄金权益产量（吨）\n8 10% 1400 总投入成本（美元/盎司） 30%\n增长速度--右轴（%）\n1200\n7.5 5% 1000 20%\n800\n10%\n7 0%\n600\n400\n0%\n6.5 -5%\n200\n0 -10%\n6 -10%\n2018 2019 2020 2021 2022 2023\n2018 2019 2020 2021 2022 2023\n资料来源：公司公告，民生证券研究院 资料来源：公司公告，民生证券研究院\n图34：Agnew 金矿近几年开始露天采矿\n露天采矿量（千吨） 地下采矿量（千吨）\n露天矿石品位(g/t，右轴） 地下矿石品位(g/t，右轴)\n综合处理品位（g/t，右轴）\n1400 8\n1200 7\n6\n1000\n5\n800\n4\n600\n3\n400\n2\n200 1\n0 0\n2018 2019 2020 2021 2022 2023\n资料来源：公司公告，民生证券研究院\n其他矿山：Gruyere金矿是一座露天矿，位于澳大利亚西南部，公司持股 50%，\n金路资源持股 50%。产量端近几年产量增长缓慢，2023 年增长率为 2.5%，主要\n是因为回收率的提高。成本端近几年由于销售成本的增加，总投入成本缓慢增加。\n2.4.3 美洲地区：核心资产为秘鲁的 Cerro Corona 金铜矿\n2023 年公司在美洲地区的黄金权益产量占了全公司黄金权益产量的 5.4%。\n全部来自于位于秘鲁瓦尔加约克村附近的 Cerro Corona 金铜矿（ 公司持股\n99.53%，剩余部分私人持有）。此外，公司在美洲还有一座 Salares Norte 金银\n矿（公司持股 100%，2023 年没有进行黄金与白银的生产）。\n本公司具备证券投资咨询业务资格，请务必阅读最后一页免责声明 证券研究报告 22",
      "tables": [
        [
          [
            "",
            ""
          ],
          [
            "",
            ""
          ]
        ]
      ]
    },
    {
      "page_number": 23,
      "width": 595.32,
      "height": 841.92,
      "text": "行业深度研究/有色金属\n2023 年公司铜权益产量全部来自于秘鲁的 Cerro Corona 金铜矿，产量为\n2.7 万吨。\n图35：公司美洲地区布局\n资料来源：公司公告，民生证券研究院\n注：2023 年数据\nCerro Corona 是一座露天矿，位于南美洲的秘鲁，公司持股 99.53%，剩余\n部分私人持有。产量端，该矿山 2023 年黄金产量比去年减少 5%（7 千盎司），\n主要是由于该矿山储量即将枯竭，没有更多的资源可开采。成本端，近几年由于销\n售成本的增长，该矿山总投入成本持续增长。\n本公司具备证券投资咨询业务资格，请务必阅读最后一页免责声明 证券研究报告 23",
      "tables": []
    },
    {
      "page_number": 24,
      "width": 595.32,
      "height": 841.92,
      "text": "行业深度研究/有色金属\n图36：Cerro Corona 金矿 2018-2023 年黄金权益产 图37：Cerro Corona 金矿 2018-2023 年黄金总投入\n量（单位：吨） 成本（单位：美元/盎司）\n总投入成本（美元/盎司）\n黄金权益产量（千盎司）\n增长速度--右轴（%）\n800 1\n增长速度--右轴（%）\n180 20% 700 0.8\n160 0.6\n600\n140 10% 0.4\n120 500 0.2\n0%\n100 400 0\n80 -10% 300 -0.2\n60\n-0.4\n40 -20% 200 -0.6\n20 100 -0.8\n0 -30%\n0 -1\n2018 2019 2020 2021 2022 2023\n2018 2019 2020 2021 2022 2023\n资料来源：公司公告，民生证券研究院 资料来源：公司公告，民生证券研究院\n图38：Cerro Corona 金矿近几年黄金回收率持续增加\n黄金回收率(%) 铜回收率(%)\n95\n90\n85\n80\n75\n70\n65\n60\n55\n50\n2018 2019 2020 2021 2022 2023\n资料来源：公司公告，民生证券研究院\n本公司具备证券投资咨询业务资格，请务必阅读最后一页免责声明 证券研究报告 24",
      "tables": []
    },
    {
      "page_number": 25,
      "width": 595.32,
      "height": 841.92,
      "text": "行业深度研究/有色金属\n3 远期增量：主要来源于智利\n3.1 增量有限，主要来源于智利地区\n产量端， 金田预计 2024-2026 年集团黄金当量产量分别达到 243 万盎司、\n270 万盎司、260 万盎司。远期增量主要来自于智利地区 Salares Norte 项目，\n预计 2025 年到 2029 年平均年产量达到 48.5 万盎司。澳大利亚地区产量将保持\n稳定，到 2030 年澳大利亚地区预计实现金产量 100 万盎司；加纳地区产量从\n2023 逐年缩减的态势，公司预计 Tarkw 矿山年产量远期将达到约 48 万盎司（不\n包括与 lduapriem 合资企业产量）；南非地区金田公司预计 South Deep 从 2027\n年开始黄金年产量将稳定于 38 万盎司；秘鲁地区的产量有轻微缩减，预计在\n2024 年到 2025 年 Cerro Corona 产量将降至 19.7 万盎司，从 2026 年开始该\n矿将处理库存，产量预计继续下降，直到 2030 年该矿山开采寿命结束。\n图39：金田公司黄金产量预测（单位：千盎司）\n资料来源：公司公告，民生证券研究院\n注：不包括 Windfall Project 和 Tarkwa/lduapriem 合资企业产量\n表9：金田黄金项目远期情况汇总\n金属类型 项目 地区/国家 股权 进度指引\nGruyere 西澳大利亚 50% Golden Highway 为该矿山 2024 年重点勘探项目\n基础设施开发计划于 2025 年开始，公司预计资源转换后有望贡献\nGranny Smith 西澳大利亚 100%\n55.3 万盎司黄金储量\n现有的矿山储量将在 2031 年耗尽，目前公司仍在继续扩展勘探和棕地\nSt Ives 西澳大利亚 100%\n勘探工作\n金 2024 年项目包括 Waroonga Deeps 的战略范围界定研究和初步工作\nAgnew 西澳大利亚 100%\n和 Redeemer 扩建\nSouth Deep 南非 90% 公司目标是到 2027 年每年黄金产量 12 吨\nDamang 加纳 90% 据估计目前的矿石储量只够维持到 2025 年\nTarkwa 加纳 90% 据公司估计目前的矿石储量将在 2036 年耗尽\nWindfall 加拿大 50% 高品位金矿，处于项目评估和规划阶段\n该矿山于 2024 年 4 月份正式投产运营，公司预估项目投产后黄金产\n金、银 Salares Norte 智利 100%\n量将达 25 万盎司，2025 年产量有望增至 58 万盎司\n金、铜 Cerro Corona 秘鲁 100% 目前的矿石储量将在 2030 年耗尽\n资料来源：公司公告，民生证券研究院\n本公司具备证券投资咨询业务资格，请务必阅读最后一页免责声明 证券研究报告 25",
      "tables": [
        [
          [
            "",
            "金属类型",
            "",
            "",
            "项目",
            "",
            "",
            "地区/国家",
            "",
            "",
            "股权",
            "",
            "",
            "进度指引",
            ""
          ]
        ],
        [
          [
            "Granny Smith",
            "西澳大利亚",
            "100%",
            "",
            "基础设施开发计划于2025年开始，公司预计资源转换后有望贡献",
            ""
          ],
          [
            "",
            "",
            "",
            "",
            "55.3万盎司黄金储量",
            ""
          ]
        ],
        [
          [
            "Agnew",
            "西澳大利亚",
            "100%",
            "",
            "2024年项目包括Waroonga Deeps的战略范围界定研究和初步工作",
            ""
          ],
          [
            "",
            "",
            "",
            "",
            "和Redeemer扩建",
            ""
          ]
        ],
        [
          [
            "",
            "Damang",
            "",
            "",
            "加纳",
            "",
            "",
            "90%",
            "",
            "",
            "据估计目前的矿石储量只够维持到2025年",
            ""
          ]
        ],
        [
          [
            "",
            "Windfall",
            "",
            "",
            "加拿大",
            "",
            "",
            "50%",
            "",
            "",
            "高品位金矿，处于项目评估和规划阶段",
            ""
          ]
        ],
        [
          [
            "",
            "Cerro Corona",
            "",
            "",
            "秘鲁",
            "",
            "",
            "100%",
            "",
            "",
            "目前的矿石储量将在2030年耗尽",
            ""
          ]
        ]
      ]
    },
    {
      "page_number": 26,
      "width": 595.32,
      "height": 841.92,
      "text": "行业深度研究/有色金属\n勘探增储方面，2023 年 3 月，金田公司宣布加纳地区 Tarkwa 矿与\nIduapriem 矿（AngloGold Ashanti 公司 100%拥有）的合资计划，两家公司\n与加纳政府谈判仍在继续，如果能够达成各方都认同的条款，合资计划将创建\n非洲最大的金矿，矿山寿命长达 18 年。2023 年 5 月，金田公司宣布与 Osisko\nMining 公司合作进行 Windfall Project，2023 年期间共花费 2700 万美元\n勘探费。目前位于智利地区 Salares Norte 矿山拥有巨大增储潜力，公司从\n2025 年开始将重点开发该地区的勘探增储活动。\n表10：2023 年澳大利亚地区金矿勘探活动\n金属类型 项目 项目属性 花费（美元） 可归属矿石储量\n现有矿山基础\nGruyere 160 万 下降 9%至 180 万盎司\n上勘探\n现有矿山基础\nSt Ives 2600 万 下降 4%至 260 万盎司\n上勘探\n金\n现有矿山基础\nGranny Smith 1300 万 增加 12%至 240 万盎司\n上勘探\n现有矿山基础\nAgnew 1600 万 下降 20%至 90 万盎司\n上勘探\n资料来源：公司公告，民生证券研究院\n3.2 项目细览：多地布局，勘探增储为主要工作\n澳大利亚地区：Gruyere, Granny Smith, St Ives,Agnew\nGruyere 金矿位于西澳大利亚洲，金田公司拥有 5 0 %所有权。Gruyere\n金矿品位 1.2 克/吨， 2023 年黄金金属产量 32.2 万盎司。资源方面，2023 年\n矿山金金属探明和控制储量 183.2 万盎司，同比减少 19 万盎司（9%），资\n源量为 53.3 万盎司，同比减少 5.3 万盎司（9%），推断资源量 103.8 万盎\n司，同比减少 9 万盎司（13%）。Golden Highway 为该矿山 2024 年重点\n勘探项目。\n本公司具备证券投资咨询业务资格，请务必阅读最后一页免责声明 证券研究报告 26",
      "tables": [
        [
          [
            "",
            "金属类型",
            "",
            "",
            "项目",
            "",
            "",
            "项目属性",
            "",
            "",
            "花费（美元）",
            "",
            "",
            "可归属矿石储量",
            ""
          ]
        ],
        [
          [
            "St Ives",
            "",
            "现有矿山基础",
            "",
            "2600万",
            "下降4%至260万盎司"
          ],
          [
            "",
            "",
            "上勘探",
            "",
            "",
            ""
          ]
        ],
        [
          [
            "Agnew",
            "",
            "现有矿山基础",
            "",
            "1600万",
            "下降20%至90万盎司"
          ],
          [
            "",
            "",
            "上勘探",
            "",
            "",
            ""
          ]
        ]
      ]
    },
    {
      "page_number": 27,
      "width": 595.32,
      "height": 841.92,
      "text": "行业深度研究/有色金属\n图40：Gruyere 矿山品位吨位曲线图\n资料来源：公司公告，民生证券研究院\nGranny Smith 金矿位于西澳大利亚洲，公司拥有100%股权，属于公司一\n级资产。 该矿山品位5.4克/吨，矿石储量1197万吨，金金属储量约239万盎司。\n2023年黄金总产量28.4万盎司。增储方面，Zone150矿脉的初步可行性研究于\n2023年完成，初步基础设施开发计划于2025年开始，公司预计资源转换后有望贡\n献55.3万盎司黄金储量。\n图41：Granny Smith 矿山品位吨位曲线图\n资料来源：公司公告，民生证券研究院\n本公司具备证券投资咨询业务资格，请务必阅读最后一页免责声明 证券研究报告 27",
      "tables": []
    },
    {
      "page_number": 28,
      "width": 595.32,
      "height": 841.92,
      "text": "行业深度研究/有色金属\n图42：Granny Smith 矿山基础设施示意图\n资料来源：公司公告，民生证券研究院\n图43：Wallaby Underground 矿区模型长剖示意图\n资料来源：公司公告，民生证券研究院\nSt Ives 金矿位于西澳大利亚洲，公司拥有100%股权，属于公司一级资产\n。 该矿山品位3.4克/吨，矿石储量2410万吨，金金属储量约261万盎司。2023年\n黄金总产量为37.2万盎司，据估计，现有的矿山储量将在2031年耗尽，目前公司\n仍在继续扩展勘探和棕地勘探工作。\n本公司具备证券投资咨询业务资格，请务必阅读最后一页免责声明 证券研究报告 28",
      "tables": []
    },
    {
      "page_number": 29,
      "width": 595.32,
      "height": 841.92,
      "text": "行业深度研究/有色金属\n图44：St Ives 矿山品位吨位曲线图\n资料来源：公司公告，民生证券研究院\n图45：St Ives 矿山基础设施示意图\n资料来源：公司公告，民生证券研究院\nAgnew金矿位于西澳大利亚洲，金田公司拥有100%所有权，属于公司一\n级资产。 该矿山品位6.7克/吨，矿石储量398万吨，金金属储量约87.2万盎司。\n2023黄金产量为24.5万盎司，同比2022年净减少22.2万盎司（20%），推断金\n属资源量56.4万盎司，同比2022年净减少3.8万盎司（6%）。2023年勘探重点为\nWaroonga和New Holland矿化系统扩建以及地表勘探钻探。2024年项目包括\nWaroonga Deeps的战略范围界定研究和Redeemer扩建活动。\n本公司具备证券投资咨询业务资格，请务必阅读最后一页免责声明 证券研究报告 29",
      "tables": []
    },
    {
      "page_number": 30,
      "width": 595.32,
      "height": 841.92,
      "text": "行业深度研究/有色金属\n图46：Agnew 矿山品位吨位曲线图\n资料来源：公司公告，民生证券研究院\n图47：Agnew 矿山基础设施示意图\n资料来源：公司公告，民生证券研究院\n南非地区：South Deep\nSouth Deep 金矿位于南非地区，金田公司拥有90%的所有权，是公司的\n旗舰资产。 该矿石品位为6.4 克/吨，金金属储量约2823.9万盎司，较2022年净\n减少44万盎司（2%），黄金产量从2022年的32.2万盎司增加到2023年的32.8万\n盎司，探明控制和判断的专属矿产资源量估计为2万盎司，减少了24.1万盎司（1%\n），矿产资源和矿石储量的变化主要是由于矿产枯竭和成本通胀导致的，据公司\n估计目前的矿石储量将在2096年耗尽，公司现在目标是到2027年每年黄金产量\n12吨。\n本公司具备证券投资咨询业务资格，请务必阅读最后一页免责声明 证券研究报告 30",
      "tables": []
    },
    {
      "page_number": 31,
      "width": 595.32,
      "height": 841.92,
      "text": "行业深度研究/有色金属\n图48：South Deep 矿山品位吨位曲线图\n资料来源：公司公告，民生证券研究院\n图49：South Deep 矿山基础设施示意图\n资料来源：公司公告，民生证券研究院\n本公司具备证券投资咨询业务资格，请务必阅读最后一页免责声明 证券研究报告 31",
      "tables": []
    },
    {
      "page_number": 32,
      "width": 595.32,
      "height": 841.92,
      "text": "行业深度研究/有色金属\n图50：以 10 年为增量显示的可维持开采计划和时间表\n资料来源：公司公告，民生证券研究院\n加纳地区：Tarkwa, Damang\n金田公司在加纳的业务包括Tarkwa和Damang金矿。Tarkwa为露天矿,矿山\n寿命约12年。Damang 再投资项目资源计划于2025年耗尽，最后两年的重点任\n务是处理库存。2023年底公司达成协议将Asanko金矿剥离给合资伙伴Galiano\nGold。\nDamang 金矿位于加纳地区，金田公司拥有90%的所有权。 该矿山矿石品\n位1.1克/吨，金金属储量约19.4万盎司，较2022年净减少11.2万盎司（37%）。\n2023年矿区黄金产量15.3万盎司，矿石储量估计为201.9万盎司，减少87.5万盎\n司（30%），该变化主要是由于矿山资源枯竭，据估计目前的矿石储量只够维持\n到2025年。\n本公司具备证券投资咨询业务资格，请务必阅读最后一页免责声明 证券研究报告 32",
      "tables": []
    },
    {
      "page_number": 33,
      "width": 595.32,
      "height": 841.92,
      "text": "行业深度研究/有色金属\n图51：Damang 矿山基础设施示意图\n资料来源：公司公告，民生证券研究院\nTarkwa金矿位于 加 纳地 区 ，金田公司拥有90%的所有权。 该矿山品位为1.2\n克/吨，储量15163万吨，金金属储量约434.8万盎司。根据公司公告，2023年该\n矿区矿石处理量 14.1百万吨，黄金产量为55.1万盎司，矿石储量估计为434.8万\n盎司，比2022年减少50.8万盎司（10%），据估计目前的矿石储量将在2036年耗\n尽。\n图52：Tarkwa 矿山品位吨位曲线图\n资料来源：公司公告，民生证券研究院\n本公司具备证券投资咨询业务资格，请务必阅读最后一页免责声明 证券研究报告 33",
      "tables": []
    },
    {
      "page_number": 34,
      "width": 595.32,
      "height": 841.92,
      "text": "行业深度研究/有色金属\n图53：Tarkwa 矿山基础设施示意图\n资料来源：公司公告，民生证券研究院\n智利和秘鲁地区：Salares Norte,Cerro Corona\nSalares Norte矿山位 于 智 利 地 区 ， 金田公司拥有100%的所有权。 该矿石\n金品位为 6.8克/吨，银品位为 44.8克/吨，矿石储量 18136千吨，金金属储量约\n341.6万盎司。2023年该矿山在建设中，没有生产黄金或者白银，预计将于2024\n年第一季度进行最后调试和第一批黄金开采，应占黄金储量为341.6万盎司，减少\n3.9万盎司（1%），应占白银储量为4194万盎司白银，减少22.4万盎司（1%），\n黄金推断矿产资源量为1万盎司，减少了4.8万盎司（83%），白银8.6万盎司，减\n少了44.5万盎司（84%）。该矿山按照原计划已正式投产运营，公司预估项目投产\n后黄金产量将达25万盎司，2025年产量有望增至58万盎司。\n图54：Salares Norte 矿山品位吨位曲线图\n资料来源：公司公告，民生证券研究院\n本公司具备证券投资咨询业务资格，请务必阅读最后一页免责声明 证券研究报告 34",
      "tables": []
    },
    {
      "page_number": 35,
      "width": 595.32,
      "height": 841.92,
      "text": "行业深度研究/有色金属\n图55：Salares Norte 矿山基础设施示意图\n资料来源：公司公告，民生证券研究院\nCerro Corona矿山位于秘鲁地区，金田公司拥有100%的所有权。该矿石\n金品位为 0.63克/吨，铜品位为 0.4克/吨，矿石储量4544万吨，金金属储量约\n74.9万盎司，较2022年净减少了12.3万盎司（14%），铜金属储量约33.6万盎\n司。2023年该矿区矿石处理量650万吨，黄金产量为12.2万盎司,铜产量5890万\n磅，铜336百万磅,减少了63百万磅（16%）。矿石储量变化是由于矿产损耗造成\n的，目前的矿石储量将在2030年耗尽。\n图56：Cerro Corona 矿山品位吨位曲线图\n资料来源：公司公告，民生证券研究院\n本公司具备证券投资咨询业务资格，请务必阅读最后一页免责声明 证券研究报告 35",
      "tables": []
    },
    {
      "page_number": 36,
      "width": 595.32,
      "height": 841.92,
      "text": "行业深度研究/有色金属\n图57：Cerro Corona 矿山基础设施示意图\n资料来源：公司公告，民生证券研究院\n加拿大地区：金田公司与加拿大的 Osisko Mining 有一家合资企业，项\n目目前正在建设中，拥有 50%所有权。旗下 Windfall 项目是一个高品位的\n金矿，正处于高级项目评估和规划阶段。\n图58：Windfall 地理位置\n资料来源：公司公告，民生证券研究院\n本公司具备证券投资咨询业务资格，请务必阅读最后一页免责声明 证券研究报告 36",
      "tables": []
    },
    {
      "page_number": 37,
      "width": 595.32,
      "height": 841.92,
      "text": "行业深度研究/有色金属\n4 风险提示\n1）地缘政治风险。公司资产分布全球各地，各个国家的矿业政策发生变更，\n会对公司资产的盈利能力产生影响。\n2）项目投产不及预期风险。公司仍有较多待投产项目，若由于气候等不可抗\n力因素投产低于预期，则会对公司的成长性产生不利影响。\n3）金属价格波动风险。公司的主要产品为金铜银等相关金属矿物，其价格与\n金铜银价格正相关，若价格下跌，会对公司盈利产生不利影响。\n本公司具备证券投资咨询业务资格，请务必阅读最后一页免责声明 证券研究报告 37",
      "tables": []
    },
    {
      "page_number": 38,
      "width": 595.32,
      "height": 841.92,
      "text": "行业深度研究/有色金属\n插图目录\n图 1： 金田黄金发展历史........................................................................................................................................................................ 5\n图 2： 2023 年世界黄金生产商产量排行（单位：吨） ................................................................................................................... 5\n图 3： 金田黄金资产布局图 ................................................................................................................................................................... 6\n图 4： 公司营收情况 ................................................................................................................................................................................ 6\n图 5： 公司盈利情况 ................................................................................................................................................................................ 6\n图 6： 黄金价格走势 ................................................................................................................................................................................ 7\n图 7： 公司营收结构中黄金是主要收入来源（单位：百万美元）（2023 年） ......................................................................... 7\n图 8： 公司毛利率净利率情况 ............................................................................................................................................................... 7\n图 9： 公司三费情况 ................................................................................................................................................................................ 7\n图 10： 公司资本开支情况 ..................................................................................................................................................................... 8\n图 11： 公司资产负债率 ......................................................................................................................................................................... 8\n图 12： 公司折旧与摊销情况 ................................................................................................................................................................. 8\n图 13： 近几年公司黄金权益产量上下波动 ...................................................................................................................................... 13\n图 14： 近几年公司铜权益产量维持 2.5 万吨左右 .......................................................................................................................... 13\n图 15： 20 年以来公司黄金成本持续上行 ........................................................................................................................................ 14\n图 16： 22 年以来公司黄金当量的铜全成本持续上行 ................................................................................................................... 14\n图 17： 公司在加纳地区布局 ............................................................................................................................................................... 15\n图 18： Tarkwa 金矿 2018-2023 年黄金权益产量（单位：吨） ................................................................................................ 16\n图 19： Tarkwa 金矿 2018-2023 年黄金总投入成本（单位：美元/盎司） ............................................................................. 16\n图 20： Tarkwa 金矿近几年入选品位增长明显................................................................................................................................ 16\n图 21： 公司在南非地区布局 ............................................................................................................................................................... 17\n图 22： Soutn Deep 金矿 2018-2023 年黄金权益产量（单位：吨） ...................................................................................... 18\n图 23： South Deep 金矿 2018-2023 年黄金总投入成本（单位：美元/盎司） ................................................................... 18\n图 24： South Deep 金矿近几年回收率持续下滑 .......................................................................................................................... 18\n图 25： 公司澳大利亚地区布局 ........................................................................................................................................................... 19\n图 26： St lves 金矿 2018-2023 年黄金权益产量（单位：吨） ................................................................................................. 20\n图 27： St lves 金矿 2018-2023 年黄金总投入成本（单位：美元/盎司） .............................................................................. 20\n图 28： St lves 金矿近几年正在露天转地下 ..................................................................................................................................... 20\n图 29： Granny Smith 金矿 2018-2023 年黄金权益产量（单位：吨） .................................................................................. 21\n图 30： Granny Smith 金矿 2018-2023 年黄金总投入成本（单位：美元/盎司） ................................................................ 21\n图 31： Granny Smith 金矿近几年回收率持续下滑 ...................................................................................................................... 21\n图 32： Agnew 金矿 2018-2023 年黄金权益产量（单位：吨） ................................................................................................ 22\n图 33： Agnew 金矿 2018-2023 年黄金总投入成本（单位：美元/盎司） ............................................................................. 22\n图 34： Agnew 金矿近几年开始露天采矿 ........................................................................................................................................ 22\n图 35： 公司美洲地区布局 ................................................................................................................................................................... 23\n图 36： Cerro Corona 金矿 2018-2023 年黄金权益产量（单位：吨） ................................................................................... 24\n图 37： Cerro Corona 金矿 2018-2023 年黄金总投入成本（单位：美元/盎司） ................................................................ 24\n图 38： Cerro Corona 金矿近几年黄金回收率持续增加 .............................................................................................................. 24\n图 39： 金田公司黄金产量预测（单位：千盎司）........................................................................................................................ 25\n图 40： Gruyere 矿山品位吨位曲线图 .............................................................................................................................................. 27\n图 41： Granny Smith 矿山品位吨位曲线图 ................................................................................................................................... 27\n图 42： Granny Smith 矿山基础设施示意图 ................................................................................................................................... 28\n图 43： Wallaby Underground 矿区模型长剖示意图 .................................................................................................................. 28\n图 44： St Ives 矿山品位吨位曲线图 ................................................................................................................................................ 29\n图 45： St Ives 矿山基础设施示意图 ................................................................................................................................................ 29\n图 46： Agnew 矿山品位吨位曲线图 ............................................................................................................................................... 30\n图 47： Agnew 矿山基础设施示意图 ............................................................................................................................................... 30\n图 48： South Deep 矿山品位吨位曲线图 .................................................................................................................................... 31\n图 49： South Deep 矿山基础设施示意图 .................................................................................................................................... 31\n图 50： 以 10 年为增量显示的可维持开采计划和时间表 ....................................................................................................... 32\n图 51： Damang 矿山基础设施示意图 ............................................................................................................................................ 33\n图 52： Tarkwa 矿山品位吨位曲线图 ................................................................................................................................................ 33\n图 53： Tarkwa 矿山基础设施示意图 ................................................................................................................................................ 34\n图 54： Salares Norte 矿山品位吨位曲线图 ................................................................................................................................... 34\n本公司具备证券投资咨询业务资格，请务必阅读最后一页免责声明 证券研究报告 38",
      "tables": []
    },
    {
      "page_number": 39,
      "width": 595.32,
      "height": 841.92,
      "text": "行业深度研究/有色金属\n图 55： Salares Norte 矿山基础设施示意图 ................................................................................................................................... 35\n图 56： Cerro Corona 矿山品位吨位曲线图 ................................................................................................................................. 35\n图 57： Cerro Corona 矿山基础设施示意图 ................................................................................................................................. 36\n图 58： Windfall 地理位置 ............................................................................................................................................................... 36\n表格目录\n表 1： 截至 2023 年末，公司储量和资源量情况汇总 ...................................................................................................................... 9\n表 2： 储量和资源量价格假设 ............................................................................................................................................................... 9\n表 3： 截至 2023 年底，公司的黄金权益储量合计为 4464.9 万盎司（1388.7 吨） .............................................................. 10\n表 4： 截至 2023 年底，公司的铜与白银权益储量分别为 336 百万磅（15.24 万吨）和 41.9 百万盎司（1304.5 吨） 11\n表 5： 截至 2023 年底，公司的黄金权益资源量合计为 3027.9 万盎司（941.8 吨） ............................................................ 11\n表 6： 截至 2023 年底，公司的白银权益资源量合计为 216.8 万盎司（67.4 吨） ................................................................. 12\n表 7： 2018-2023 年公司细分矿山的黄金产量 .............................................................................................................................. 13\n表 8： 2018-2023 年公司细分矿山的黄金总投入成本 .................................................................................................................. 14\n表 9： 金田黄金项目远期情况汇总 ..................................................................................................................................................... 25\n表 10： 2023 年澳大利亚地区金矿勘探活动 ................................................................................................................................... 26\n本公司具备证券投资咨询业务资格，请务必阅读最后一页免责声明 证券研究报告 39",
      "tables": []
    },
    {
      "page_number": 40,
      "width": 595.32,
      "height": 841.92,
      "text": "行业深度研究/有色金属\n分析师承诺\n本报告署名分析师具有中国证券业协会授予的证券投资咨询执业资格并登记为注册分析师，基于认真审慎的工作态度、专业严谨的研\n究方法与分析逻辑得出研究结论，独立、客观地出具本报告，并对本报告的内容和观点负责。本报告清晰准确地反映了研究人员的研\n究观点，结论不受任何第三方的授意、影响，研究人员不曾因、不因、也将不会因本报告中的具体推荐意见或观点而直接或间接收到任\n何形式的补偿。\n评级说明\n投资建议评级标准 评级 说明\n推荐 相对基准指数涨幅 15%以上\n以报告发布日后的 12 个月内公司股价（或行业 谨慎推荐 相对基准指数涨幅 5%～15%之间\n公司评级\n指数）相对同期基准指数的涨跌幅为基准。其 中性 相对基准指数涨幅-5%～5%之间\n中：A 股以沪深 300 指数为基准；新三板以三\n回避 相对基准指数跌幅 5%以上\n板成指或三板做市指数为基准；港股以恒生指\n数为基准；美股以纳斯达克综合指数或标普 推荐 相对基准指数涨幅 5%以上\n500 指数为基准。 行业评级 中性 相对基准指数涨幅-5%～5%之间\n回避 相对基准指数跌幅 5%以上\n免责声明\n民生证券股份有限公司（以下简称“本公司”）具有中国证监会许可的证券投资咨询业务资格。\n本报告仅供本公司境内客户使用。本公司不会因接收人收到本报告而视其为客户。本报告仅为参考之用，并不构成对客户的投资\n建议，不应被视为买卖任何证券、金融工具的要约或要约邀请。本报告所包含的观点及建议并未考虑个别客户的特殊状况、目标或需\n要，客户应当充分考虑自身特定状况，不应单纯依靠本报告所载的内容而取代个人的独立判断。在任何情况下，本公司不对任何人因\n使用本报告中的任何内容而导致的任何可能的损失负任何责任。\n本报告是基于已公开信息撰写，但本公司不保证该等信息的准确性或完整性。本报告所载的资料、意见及预测仅反映本公司于发\n布本报告当日的判断，且预测方法及结果存在一定程度局限性。在不同时期，本公司可发出与本报告所刊载的意见、预测不一致的报\n告，但本公司没有义务和责任及时更新本报告所涉及的内容并通知客户。\n在法律允许的情况下，本公司及其附属机构可能持有报告中提及的公司所发行证券的头寸并进行交易，也可能为这些公司提供或\n正在争取提供投资银行、财务顾问、咨询服务等相关服务，本公司的员工可能担任本报告所提及的公司的董事。客户应充分考虑可能\n存在的利益冲突，勿将本报告作为投资决策的唯一参考依据。\n若本公司以外的金融机构发送本报告，则由该金融机构独自为此发送行为负责。该机构的客户应联系该机构以交易本报告提及的\n证券或要求获悉更详细的信息。本报告不构成本公司向发送本报告金融机构之客户提供的投资建议。本公司不会因任何机构或个人从\n其他机构获得本报告而将其视为本公司客户。\n本报告的版权仅归本公司所有，未经书面许可，任何机构或个人不得以任何形式、任何目的进行翻版、转载、发表、篡改或引\n用。所有在本报告中使用的商标、服务标识及标记，除非另有说明，均为本公司的商标、服务标识及标记。本公司版权所有并保留一\n切权利。\n民生证券研究院：\n上海：上海市浦东新区浦明路 8 号财富金融广场 1 幢 5F；200120\n北京：北京市东城区建国门内大街 28 号民生金融中心 A 座 18 层；100005\n深圳：广东省深圳市福田区益田路 6001 号太平金融大厦 32 层 05 单元；518026\n本公司具备证券投资咨询业务资格，请务必阅读最后一页免责声明 证券研究报告 40",
      "tables": [
        [
          [
            "",
            "投资建议评级标准",
            "",
            "",
            "评级",
            "",
            "",
            "说明",
            ""
          ]
        ]
      ]
    }
  ]
}