{
  "metadata": {
    "file_name": "2024-09-19_信达证券_京沪高铁_京沪高铁（601816）：深度报告：坐拥黄金路产，铁路龙头未来成长可期.pdf",
    "file_stem": "2024-09-19_信达证券_京沪高铁_京沪高铁（601816）：深度报告：坐拥黄金路产，铁路龙头未来成长可期",
    "relative_path": "2024-09-19_信达证券_京沪高铁_京沪高铁（601816）：深度报告：坐拥黄金路产，铁路龙头未来成长可期.pdf",
    "source_path": "/Users/macbook/Desktop/黄金/2024-09-19_信达证券_京沪高铁_京沪高铁（601816）：深度报告：坐拥黄金路产，铁路龙头未来成长可期.pdf",
    "page_count": 31,
    "converted_pages": 31,
    "text_chars": 41042,
    "table_count": 95,
    "pdf_metadata": {
      "Author": "Microsoft 帐户",
      "Creator": "Microsoft® Word 2021",
      "CreationDate": "D:20240919110828+08'00'",
      "ModDate": "D:20240919110828+08'00'",
      "Producer": "Microsoft® Word 2021"
    }
  },
  "pages": [
    {
      "page_number": 1,
      "width": 595.32,
      "height": 841.92,
      "text": "坐拥黄金路产，铁路龙头未来成长可期\n[Table_CoverStock]\n—京沪高铁(601816)公司深度报告\n[Tab2l0e_2Re4po年rtDa0t9e]月 19 日\n[匡Ta培bl钦e_ C o v交er通Au运th输or行] 业首席分析师\n执业编号 S1500524070004\n邮 箱 kuangpeiqin@cindasc.com\n[ Table_CoverReportList]",
      "tables": []
    },
    {
      "page_number": 2,
      "width": 595.32,
      "height": 841.92,
      "text": "[Table_Title]\n证券研究报告 京沪高铁（601816.SH）深度报告：坐拥黄金\n公司研究 路产，铁路龙头未来成长可期\n[Table_ReportType]\n公司深度报告\n[Table_ReportDate] 2024 年 09 月 19 日\n[京Ta沪bl高e_铁Sto(c6k0A1n8d1R6an)k ] 本期内容提要:\n[Table_Summary]\n投资评级 增持 高铁承运量快速提升，铁路黄金资产上市。\n1）行业：铁路发展成效显著，高铁规模持续扩大。营业里程上，2008~2023\n上次评级\n年，铁路/高铁营业里程年均增速为 4.7%/32.0%。截至 2023 年末，高速\n铁路营业里程增至 4.5 万公里，占铁路总里程比例为 28.3%。旅客周转量\n[Table_Chart 京 ] 沪高 铁 沪深300 上，铁路已成为最主要的大众出行方式，2022 年，铁路周转量占比为\n20% 50.9%，其中高铁在铁路中的周转量占比达到 66.7%。\n10% 2）公司：京沪线黄金资产，经营稳健坐拥百亿利润。公司线路纵横首都\n0% 北京和经济中心上海，沿线覆盖了中国经济发展最活跃和最具潜力的区\n-10% 域，运输需求旺盛，客运量增长迅猛。凭借显著的区位优势及高铁出行需\n-20% 求的持续增加，公司盈利稳增。2019 年前，公司营收及归母净利保持稳\n23/09 24/01 24/05 24/09\n步增长，归母净利同比增速保持在 10%以上。2023 年公司营收/归母净利\n达到 407/115.46 亿元，较 2019 年同期+16.7%/+4.3%。\n资料来源：聚源，信达证券研发中心\n收入源自客票及路网服务，成本整体较稳定。按是否担当列车，公司业务\n可分为本线及跨线业务。本线客票业务主要是公司为乘坐担当列车的旅客\n[公Ta司bl主e_要Ba数se据Da ta] 提供高铁运输服务并收取票价款；跨线的提供路网服务业务则是公司向其\n收盘价（元） 5.30 他铁路运输企业提供线路使用、接触网使用等服务并收取相应费用等。\n52 周内股价波动区间5.85-4.67 2019 年前，两大主营业务收入基本对半，跨线路网服务业务毛利占比约\n(元) 六成。2023 年，公司本线/跨线业务收入分别为 160.8/242.2 亿元，占比\n最近一月涨跌幅(％) -7.50 分别为 39.5%/59.5%。公司营业成本较稳定，其中委托运输管理费、动\n总股本(亿股) 491.06 车组使用费、折旧和能源支出为主要成本项，合计占比约 90%。\n流通 A 股比例(％) 100.00 未来展望：票价市场化持续，运量仍有增长。\n总市值(亿元) 2,602.64\n1）旅客运输业务：京沪黄金通道，量价有望双升。旅客运输业务收入取\n资料来源：聚源，信达证券研发中心 决于票价及旅客量情况，二者均有进一步提升的可能。票价端，随着高铁\n票价市场化机制改革持续推进及大众人均收入提升、出行需求增加，票价\n可能会迎来进一步上涨。旅客量端，可通过提升客座率、增加发车频次、\n增加加长列车车次等方式提升旅客量。\n2）提供路网服务业务：南北大通道价值提升，跨线车稳步增加。我们预计\n该业务收入增长主要依托于跨线列车车次、运营里程等量的提升。服务价\n格由国铁集团定价，费率相对稳定；业务量大体与跨线车列次、运营里程、\n旅客数等正向相关。随路网逐步完善，公司本线跨线列车调整，跨线车列\n次、运营里程、旅客人数等均有望增长，我们预计将带动路网服务业务量\n进一步增加。\n盈利预测与投资评级：我们预计公司 2024-2026 年公司归母净利润分别\n130.54/144.02/155.81 亿元，同比分别+13.06%、+10.33%、+8.19%，\n对应每股收益分别为 0.27、0.29、0.32 元，现价对应 PE 分别为 19.94、\n18.07、16.70 倍。综合绝对估值和相对估值情况考虑，首次覆盖，我们\n信达证券股份有限公司\n给予公司“增持”评级。\nCINDA SECURITIES CO.,LTD\n风险因素：宏观经济波动风险，清算政策调整风险，委托管理风险，行业\n北京市西城区宣武门西大街甲127号金隅大厦B\n座\n竞争加剧风险，京福安徽运量增长不及预期风险等。\n邮编：100031\n请阅读最后一页免责声明及信息披露 http://www.cindasc.com 2",
      "tables": [
        [
          [
            "",
            "证券研究报告",
            "",
            ""
          ],
          [
            "",
            "公司研究",
            "",
            ""
          ],
          [
            "[Table_ReportType] 公司深度报告",
            "",
            "",
            ""
          ],
          [
            "[京Ta沪bl高e_铁Sto(c6k0A1n8d1R6an)k ]",
            "",
            "",
            ""
          ],
          [
            "投资评级",
            "",
            "增持",
            ""
          ],
          [
            "",
            "",
            "",
            ""
          ],
          [
            "上次评级",
            "",
            "",
            ""
          ],
          [
            "",
            "",
            "",
            ""
          ],
          [
            "[Table_Chart] 京沪高铁 沪深300 20% 10% 0% -10% -20% 23/09 24/01 24/05 24/09",
            "",
            "",
            ""
          ],
          [
            "资料来源：聚源，信达证券研发中心",
            "",
            "",
            ""
          ],
          [
            "",
            "",
            "",
            ""
          ],
          [
            "[公Ta司bl主e_要Ba数se据Da ta]",
            "",
            "",
            ""
          ],
          [
            "收盘价（元）",
            "",
            "5.30",
            ""
          ],
          [
            "52 周内股价波动区间",
            "",
            "5.85-4.67",
            ""
          ],
          [
            "(元)",
            "",
            "",
            ""
          ],
          [
            "",
            "",
            "",
            ""
          ],
          [
            "最近一月涨跌幅(％)",
            "",
            "-7.50",
            ""
          ],
          [
            "",
            "",
            "",
            ""
          ],
          [
            "总股本(亿股)",
            "",
            "491.06",
            ""
          ],
          [
            "流通A股比例(％)",
            "",
            "100.00",
            ""
          ],
          [
            "总市值(亿元)",
            "",
            "2,602.64",
            ""
          ],
          [
            "资料来源：聚源，信达证券研发中心",
            "",
            "",
            ""
          ],
          [
            "",
            "",
            "",
            ""
          ],
          [
            "",
            "",
            "",
            ""
          ],
          [
            "",
            "信达证券股份有限公司",
            "",
            ""
          ],
          [
            "",
            "CINDA SECURITIES CO.,LTD",
            "",
            ""
          ],
          [
            "",
            "北京市西城区宣武门西大街甲127号金隅大厦B",
            "",
            ""
          ],
          [
            "",
            "座",
            "",
            ""
          ],
          [
            "",
            "邮编：100031",
            "",
            ""
          ]
        ],
        [
          [
            "",
            "本期内容提要:",
            ""
          ]
        ]
      ]
    },
    {
      "page_number": 3,
      "width": 595.32,
      "height": 841.92,
      "text": "[T重a要bl财e务_P指r标of it] 2022A 2023A 2024E 2025E 2026E\n营业总收入(百万元) 19,336 40,683 44,277 47,311 50,369\n增长率 YoY % -34.0% 110.4% 8.8% 6.9% 6.5%\n归属母公司净利润\n-576 11,546 13,054 14,402 15,581\n(百万元)\n增长率 YoY% -112.0% 2103.6% 13.1% 10.3% 8.2%\n毛利率% 13.5% 45.8% 46.7% 48.2% 48.3%\n净资产收益率ROE% -0.3% 5.9% 6.4% 6.8% 7.1%\nEPS(摊薄)(元) -0.01 0.24 0.27 0.29 0.32\n市盈率 P/E(倍) — 22.54 19.94 18.07 16.70\n市净率 P/B(倍) 1.41 1.33 1.28 1.24 1.19\n资[T料a来bl源e_：RWepinodr，t信Cl达o证si券n研g]发 中心预测 ; 股价为2024 年 9 月18 日收盘价\n请阅读最后一页免责声明及信息披露 http://www.cindasc.com 3",
      "tables": [
        [
          [
            "",
            "增长率YoY %",
            "",
            "",
            "-34.0%",
            "",
            "",
            "110.4%",
            "",
            "",
            "8.8%",
            "",
            "",
            "6.9%",
            "",
            "",
            "6.5%",
            ""
          ]
        ],
        [
          [
            "",
            "增长率YoY%",
            "",
            "",
            "-112.0%",
            "",
            "",
            "2103.6%",
            "",
            "",
            "13.1%",
            "",
            "",
            "10.3%",
            "",
            "",
            "8.2%",
            ""
          ]
        ],
        [
          [
            "",
            "净资产收益率ROE%",
            "",
            "",
            "-0.3%",
            "",
            "",
            "5.9%",
            "",
            "",
            "6.4%",
            "",
            "",
            "6.8%",
            "",
            "",
            "7.1%",
            ""
          ]
        ],
        [
          [
            "",
            "市盈率P/E(倍)",
            "",
            "",
            "—",
            "",
            "",
            "22.54",
            "",
            "",
            "19.94",
            "",
            "",
            "18.07",
            "",
            "",
            "16.70",
            ""
          ]
        ]
      ]
    },
    {
      "page_number": 4,
      "width": 595.32,
      "height": 841.92,
      "text": "目 录\n1 高铁承运量快速提升，铁路黄金资产上市 ................................................................................ 6\n1.1 行业：铁路发展成效显著，高铁规模持续扩大 ....................................................... 6\n1.2 公司：京沪线黄金资产，区位优势显著 ................................................................... 7\n1.3 财务情况：经营稳健坐拥百亿利润，现金流充裕 ................................................... 9\n2 收入源自客票及路网服务，成本整体较稳定 .......................................................................... 11\n2.1 业务模式：按是否担当列车分为本线及跨线业务 ................................................. 11\n2.2 本线业务：收入源自担当列车的客票收入 ............................................................. 12\n2.3 跨线业务：收入源自其他铁路企业支付的路网使用费.......................................... 16\n2.4 成本情况：多为关联采购交易，收费标准由国铁集团清算定价 .......................... 18\n3 未来展望：票价市场化持续，运量仍有增长 .......................................................................... 20\n3.1 旅客运输业务：京沪黄金通道，量价有望双升 ..................................................... 20\n3.2 提供路网服务业务：南北大通道价值提升，跨线车稳步增加 .............................. 21\n3.3 京福安徽：短期业绩承压，长期利润可期 ............................................................. 22\n4 盈利预测、估值与投资评级 ...................................................................................................... 24\n4.1 盈利预测：预计公司 2024 年归母净利润 130.54 亿元........................................... 24\n4.2 估值方式：绝对估值与相对估值 ............................................................................. 25\n4.3 投资评级：首次覆盖给予“增持”评级 ................................................................. 27\n5 风险因素 ..................................................................................................................................... 28\n表 目 录\n表 1： 京沪高铁发起人出资及持股比例一览 .......................................................................... 8\n表 2： 京沪高铁主要固定资产一览（截至 2023 年末） ......................................................... 9\n表 3： 中国铁路客运票价政策推进进程 ............................................................................... 13\n表 4： 实施浮动票价的铁路线路路段及对象一览 ................................................................. 14\n表 5： 京沪高铁票价标准变化 .............................................................................................. 15\n表 6： 提供路网服务收入的五类细项收入及相应清算单价 ................................................... 17\n表 7： 公司营业成本细项构成及收费标准 ............................................................................ 19\n表 8： 公司营收拆分及预测表 .............................................................................................. 24\n表 9： 简易盈利预测表 ........................................................................................................ 25\n表 10： DCF 关键假设说明 .................................................................................................. 25\n表 11： FCFF 预测及估值结果（截至 2024.9.18） .............................................................. 26\n表 12： 京沪高铁的 FCFF 估值敏感型分析，对应每股价值情况（单位：元） ..................... 26\n图 目 录\n图 1： 2023 年，铁路周转量占比提升至 51.5%，稳居首位 ................................................... 6\n图 2： 2024 年上半年，铁路周转量同比增长 14.1% .............................................................. 6\n图 3： 至 2023 年，高铁营业里程占比提升至 28.3% ............................................................. 6\n图 4： 至 2022 年，高铁旅客周转量占比增至 66.7% ............................................................. 6\n图 5： 京沪高速铁路线路示意图 ............................................................................................ 7\n图 6： 京沪高铁股权结构（截至 2024 年 7 月 12 日）........................................................... 8\n图 7： 24H1 公司营业收入 209 亿元，较 2019 年同期+24.3% ............................................ 10\n图 8： 24H1 公司归母净利 63.6 亿元，较 2019 年同期+19.1% ........................................... 10\n图 9： 2019 年前，公司毛利率/净利率基本在 40%/30%以上 .............................................. 10\n图 10： 公司经营性净现金流基本稳定在百亿以上 ............................................................... 10\n图 11： 京沪高铁业务模式一览 ............................................................................................ 11\n图 12： 公司跨线车列次多于本线车列次，且增速更快 ........................................................ 11\n图 13： 公司本线列均旅客量高于跨线列均旅客量 ............................................................... 11\n图 14： 公司提供路网服务收入占比逐渐提升至六成 ............................................................ 12\n请阅读最后一页免责声明及信息披露 http://www.cindasc.com 4",
      "tables": []
    },
    {
      "page_number": 5,
      "width": 595.32,
      "height": 841.92,
      "text": "图 15： 2019 年前，公司提供路网服务业务毛利占比约六成 ............................................... 12\n图 16： 京沪高铁旅客运输业务模式 ..................................................................................... 12\n图 17： 京沪高铁二等座全票价对飞机经济舱全票价折扣幅度加大至三折 ............................ 15\n图 18： 2019 年前，公司本线发送旅客量微增 ..................................................................... 16\n图 19： 2019 年前，公司本线周转量保持增长 ..................................................................... 16\n图 20： 京沪高铁提供路网服务业务模式 .............................................................................. 16\n图 21： 2016~2019 年公司提供路网业务年均收入增速+16.6% ........................................... 17\n图 22： 公司提供路网服务业务收入构成占比（2023 年） ................................................... 17\n图 23： 2016~2019 年，公司跨线车发送列次年均增速+13.3% ........................................... 18\n图 24： 2023 年，公司跨线运营里程超 1.2 亿列公里 .......................................................... 18\n图 25： 公司营业成本稳定，2023 年较 2019 年同期+21.4% ............................................... 18\n图 26： 2023 年，公司委托运输管理费成本占比 26.4% ...................................................... 18\n图 27： 旅客运输业务收入增长来源 ..................................................................................... 20\n图 28： 公司客座率已有较大提升，略低于航空客运客座率 ................................................. 21\n图 29： 2021 年，公司日均发车列次增至 615 列 ................................................................. 21\n图 30： 提供路网业务收入增长来源 ..................................................................................... 21\n图 31： 京福安徽公司管辖线路 ............................................................................................ 22\n图 32： 2023 年，京福安徽公司营收为 54.7 亿元，同比+53.3% ......................................... 23\n图 33： 2023 年，京福安徽公司归母净利亏损收窄至-9.7 亿元 ............................................ 23\n图 34： 广深铁路 2010~2019 年间平均 PE 为 24.5 倍 ......................................................... 27\n请阅读最后一页免责声明及信息披露 http://www.cindasc.com 5",
      "tables": []
    },
    {
      "page_number": 6,
      "width": 595.32,
      "height": 841.92,
      "text": "1 高铁承运量快速提升，铁路黄金资产上市\n1.1 行业：铁路发展成效显著，高铁规模持续扩大\n铁路已成为中国最重要的运输方式之一，周转量占比超越公路回升至第一。1978 年改\n革开放后，中国交通运输行业开始飞速发展，综合交通运输体系不断完善，各类交通方式出\n行旅客量及周转量均大幅提升。1978~2023 年，总客运周转量年均复合增速达到 6.4%，其\n中铁路、民航周转量增速最快，分别为 5.9%、14.0%。\n对比不同出行方式看，铁路周转量占比在 2012 年前有所下降，此后快速回升至首位。\n铁路周转量从 1978 年的 1093.2 亿人公里增至 2012 年的 9812.3 亿人公里，占比从 62.7%\n降至 29.4%。2012 年后，铁路发展进入新阶段，铁路建设投资持续加大，相应周转量占比\n不断回升，重新成为大众最主要的出行方式。至 2023 年，铁路周转量占比提升至 51.5%，\n占比稳居首位。从出行方式增速看，2024 年上半年铁路周转量增速达到 14.1%，高基数下\n仍保持两位数以上增长。\n图1：2023 年，铁路周转量占比提升至 51.5%，稳居首位 图2：2024 年上半年，铁路周转量同比增长 14.1%\n资料来源：iFind，国家统计局，信达证券研发中心 资料来源：iFind，国家统计局，中国民用航空局，信达证券研发中心\n铁路客运中高速铁路营业里程及承运量均快速提升。2008 年以来，铁路营业里程稳步\n增长，高速铁路营业里程快速攀升。2008~2023 年，铁路营业里程年均增速为 4.7%，高速\n铁路营业里程年均增速高达 32.0%。截至 2023 年末，铁路营业里程增长至 15.9 万公里，\n其中高速铁路营业里程增至 4.5 万公里，占比达到 28.3%，对比 2008 年高铁营业里程占比\n0.8%提升显著。从旅客周转量看，高铁出行大众化普遍化的程度也在持续扩大。2008 至 2022\n年，高铁在铁路中的旅客周转量占比从仅有 0.2%快速增加至 66.7%。\n图3：至 2023 年，高铁营业里程占比提升至 28.3% 图4：至 2022 年，高铁旅客周转量占比增至 66.7%\n资料来源：iFind，交通运输部，国家统计局，信达证券研发中心 资料来源：iFind，交通运输部，国家统计局，信达证券研发中心\n请阅读最后一页免责声明及信息披露 http://www.cindasc.com 6\n7\n6\n5\n4\n3\n2\n1\n0\n0\n0\n0\n0\n0\n0\n0\n%\n%\n%\n%\n%\n%\n%\n%\n公水 路运 周周 转转 量量 占占 比比 铁民 路航 周周 转转 量量 占占\n1\n比比\n5\n3\n2\n1\n6\n. 3\n. 5\n. 0\n%\n%\n%\n2024H1各出行方式周转量累计同比增速\n40%\n33.6%\n35%\n30%\n25% 20.8%\n20%\n13.2% 14.1%\n15%\n10% 7.0%\n5%\n0%\n总客运 公路 铁路 水运 民航\n18 28.3% 30% 16000 66.7% 80%\n16 14000 70%\n25%\n14 12000 60%\n12 20%\n10000 50%\n10\n15% 8000 40%\n8\n6000 30%\n6 10%\n4000 20%\n4 0.2%\n0.8% 5% 2000 10%\n2\n0 0%\n0 0%\n8 9 0 1 2 3 4 5 6 7 8 9 0 1 2\n8 9 0 1 2 3 4 5 6 7 8 9 0 1 2 3 0 0 1 1 1 1 1 1 1 1 1 1 2 2 2\n0 0 1 1 1 1 1 1 1 1 1 1 2 2 2 2 0 0 0 0 0 0 0 0 0 0 0 0 0 0 0\n0 0 0 0 0 0 0 0 0 0 0 0 0 0 0 0 2 2 2 2 2 2 2 2 2 2 2 2 2 2 2\n2 2 2 2 2 2 2 2 2 2 2 2 2 2 2 2\n铁路旅客周转量（亿人公里） 高铁旅客周转量（亿人公里）\n铁路营业里程（万公里） 高铁营业里程（万公里）\n高铁营业里程占比 高铁周转量占比",
      "tables": [
        [
          [
            "0.8%"
          ],
          [
            ""
          ]
        ]
      ]
    },
    {
      "page_number": 7,
      "width": 595.32,
      "height": 841.92,
      "text": "1.2 公司：京沪线黄金资产，区位优势显著\n京沪高铁是国家“八纵八横”高速铁路主通道的组成部分，连接北京到上海的黄金通\n道，是国家战略性重大交通工程。京沪高铁于 2011 年 6 月 30 号建成通车，全长 1318 公\n里，共设置 24 个站点；线路纵横首都北京和经济中心上海，连接“京津冀”和“长三角”\n两大经济区，途经天津、济南、徐州、南京等多个省会城市及重要交通枢纽，沿线覆盖了中\n国经济发展最活跃和最具潜力的区域，运输需求旺盛，客运量增长迅猛，公司区位优势显著。\n图5：京沪高速铁路线路示意图\n资料来源：iFind，公司招股说明书，信达证券研发中心\n公司是国家重要铁路资产之一，股东资金实力雄厚。2007 年，公司由中国铁投、平安\n资管、社保基金、上海申铁、江苏交通、京投公司、津投公司、南京铁投、山东高速、河北\n建投、安徽投资等 11 名股东共同发起设立。2008 年 1 月 9 日，京沪高铁公司登记设立，\n主要从事京沪高速铁路的投资、建设和运营，通过委托运输管理模式开展高铁旅客运输等业\n务。2020 年 1 月 16 日，公司在上海证券交易所上市，登陆 A 股市场，公开发行股票不超\n过 62.86 亿股，募集资金总额 306.74 亿元，用于收购京福安徽公司 65.0759%的股权。\n请阅读最后一页免责声明及信息披露 http://www.cindasc.com 7",
      "tables": []
    },
    {
      "page_number": 8,
      "width": 595.32,
      "height": 841.92,
      "text": "表1：京沪高铁发起人出资及持股比例一览\n发起人 股份数（万股） 出资比例\n中国铁投 112,534.00 56.27%\n平安资管 27,826.00 13.91%\n社保基金 17,392.00 8.70%\n上海申铁 13,128.00 6.56%\n江苏交通 7,606.00 3.80%\n京投公司 6,668.00 3.33%\n津投公司 5,502.00 2.75%\n南京铁投 3,806.00 1.90%\n山东高速 3,230.00 1.62%\n河北建投 1,182.00 0.59%\n安徽投资 1,126.00 0.56%\n合计 200,000.00 100.00%\n资料来源：公司招股说明书，信达证券研发中心\n公司大股东为中国铁路投资集团，实际控制人为国铁集团。截至 2024 年 7 月 12 日，\n公司控股股东为中国铁路投资集团有限公司，持有公司股权 43.39%。中国国家铁路集团通\n过 100%控股中铁投集团控制京沪高铁，对公司享有实际控制权。\n图6：京沪高铁股权结构（截至 2024 年 7 月 12 日）\n资料来源：公司公告，iFind，信达证券研发中心\n公司“网运分离”模式上市，固定资产均为不动产，主要包括高铁线路、房屋建筑物、\n电气化供电设备等。截至 2023 年末，公司固定资产账面价值 2188 亿元，占期末总资产的\n74.89%，主要为线路及沿线配套设施等，其中高铁线路为最主要资产，在固定资产中占比\n84.8%。由于采用的是“网运分离”模式，公司并不拥有动车组列车资产，而是委托沿线铁\n路局进行运输组织、线路维护管理等工作。\n请阅读最后一页免责声明及信息披露 http://www.cindasc.com 8\n平 安 资 管\n6 . 4 2 %\n中 国 国\n中\n家\n国\n实\n铁\n铁有\n际\n路\n路限\n控\n集\n投公\n制\n4\n1\n资司\n3\n人\n团\n0\n.\n0\n3\n有\n%\n集\n9 %\n京\n团\n限\n福\n公\n安\n司\n徽\n6\n公\n5 . 0\n全\n7\n司\n5\n国\n9\n金\n%\n社\n理\n会\n事\n保\n6\n会\n. 2\n障\n4 %\n基\n4 3\n其\n. 9 5\n他\n%\n股 东",
      "tables": [
        [
          [
            "",
            "中国铁投",
            "",
            "",
            "112,534.00",
            "",
            "",
            "56.27%",
            ""
          ]
        ],
        [
          [
            "",
            "社保基金",
            "",
            "",
            "17,392.00",
            "",
            "",
            "8.70%",
            ""
          ]
        ],
        [
          [
            "",
            "江苏交通",
            "",
            "",
            "7,606.00",
            "",
            "",
            "3.80%",
            ""
          ]
        ],
        [
          [
            "",
            "津投公司",
            "",
            "",
            "5,502.00",
            "",
            "",
            "2.75%",
            ""
          ]
        ],
        [
          [
            "",
            "山东高速",
            "",
            "",
            "3,230.00",
            "",
            "",
            "1.62%",
            ""
          ]
        ],
        [
          [
            "",
            "安徽投资",
            "",
            "",
            "1,126.00",
            "",
            "",
            "0.56%",
            ""
          ]
        ]
      ]
    },
    {
      "page_number": 9,
      "width": 595.32,
      "height": 841.92,
      "text": "表2：京沪高铁主要固定资产一览（截至 2023 年末）\n固定资产类别（亿元） 原值 累计折旧 净值 净值占比 成新率\n线路 2,137.29 281.65 1,855.65 84.80% 86.82%\n信号设备 55.33 36.61 18.72 0.86% 33.84%\n通信设备 31.60 24.32 7.29 0.33% 23.05%\n房屋 199.51 43.64 155.88 7.12% 78.13%\n建筑物 107.32 36.74 70.59 3.23% 65.77%\n机械动力设备 14.92 12.32 2.60 0.12% 17.45%\n运输启运设备 3.99 2.24 1.75 0.08% 43.78%\n传导设备 46.44 18.75 27.69 1.27% 59.62%\n电气化供电设备 110.35 68.02 42.33 1.93% 38.36%\n仪器仪表 7.71 6.32 1.38 0.06% 17.94%\n工具及器具 10.20 8.21 1.98 0.09% 19.46%\n信息技术设备 24.22 21.74 2.49 0.11% 10.26%\n合计 2,748.89 560.55 2,188.34 100.00% 79.61%\n资料来源：公司招股说明书，公司公告，信达证券研发中心\n1.3 财务情况：经营稳健坐拥百亿利润，现金流充裕\n2019 年前，公司盈利及偿债能力持续提升，百亿现金流保障稳健经营，负债率逐年下\n降。凭借显著的区位优势及高铁出行需求的持续增加，公司盈利稳增，现金流保障充足，经\n营保持稳健。\n1）营收&归母净利表现：2019 年前，公司营收及归母净利保持稳步增长，归母净利同\n比增速保持在 10%以上。疫情期间受出行客流量减少影响，公司营收及净利出现较大波动\n下降。2023 年公司经营快速恢复，营收提升至 407 亿元，创历史新高，较 2019 年同期增\n长 16.7%，归母净利达到 115.46 亿元，较 2019 年同期+4.3%，恢复至疫情前水平。24H1，\n公司营收/归母净利分别为 209/63.57 亿元，同比分别+8.2%/+23.8%，较 2019 年同期分别\n+24.3%/+19.1%。\n2）毛利率&净利率情况：2019 年前，公司毛利率及净利率稳增且水平较高。2019 年\n前，公司毛利率及净利率分别稳定在 40%、30%以上，2019 年分别达到 47.9%、30.4%。\n疫情期间受到一定影响。2023 年公司毛利率及净利率双升，达到 45.8%、27.6%，基本快\n恢复至 2019 年水平。24H1 毛利率、净利率进一步回升，分别为 47.4%、30.2%。\n3）经营性现金流及负债情况：由于公司客户群体多为公商务旅客，需求较为刚性，客\n流稳定。且高铁出行大众化程度不断提升，我们预计公司经营可保持长期稳健，保障经营性\n现金流充裕。2019 年前，公司经营性现金流净额基本维持在 130 亿元以上；高现金流保障\n下，公司资产负债率保持下降，2019 年降低至 14.3%。疫情期间负债率提升较多，但 2023\n年已有大幅降低。至 24H1 末，公司负债率降低至 22.9%。\n请阅读最后一页免责声明及信息披露 http://www.cindasc.com 9",
      "tables": [
        [
          [
            "",
            "线路",
            "",
            "",
            "2,137.29",
            "",
            "",
            "281.65",
            "",
            "",
            "1,855.65",
            "",
            "",
            "84.80%",
            "",
            "",
            "86.82%",
            ""
          ]
        ],
        [
          [
            "",
            "通信设备",
            "",
            "",
            "31.60",
            "",
            "",
            "24.32",
            "",
            "",
            "7.29",
            "",
            "",
            "0.33%",
            "",
            "",
            "23.05%",
            ""
          ]
        ],
        [
          [
            "",
            "建筑物",
            "",
            "",
            "107.32",
            "",
            "",
            "36.74",
            "",
            "",
            "70.59",
            "",
            "",
            "3.23%",
            "",
            "",
            "65.77%",
            ""
          ]
        ],
        [
          [
            "",
            "运输启运设备",
            "",
            "",
            "3.99",
            "",
            "",
            "2.24",
            "",
            "",
            "1.75",
            "",
            "",
            "0.08%",
            "",
            "",
            "43.78%",
            ""
          ]
        ],
        [
          [
            "",
            "电气化供电设备",
            "",
            "",
            "110.35",
            "",
            "",
            "68.02",
            "",
            "",
            "42.33",
            "",
            "",
            "1.93%",
            "",
            "",
            "38.36%",
            ""
          ]
        ],
        [
          [
            "",
            "工具及器具",
            "",
            "",
            "10.20",
            "",
            "",
            "8.21",
            "",
            "",
            "1.98",
            "",
            "",
            "0.09%",
            "",
            "",
            "19.46%",
            ""
          ]
        ],
        [
          [
            "",
            "合计",
            "",
            "",
            "2,748.89",
            "",
            "",
            "560.55",
            "",
            "",
            "2,188.34",
            "",
            "",
            "100.00%",
            "",
            "",
            "79.61%",
            ""
          ]
        ]
      ]
    },
    {
      "page_number": 10,
      "width": 595.32,
      "height": 841.92,
      "text": "图7：24H1 公司营业收入 209 亿元，较 2019 年同期+24.3% 图8：24H1 公司归母净利 63.6 亿元，较 2019 年同期+19.1%\n450 407 30% 140 14.6% 49.1% 60%\n3 4 5 0 0 0 12 2 . 9 6 6 % 312 34 1 9 1.9% 16 2 . 9 1 3 % 16.7% 24.3% 1 2 0 0 % % 1 1 0 2 0 0 90.53 102.48 110.6 8 8 .0% 1 4 1 . 5 3 . % 46 19.1% 2 40 0 % %\n2 3 5 0 0 0 263 5.4% 252 209 0% 80 79.03 13.2% 63.57 - 0 2 % 0%\n193 60 48.16 -40%\n200 -10%\n150\n40 32.29 -60%\n100 -34.0% -20% 20 -70.8% -112.0% - - 1 8 0 0 0 % %\n50 -27.6% -30% 0 -120%\n0 -40% -20 -5.76 -140%\n营业收入(亿元） 同比增速-右轴 归母净利润（亿元） 同比增速-右轴\n资料来源：iFind，公司公告，信达证券研发中心 资料来源：iFind，公司公告，信达证券研发中心\n注：2023 年和24H1 为较2019 年同期增速 注：2023 年和24H1 为较2019 年同期增速\n图9：2019 年前，公司毛利率/净利率基本在 40%/30%以上 图10：公司经营性净现金流基本稳定在百亿以上\n资料来源：iFind，信达证券研发中心 资料来源：iFind，信达证券研发中心\n请阅读最后一页免责声明及信息披露 http://www.cindasc.com 10\n-\n-\n6\n5\n4 3\n2\n1\n1\n2\n0\n0\n0 0\n0\n0\n0\n0\n0\n%\n%\n% %\n%\n%\n%\n%\n%\n4\n3\n2\n0\n.\n.\n3\n1\n%\n%\n4 6 . 1 %\n3 2\n4\n.\n7\n9\n.\n%\n7 %\n毛\n4\n3\n7\n0\n利\n.\n.\n9\n4\n%\n%\n9\n率\n. 9\n3\n%\n1 . 3 %\n3\n1\n净\n5\n4\n. 8\n. 4\n利\n%\n%\n率\n1\n- 8\n3\n.\n4\n.\n0\n5\n5\n%\n%\n. 8 %\n2 7 . 6 %\n4 7\n3\n. 4\n0\n%\n. 2 %\n2\n2\n1\n1\n5\n0\n5\n0\n5\n0\n0\n0\n0\n0\n0\n1\n2\n4\n1\n2\n4\n8\n. 5\n. 8\n经\n%\n1\n%\n4\n营\n9\n性\n1\n净\n1\n5\n3 8\n. 7\n现\n%\n金\n1\n流\n6 7\n1\n（\n4\n3\n. 3\n亿\n0\n1\n%\n. 7\n2\n元\n%\n6\n）\n1 5\n2\n5\n8 . 2 %\n6\n资\n8\n产\n2\n2\n5\n负\n1\n. 4\n1\n%\n债 率\n2 2\n1\n-\n.\n0\n右\n9\n3\n%\n轴\n3\n3\n2 2\n1\n1\n5\n0\n5\n0\n5 0\n5\n0\n%\n%\n%\n%\n% %\n%\n%",
      "tables": []
    },
    {
      "page_number": 11,
      "width": 595.32,
      "height": 841.92,
      "text": "2 收入源自客票及路网服务，成本整体较稳定\n2.1 业务模式：按是否担当列车分为本线及跨线业务\n京沪高铁公司是京沪高速铁路及沿线车站的投资、建设、运营主体，主营业务为高铁\n旅客运输。公司运营京沪高速铁路，通过委托沿线的北京局、济南局、上海局对京沪高速铁\n路进行运输管理，并支付相应委托管理费用等。按照是否担当列车，公司主要业务可分为客\n运业务和路网服务业务两部分。\n1）旅客运输业务：客票业务主要是公司为乘坐担当列车的旅客提供高铁运输服务并收\n取票价款，业务主要采用委托管理模式，服务对象为列车旅客。沿线受托铁路局集团向公司\n提供动车组使用服务及相关工作人员，为本线 24 个站点间的旅客提供运输服务，公司则向\n受托铁路局支付相关委托管理费用、动车组使用费及动车组列车服务费等。\n2）提供路网服务业务：提供路网服务业务的服务对象则是其他铁路运输企业担当的列\n车。非担当列车在京沪高速铁路上运行时，公司向其提供线路使用、接触网使用等服务并收\n取相应费用等，公司需承担相应的能源电力、水费等支出。\n图11：京沪高铁业务模式一览\n资料来源：公司公告，信达证券研发中心\n从运营情况看，本线发车列次低于跨线列次，但列均旅客量更高。本线车为公司担当\n列车，跨线车则为其他铁路运输企业的非担当列车。2016~2019 年，本线车列次略有降低，\n但列均旅客量持续增长，主要是受客座率提升及长编列车增加影响；跨线发车列次持续增长，\n较本线车列次倍数由 2.6 增至 4.2，京沪线车次结构上跨线车占比逐渐增加。\n图12：公司跨线车列次多于本线车列次，且增速更快 图13：公司本线列均旅客量高于跨线列均旅客量\n资料来源：iFind，公司招股说明书，公司公告，信达证券研发中心 资料来源：iFind，公司招股说明书，公司公告，信达证券研发中心\n请阅读最后一页免责声明及信息披露 http://www.cindasc.com 11\n京营 沪业 高收 铁入 委 托\n旅业\n管\n提服\n客务\n理\n供务\n运收\n路收\n输入\n网入\n受 托 铁 路 局\n跨\n本\n线\n线\n非\n委\n担\n动\n客\n担\n托\n当\n车\n运\n当\n运\n列\n组\n服\n列\n输\n车\n使\n务\n车\n管\n用\n费\n理\n费\n用\n费\n等\n、\n取\n收运接\n得\n取输触 跨企网\n高\n折支保\n线业使\n铁\n旧出障\n的的用\n票\n支、费\n其线费\n价\n出高等\n他路等\n收\n、铁资\n铁使\n入\n能运源\n路用\n源输型\n、\n电能支\n服车\n服路\n力力出\n务上\n务的\n对的\n对其\n象旅\n象他\n成本费用\n：客\n：铁\n担\n使路\n当\n用公\n列\n线司\n16 15.13 4.5 1600 1481\n14 12.57 13.32 4.2 4.0 1400 1273 1337 1375\n3.5\n12 10.41 3.2 3.4 1200 1036 1069\n10 2.6 3 2 . . 0 5 1000 956 987\n8\n2.0 800\n6\n4.00 3.96 3.93 3.60 1.5 600\n4\n1.0 400\n2 0.5\n200\n0 0.0\n2016 2017 2018 2019 0\n2016 2017 2018 2019\n本线列次（万列） 跨线列次（万列）\n跨线车对比本线车倍数 本线列均旅客数（人） 跨线列均旅客数（人）",
      "tables": []
    },
    {
      "page_number": 12,
      "width": 595.32,
      "height": 841.92,
      "text": "从财务情况看，2019 年前，两大主营业务收入基本对半，跨线路网服务业务毛利占比\n约六成。从营收情况看，2019 年前旅客运输业务（本线业务）与提供路网服务业务（跨线\n业务）收入约各占一半；此后跨线业务占比逐渐增加，至 2023 年，公司本线业务、跨线业\n务收入分别为 160.8、242.2 亿元，占比分别为 39.5%、59.5%。\n从毛利情况看，2019 年前路网服务业务毛利及毛利率高于旅客运输业务。公司提供路\n网服务业务的毛利率基本在 60%左右，旅客运输业务毛利率约 30%~40%；2019Q1~3，公\n司本线业务、跨线业务毛利分别 50.1、79.1 亿元，占比分别 38.1%、60.2%，提供路网服\n务业务毛利贡献能力更强。\n图14：公司提供路网服务收入占比逐渐提升至六成 图15：2019 年前，公司提供路网服务业务毛利占比约六成\n资料来源：iFind，公司公告，信达证券研发中心 资料来源：iFind，公司招股说明书，信达证券研发中心\n2.2 本线业务：收入源自担当列车的客票收入\n旅客运输业务收入来自京沪线本线担当列车旅客支付的票价款，因而取决于高铁票价\n及旅客量情况，或按照单位客公里收益及旅客周转量情况计算。公司采用独特的“网运分\n离”模式上市，将铁路路网基础设施与运输服务分离，即公司仅拥有线路、土地、车站等基\n础设施，并不拥有动车组列车资产；公司对基础设施等进行管理维护，需要支付相应的能源\n支出、折旧支出、运输保障费等。提供运输服务及运输工具的则是公司委托的沿线其他铁路\n局，公司需向受托铁路局支付相应的委托运输管理费及动车组使用费等。2019 年及 2023\n年，公司委托运输管理费及动车组使用费成本合计在营业成本中占比分别为 50.02%和\n47.37%。\n图16：京沪高铁旅客运输业务模式\n资料来源：公司公告，信达证券研发中心\n请阅读最后一页免责声明及信息披露 http://www.cindasc.com 12\n4\n4\n3\n3\n2\n2\n1\n1\n5\n0\n5\n0\n5\n0\n5\n0\n5\n0\n0\n0\n0\n0\n0\n0\n0\n0\n0\n1\n1\n2\n1\n4\n0\n其\n旅\n9\n1\n1\n. 1\n. 9\n6\n他\n客\n收\n运\n5\n1\n1\n2\n4\n3\n5\n0\n入\n输\n. 0\n8\n5\n1\n%\n. 1\n. 7\n7\n（\n收\n5\n亿\n入\n5 0 .\n2 . 7\n1 5\n1 5\n2 0\n元\n（\n7\n%\n1\n7\n1\n）\n亿\n%\n. 0\n. 9\n8\n元\n1\n1\n2\n）\n8\n5\n0\n8\n6\n1\n4\n. 7\n. 8\n9\n5 . 0\n3\n%\n0\n1\n7\n2\n.\n7\n6\n0\n1\n2\n.\n2\n%\n. 3\n1\n0\n1 8\n9 9\n2 0\n提\n旅\n3 4\n8 . 8\n. 7\n2 1\n供\n客\n. 0\n路\n运\n%\n2 6\n1\n5\n2\n网\n输\n. 4 %\n3 8 . 8\n1 . 0\n0 2 2\n服\n收\n务\n入\n3 9\n2\n1\n2\n收\n占\n. 5\n4 2\n6 0\n0 2\n入\n比\n%\n. 2\n. 8\n3\n（\n- 右\n亿\n轴\n6\n5\n4\n3\n2\n1\n0\n元\n0\n0\n0\n0\n0\n0\n%\n%\n%\n%\n%\n%\n%\n）\n160 39%\n38.5%\n140\n38.1% 38% 120 37.7%\n100 82.0 89.9 79.1 37%\n80\n69.8\n60 36%\n35.8% 40\n35% 52.4 56.1 50.1\n20 39.8\n0 34%\n2016 2017 2018 2019Q1-3\n其他业务毛利（亿元） 提供路网服务毛利（亿元）\n旅客运输毛利（亿元） 旅客运输毛利占比-右轴\n旅客运输业务收入=高铁票价×旅客量\n=单位客公里收入×旅客周转量\n委托管理，支付委托运输\n产品设计， 管理费、动车组使用费等 统筹组织\n编制运行 京沪高铁公司 受托铁路局 管理列车，\n图等 服务旅客等\n提供动车组列\n支付乘坐列车 车及服务人员，\n所需的客票费用 提供运输服务\n京沪线本线担当列车旅客",
      "tables": []
    },
    {
      "page_number": 13,
      "width": 595.32,
      "height": 841.92,
      "text": "票价定价标准：高铁票价定价经过了较长时间的市场化机制改革，定价权逐渐由政府\n部门过渡到铁路运输企业。2007 年原铁道部发布通知，明确规定了时速 110 公里以上的动\n车组列车软座票价基准价为每公里一等座 0.3366 元 /人公里、二等座 0.2805 元/人公里，\n允许铁路运输企业上下浮动 10%定价；此后投入运营的普通动车组列车大多按照上述标准\n执行。因而这一时段的铁路票价基本是由政府部门管控，实施的多为固定票价。\n2015 年底，国家发改委发布《关于改革完善高铁动车组旅客票价政策的通知》，明确了\n铁路运输企业可以依据价格法律法规自主制定时速 200 公里以上的高铁动车组列车一、二\n等座旅客票价；铁路票价定价权由政府部门过渡到铁路运输企业。此后，铁总（现在的国铁\n集团）及旗下各铁路局开始根据各车次客流状况、运营成本等，进行差异化的票价调整，浮\n动的差异化市场调价机制逐渐推广开来。\n表3：中国铁路客运票价政策推进进程\n时间 出台部门 政策通知 重点内容\n 规定旅行速度达到每小时110公里以上的动车组列车软座票价基准价\n为每公里一等座 0.3366 元 /人公里、二等座 0.2805 元/人公里，允许\n2007 年 原铁道部 《关于动车组票价有关 铁路运输企业在上下 10%范围内自主确定具体票价水平。\n事项的通知》\n 广深线上的动车组列车票价可在国铁统一运价为中准价上下浮动\n50%的基础上再上下浮动 50%，由企业自主定价。\n《国家发展改革委、铁道\n国家发改委 京津城际轨道交通新开行的时速 300-350 公里动车组列车实行试行运\n2008 年 部关于京津城际轨道交\n原铁道部 价。试行运价水平由京津城际铁路有限公司根据市场供求状况自主确定\n通运价有关问题的通知》\n《关于改革完善高铁动\n铁路运输企业获得了对设计时速 200 公里以上的高铁动车组列车一、二\n2015 年 国家发改委 车组旅客票价政策的通\n等座旅客票价的自主制定权，自 2016 年 1 月 1 日起执行\n知》\n《国家发展改革委关于\n在中央管理企业全资及控股铁路上开行的普通旅客列车软座、软卧票\n完善铁路普通旅客列车\n2016 年 国家发改委 价，由铁路运输企业依法自主制定；普通旅客列车高级软卧包房票价继\n软座、软卧票价形成机制\n续实行市场调节价。自 2016 年 6 月 20 日起执行\n有关问题的通知》\n国铁集团前\n2017 年 4 月 21 日起，东南沿海高铁时速 200 至 250 公里动车组列车\n2017 年 身中国铁路 铁总公告\n的票价将进行调整，中国高铁第一次跨省调价\n总公司\n资料来源：12306，国家发改委，新华网，中国政府网，信达证券研发中心\n多条铁路路段已实施浮动票价机制，票价更加遵循市场化原则。铁路票价定价权转交\n至铁路运输企业后，各地铁路局根据各自路段的市场运营情况，逐渐开始实施更为市场化的\n定价策略。各线路每次调价后，公布票价（即票价上限）基本平均上涨 20%，但下限票价\n也有一定下降，票价有升有降、可调节空间扩大，差异化的折扣浮动定价机制逐渐成熟。\n2020 年 10 月，京沪高铁发布公告，明确自 2020 年 12 月 23 日起，实施浮动票价机制，\n对时速 300～350 公里高铁动车组列车票价进行调整。执行票价将以公布票价为上限，其中\n二等座票价最高 9.04 折、最低 7.52 折，即最高执行票价调整为 598 元，最低执行票价调整\n为 498 元，商务座、特等座和一等座与二等座的比价关系分别按照 3.5 倍、1.8 倍和 1.6 倍\n执行。京沪高铁北京南站~上海虹桥站间区间列车参照全程列车执行票价按照运行距离对应\n调整执行票价。\n请阅读最后一页免责声明及信息披露 http://www.cindasc.com 13",
      "tables": [
        [
          [
            "2007年",
            "原铁道部",
            "《关于动车组票价有关 事项的通知》",
            "",
            " 规定旅行速度达到每小时110公里以上的动车组列车软座票价基准价",
            ""
          ],
          [
            "",
            "",
            "",
            "",
            "为每公里一等座0.3366元 /人公里、二等座0.2805元/人公里，允许",
            ""
          ],
          [
            "",
            "",
            "",
            "",
            "铁路运输企业在上下10%范围内自主确定具体票价水平。",
            ""
          ],
          [
            "",
            "",
            "",
            "",
            " 广深线上的动车组列车票价可在国铁统一运价为中准价上下浮动",
            ""
          ],
          [
            "",
            "",
            "",
            "",
            "50%的基础上再上下浮动50%，由企业自主定价。",
            ""
          ]
        ],
        [
          [
            "《关于动车组票价有关"
          ],
          [
            "事项的通知》"
          ]
        ],
        [
          [
            "2015年",
            "国家发改委",
            "《关于改革完善高铁动 车组旅客票价政策的通 知》",
            "铁路运输企业获得了对设计时速200公里以上的高铁动车组列车一、二 等座旅客票价的自主制定权，自2016年1月1日起执行"
          ]
        ],
        [
          [
            "《关于改革完善高铁动"
          ],
          [
            "车组旅客票价政策的通"
          ],
          [
            "知》"
          ]
        ],
        [
          [
            "铁路运输企业获得了对设计时速200公里以上的高铁动车组列车一、二"
          ],
          [
            "等座旅客票价的自主制定权，自2016年1月1日起执行"
          ]
        ],
        [
          [
            "2017年",
            "国铁集团前 身中国铁路 总公司",
            "铁总公告",
            "2017年4月21日起，东南沿海高铁时速200至250公里动车组列车 的票价将进行调整，中国高铁第一次跨省调价"
          ]
        ],
        [
          [
            "国铁集团前"
          ],
          [
            "身中国铁路"
          ],
          [
            "总公司"
          ]
        ],
        [
          [
            "2017年4月21日起，东南沿海高铁时速200至250公里动车组列车"
          ],
          [
            "的票价将进行调整，中国高铁第一次跨省调价"
          ]
        ]
      ]
    },
    {
      "page_number": 14,
      "width": 595.32,
      "height": 841.92,
      "text": "表4：实施浮动票价的铁路线路路段及对象一览\n公布票价\n序号 发布时间 调整时点 调整线路及对象 定价策略\n（元）\n京广高铁武广段上运行的时速\n1 2024.5.2 2024.6.15 执行票价将以公布票价为上限、5.5 折为下限 553\n300 公里及以上动车组列车\n沪昆高铁沪杭段上运行的时速\n2 2024.5.2 2024.6.15 执行票价将以公布票价为上限、5.5 折为下限 87\n300 公里及以上动车组列车\n沪昆高铁杭长段上运行的时速\n3 2024.5.2 2024.6.15 执行票价将以公布票价为上限、5.5 折为下限 485\n300 公里及以上动车组列车\n杭深铁路杭甬段上运行的时速\n4 2024.5.2 2024.6.15 执行票价将以公布票价为上限、5.5 折为下限 76\n300 公里及以上动车组列车\n时速 300 公里动车组列车的执行票价初期将\n以公布票价为上限、7.43 折为下限；时速 250\n5 2023.8.26 2023.10.11 贵广客专上运行的动车组列车 364\n公里动车组列车的执行票价初期实行 8.3 折，\n与现执行票价水平相当\n6 2023.4.15 2023.5.30 胶济客专上运行的动车组列车 执行票价将以公布票价为上限、6.6 折为下限 146\n沪宁城际上运行的时速 300 公\n7 2023.4.15 2023.5.30 执行票价将以公布票价为上限、6.6 折为下限 166\n里及以上动车组列车\n8 2023.4.15 2023.5.30 南广高铁上运行的动车组列车 执行票价将以公布票价为上限、6.6 折为下限 255\n宁杭高铁上运行的时速 300 公\n9 2023.4.15 2023.5.30 执行票价将以公布票价为上限、6.6 折为下限 141\n里及以上动车组列车\n10 2023.4.15 2023.5.30 柳南客专上运行的动车组列车 执行票价将以公布票价为上限、6.6 折为下限 99\n京广高铁京武段上运行的动车 执行票价将以公布票价为上限、6.58 折为下\n11 2022.5.13 2022.6.20 623\n组列车 限（较现票价低 21%）\n郑渝高铁渝万段上运行的动车 执行票价将以公布票价为上限、6.68 折为下\n12 2022.4.16 2022.5.20 117\n组列车 限\n13 2022.2.25 2022.4.10 宁安城际上运行的动车组列车 执行票价将以公布票价为上限、6.6 折为下限 114\n14 2022.2.25 2022.4.16 青荣城际上运行的动车组列车 执行票价将以公布票价为上限、6.6 折为下限 111\n海南环岛高铁上运行的动车组\n15 2022.2.25 2022.4.10 执行票价将以公布票价为上限、6.6 折为下限 129\n列车\n16 2021.11.27 2022.1.10 邕北高铁上运行的动车组列车 执行票价将以公布票价为上限、6.7 折为下限 73\n南广高铁上运行的时速 250 公\n17 2021.3.18 2021.4.30 执行票价将以公布票价为上限、5.5 折为下限 212\n里动车组列车\n厦深高铁上运行的时速 250 公 执行票价将以公布票价为上限，初期二等座\n18 2021.2.25 2021.4.10 228\n里高铁动车组列车 票价最高 9.6 折、最低 5.5 折\n京沪高铁上运行的时速 300～ 执行票价将以公布票价为上限，二等座票价\n19 2020.10.24 2020.12.23 662\n350 公里高铁动车组列车 最高 9.04 折、最低 7.52 折\n成渝高铁上运行的时速 300～ 执行票价将以公布票价为上限，二等座票价\n20 2020.10.24 2020.12.23 175\n350 公里高铁动车组列车 最高 9.6 折、最低 8.3 折\n贵阳至广州、柳州至南宁、武\n汉至宜昌、上海至南京、南京\n执行票价以公布票价为最高限价，最低 6.5\n21 2018.5.5 2018.7.5 至武汉、南京至杭州 6 段线路 -\n折\n上运行时速 200～250 公里的高\n铁动车组\n资料来源：12306，信达证券研发中心\n请阅读最后一页免责声明及信息披露 http://www.cindasc.com 14",
      "tables": [
        [
          [
            "1",
            "2024.5.2",
            "2024.6.15",
            "京广高铁武广段上运行的时速 300公里及以上动车组列车",
            "执行票价将以公布票价为上限、5.5折为下限",
            "553"
          ]
        ],
        [
          [
            "京广高铁武广段上运行的时速"
          ],
          [
            "300公里及以上动车组列车"
          ]
        ],
        [
          [
            "3",
            "2024.5.2",
            "2024.6.15",
            "沪昆高铁杭长段上运行的时速 300公里及以上动车组列车",
            "执行票价将以公布票价为上限、5.5折为下限",
            "485"
          ]
        ],
        [
          [
            "沪昆高铁杭长段上运行的时速"
          ],
          [
            "300公里及以上动车组列车"
          ]
        ],
        [
          [
            "5",
            "2023.8.26",
            "2023.10.11",
            "贵广客专上运行的动车组列车",
            "",
            "时速 300 公里动车组列车的执行票价初期将",
            "，",
            "364"
          ],
          [
            "",
            "",
            "",
            "",
            "",
            "以公布票价为上限、7.43折为下限；时速250",
            "",
            ""
          ],
          [
            "",
            "",
            "",
            "",
            "",
            "公里动车组列车的执行票价初期实行8.3折",
            "",
            ""
          ],
          [
            "",
            "",
            "",
            "",
            "",
            "与现执行票价水平相当",
            "",
            ""
          ]
        ],
        [
          [
            "7",
            "2023.4.15",
            "2023.5.30",
            "沪宁城际上运行的时速 300 公 里及以上动车组列车",
            "执行票价将以公布票价为上限、6.6折为下限",
            "166"
          ]
        ],
        [
          [
            "沪宁城际上运行的时速 300 公"
          ],
          [
            "里及以上动车组列车"
          ]
        ],
        [
          [
            "9",
            "2023.4.15",
            "2023.5.30",
            "宁杭高铁上运行的时速 300 公 里及以上动车组列车",
            "执行票价将以公布票价为上限、6.6折为下限",
            "141"
          ]
        ],
        [
          [
            "宁杭高铁上运行的时速 300 公"
          ],
          [
            "里及以上动车组列车"
          ]
        ],
        [
          [
            "11",
            "2022.5.13",
            "2022.6.20",
            "京广高铁京武段上运行的动车 组列车",
            "执行票价将以公布票价为上限、6.58 折为下 限（较现票价低21%）",
            "623"
          ]
        ],
        [
          [
            "京广高铁京武段上运行的动车"
          ],
          [
            "组列车"
          ]
        ],
        [
          [
            "执行票价将以公布票价为上限、6.58 折为下"
          ],
          [
            "限（较现票价低21%）"
          ]
        ],
        [
          [
            "13",
            "2022.2.25",
            "2022.4.10",
            "宁安城际上运行的动车组列车",
            "执行票价将以公布票价为上限、6.6折为下限",
            "114"
          ]
        ],
        [
          [
            "15",
            "2022.2.25",
            "2022.4.10",
            "海南环岛高铁上运行的动车组 列车",
            "执行票价将以公布票价为上限、6.6折为下限",
            "129"
          ]
        ],
        [
          [
            "海南环岛高铁上运行的动车组"
          ],
          [
            "列车"
          ]
        ],
        [
          [
            "17",
            "2021.3.18",
            "2021.4.30",
            "南广高铁上运行的时速 250 公 里动车组列车",
            "执行票价将以公布票价为上限、5.5折为下限",
            "212"
          ]
        ],
        [
          [
            "南广高铁上运行的时速 250 公"
          ],
          [
            "里动车组列车"
          ]
        ],
        [
          [
            "19",
            "2020.10.24",
            "2020.12.23",
            "京沪高铁上运行的时速 300～ 350公里高铁动车组列车",
            "执行票价将以公布票价为上限，二等座票价 最高9.04折、最低7.52折",
            "662"
          ]
        ],
        [
          [
            "京沪高铁上运行的时速 300～"
          ],
          [
            "350公里高铁动车组列车"
          ]
        ],
        [
          [
            "执行票价将以公布票价为上限，二等座票价"
          ],
          [
            "最高9.04折、最低7.52折"
          ]
        ],
        [
          [
            "21",
            "2018.5.5",
            "2018.7.5",
            "",
            "贵阳至广州、柳州至南宁、武",
            "",
            "执行票价以公布票价为最高限价，最低 6.5 折",
            "-"
          ],
          [
            "",
            "",
            "",
            "",
            "汉至宜昌、上海至南京、南京",
            "",
            "",
            ""
          ],
          [
            "",
            "",
            "",
            "",
            "至武汉、南京至杭州 6 段线路",
            "",
            "",
            ""
          ],
          [
            "",
            "",
            "",
            "",
            "上运行时速200～250公里的高",
            "",
            "",
            ""
          ],
          [
            "",
            "",
            "",
            "",
            "铁动车组",
            "",
            "",
            ""
          ]
        ],
        [
          [
            "执行票价以公布票价为最高限价，最低 6.5"
          ],
          [
            "折"
          ]
        ]
      ]
    },
    {
      "page_number": 15,
      "width": 595.32,
      "height": 841.92,
      "text": "京沪高铁此前近十年提速未调价，实施浮动票价后二等座全票价上涨约 20%。2011 年\n6 月底，京沪高铁开通运行，实行时速 300 公里和 250 公里混跑模式，当时全程票价标准\n为：时速 300 公里动车组列车二等座全票价为 555 元，时速 250 公里动车组列车二等座全\n票价为 410 元。2017 年 6 月，时速 350 公里“复兴号”动车组列车在京沪高铁线首发投入\n使用，时速提升票价却并未上调。2020 年 12 月 23 日后，京沪高铁对时速 300～350 公里\n高铁动车组列车开始实施浮动票价机制，二等座全票价上调至 662 元，较此前全票价上涨\n19.71%。但由于浮动票价机制，二等座票价下限也下调至 498 元。\n表5：京沪高铁票价标准变化\n时间 京沪线列车组类别 项目 二等座 一等座 商务座\n时速 250 动车组 全线票价（元） 410 650 -\n列车 平均费率（元/公里） 0.31 0.49 -\n2011 年 6 月\n时速 300 动车组 全线票价（元） 555 935 1750\n列车 平均费率（元/公里） 0.42 0.71 1.33\n2020 年 12 月 23 时速 300~350 动车 全线票价（元） 553 933 1748\n日前 组列车 平均费率（元/公里） 0.42 0.71 1.33\n2020 年 12 月 23 时速 300~350 动车 全线票价（元） 662 1060 2318\n日后（浮动票价） 组列车 平均费率（元/公里） 0.50 0.80 1.76\n资料来源：12306，中国政府网，央视网，信达证券研发中心\n与主要竞争对手航空公司对比，京沪线高铁票价显著低于飞机票价。京沪高铁实施浮\n动票价前后，对比航空公司票价均具备较强价格优势。此前京沪航线经济舱全票价已经过多\n轮调价，全票价累计涨幅达到 73.4%，基本每次调价上调 10%。对比京沪高铁二等座全票\n价看，仅在 2020 年 12 月 23 日起，票价由 553 元上调至 662 元，涨幅为 19.7%。高铁票\n对飞机票的折扣幅度由此前的 45%加大至 31%，价格优势更加显著；且高铁提速后，京沪\n高铁线全程用时最快可以达到 4 小时 18 分，时间效率也有较大提升。\n图17：京沪高铁二等座全票价对飞机经济舱全票价折扣幅度加大至三折\n资料来源：公司公告，12306，澎湃新闻，中国民用航空网，第一财经，信达证券研发中心\n请阅读最后一页免责声明及信息披露 http://www.cindasc.com 15\n2\n2\n1\n1\n5\n0\n5\n0\n5\n0\n0\n0\n0\n0\n0\n0\n0\n0\n0\n0\n1\n原\n2\n4\n4\n5\n始\n0\n%\n5\n京\n高\n5\n价\n3\n沪\n铁\n航\n票\n线\n价\n1\n2\n4\n3\n0\n经\n对\n6\n1\n1 %\n0\n5\n8\n济\n飞\n-\n5\n0\n舱\n机\n3\n6\n全\n票\n价\n价\n1\n2\n票\n折\n3\n4\n0\n7\n9\n1\n（\n扣\n0\n8\n%\n5 5\n- 1\n元\n幅\n3\n2\n）\n度\n1\n2\n6\n0\n3\n3\n2\n0\n4\n0\n5\n%\n-\n5\n0\n3\n1\n京 沪 高\n2\n1\n0\n铁\n9\n3\n2\n6\n4\n2\n二\n0\n%\n-\n6\n1\n6\n1\n等\n2\n前\n座 全 票\n2\n2\n1\n0\n价\n5\n2\n0\n3\n6\n2\n（\n-\n1\n6\n1\n%\n2\n1\n元 ）\n5\n4\n4\n3\n3\n2\n2\n1\n1\n5\n0\n0\n5\n0\n5\n0\n5\n0\n5\n0\n%\n%\n%\n%\n%\n%\n%\n%\n%\n%\n%",
      "tables": [
        [
          [
            "时速250动车组 列车",
            "",
            "全线票价（元）",
            "",
            "",
            "410",
            "",
            "650",
            "",
            "",
            "-",
            ""
          ],
          [
            "",
            "",
            "全线票价（元）",
            "",
            "",
            "555",
            "",
            "935",
            "",
            "",
            "1750",
            ""
          ]
        ],
        [
          [
            "时速300~350动车 组列车",
            "",
            "全线票价（元）",
            "",
            "",
            "553",
            "",
            "933",
            "",
            "",
            "1748",
            ""
          ],
          [
            "",
            "",
            "全线票价（元）",
            "",
            "",
            "662",
            "",
            "1060",
            "",
            "",
            "2318",
            ""
          ]
        ]
      ]
    },
    {
      "page_number": 16,
      "width": 595.32,
      "height": 841.92,
      "text": "旅客量情况：本线旅客量人数微增，周转量增长。从本线旅客量情况看，2019 年前旅\n客量较稳定，基本保持在 5300~5400 万人次左右，2023 年本线旅客量达到 5325 万人次，\n基本恢复到 2019 年同期水平。周转量情况看，2019 年前本线周转量保持增长。\n图18：2019 年前，公司本线发送旅客量微增 图19：2019 年前，公司本线周转量保持增长\n资料来源：iFind，公司公告，公司招股说明书，信达证券研发中心\n资料来源：iFind，公司招股说明书，信达证券研发中心\n注：2023 年为较2019 年同期增速\n2.3 跨线业务：收入源自其他铁路企业支付的路网使用费\n提供路网服务业务收入来自跨线的其他铁路企业支付的路网使用费。公司拥有路网基\n础设施，当其他铁路运输企业运行的公司非担当列车跨线途经京沪线时，需要向公司支付相\n应的线路使用、接触网使用费用等，跨线列车的旅客票价款收入则归属其他运输企业。公司\n获得跨线的路网租用费，同时需要承担线路的能源支出、折旧支出、高铁运输能力保障费用\n等。2019 年及 2023 年，公司能源成本及折旧成本合计在营业成本中占比分别为 39.51%和\n41.08%。\n图20：京沪高铁提供路网服务业务模式\n资料来源：公司公告，信达证券研发中心\n提供路网服务业务细项收入中，线路使用及接触网使用收入占比 90%以上。2016~2019\n年，公司提供路网业务收入保持较快增长，年均复合增速达到 16.6%，超过旅客运输业务收\n入年均增速 3.4%。具体细项收入看，路网服务业务收入中包含线路使用服务、接触网使用\n服务、车站旅客服务、售票服务、车站上水服务等业务收入，其中最主要业务收入为线路使\n用服务收入和接触网使用服务收入，2023 年分别占比 62.5%和 28.4%。\n请阅读最后一页免责声明及信息披露 http://www.cindasc.com 16\n6\n5\n4\n3\n2\n1\n0\n0\n0\n0\n0\n0\n0\n0\n0\n0\n0\n0\n0\n0\n0\n0\n0\n0\n0\n5 0 9 8\n4\n本\n. 0\n5\n%\n线\n3 0\n发\n0\n送\n5\n1\n旅\n3\n. 9\n9\n%\n客\n8\n量\n5\n（\n3 3\n万\n3\n京\n公上折铁障\n-\n人\n1\n-\n.\n2\n4\n沪\n司的旧运费\n2\n7\n次\n7\n%\n.\n7\n9\n）\n高\n承能支输等\n7\n%\n铁\n担源出能费\n3 5\n公\n线支，力用\n2 9\n2\n司\n路出高保\n7\n-\n. 1\n1\n5\n，\n7\n1\n%\n2\n.\n3\n2\n同\n%\n提\n-\n比\n5\n0\n3\n. 1\n增\n供\n提网\n支接\n2\n%\n5\n速\n路\n供使\n付触\n网\n43210------\n线用\n线网\n0000%123456 %%%%\n000000\n服\n%%%%%%\n路服\n路使\n务\n，务\n使用\n业\n接等\n用费\n务\n触\n费等\n收\n4\n3\n3\n2\n2\n1\n1\n0\n5\n0\n5\n0\n5\n0\n5\n，\n0\n0\n0\n0\n0\n0\n0\n0\n0\n入 =\n（\n单\n跨\n路非\n列\n线\n3 1\n2\n公\n运担\n8\n0\n的\n. 2\n1 6\n里\n输当\n5\n其\n费\n企列\n他\n率\n业车\n本\n铁\n×\n）\n线\n3\n跨\n4\n2\n周\n2\n0\n线\n.\n1\n转\n支局\n3\n7\n6\n量\n列\n提\n付相\n（\n车\n供\n给应\n亿\n运\n运\n对客\n人\n营\n输\n3\n应票\n4\n2\n公\n里\n4\n0\n服\n铁费\n.\n1\n里\n程\n5\n8\n务\n7\n）\n路用\n2\n跨\n0\n2 5\n1\n线旅\n9\n8\nQ\n.\n列客\n5\n1\n9\n~\n车\n3",
      "tables": []
    },
    {
      "page_number": 17,
      "width": 595.32,
      "height": 841.92,
      "text": "图21：2016~2019 年公司提供路网业务年均收入增速+16.6% 图22：公司提供路网服务业务收入构成占比（2023 年）\n30000 40%\n28.37%\n24.95% 15.93% 20%\n20000\n9.34% 9.57%\n0%\n-8.69%\n10000\n-20%\n-26.50%\n0 -40%\n2016 2017 2018 2019 2020 2021 2022 2023*\n车站上水服务（百万元） 售票服务（百万元）\n车站旅客服务（百万元） 接触网使用服务（百万元）\n线路使用服务（百万元） 提供路网服务收入同比增速\n资料来源：iFind，公司公告，信达证券研发中心\n资料来源：iFind，公司公告，信达证券研发中心\n注：2023 年为较2019 年同期增速\n定价标准：提供路网服务业务各细项业务收费标准参照国铁集团规定，收入规模大体\n与跨线列车运营里程有关，费率相对较为稳定。各细项服务收入清算单价各有不同，基本与\n跨线列车车次数及运营里程正向相关，销售模式为关联交易销售，交易对象为各地铁路局等。\n表6：提供路网服务收入的五类细项收入及相应清算单价\n款项结算方式&\n细项收入 具体服务内容 清算单价\n资金流向\n北京南-天津南区段为特一类特别繁忙第一档，单组动车组\n为 101.7 元/列车公里，重联动车组为 152.7 元/列车公里；\n京沪高铁公司利用自有高铁线 徐州东-蚌埠南为特一类特别繁忙第二档，单组动车组为\n线路使用\n路为其他铁路运输企业担当列 105.5 元/列车公里，重联动车组为 158.4 元/列车公里；其\n服务\n车提供线路使用服务 余线路段为特一类繁忙线路，单组动车组为 94.2 元/列车公\n里，重联动车组为 141.4 元/列车公里。夜间车按现行标准\n40%计算【按照列公里费率计价】\n京沪高铁公司利用自有线路接 月度预付，次月结\n接触网使 700 元/万总重吨公里（含电费），夜间车按现行标准（不\n触网为其他铁路运输企业担当 清；\n用服务 含电费）40%计算【按照列车吨公里计价】\n列车提供接触网使用服务\n北京南站和南京南站为繁忙车站第一档，高速动车组的清算 其他铁路运输企业\n车站旅客 京沪高铁公司 24 个自有车站向 标准为 8 元/人；上海虹桥站为繁忙车站第二档，高速动车 →国铁集团→京沪\n乘坐其他铁路运输企业担当列\n服务 组的清算标准为 9 元/人；其余车站为 5 元/人（高速动车组）、 高铁公司\n车的旅客提供发送服务等\n3 元/人（其他）【按照车站分类、人头收费】\n京沪高铁公司 24 个自有车站为\n售票服务 其他铁路运输企业担当列车提 旅客票价收入的 1%【按票价收入计提比例收费】\n供售票服务\n京沪高铁公司 24 个自有车站为 始发及上水站停车的旅客列车 20.00 元/列次，单组动车组\n车站上水\n其他铁路运输企业担当列车提 （仅指始发）为 24.00 元/列次，重联动车组（仅指始发）\n服务\n供上水服务 为 48.00 元/列次【按照动车组类别、分列次收费】\n资料来源：公司招股说明书，信达证券研发中心\n请阅读最后一页免责声明及信息披露 http://www.cindasc.com 17\n接\n用\n2\n触\n8\n服\n.\n网\n4\n务%\n车\n使\n务\n,\n站\n,\n旅\n7 .\n客\n4 %\n服\n售 票1\n. 7\n服\n%\n务 , 车\n务\n站\n,\n上\n0 .\n水\n0 %\n服\n线\n务\n路\n,\n使\n6 2\n用\n. 5 %\n服",
      "tables": [
        [
          [
            "线路使用 服务",
            "京沪高铁公司利用自有高铁线 路为其他铁路运输企业担当列 车提供线路使用服务",
            "北京南-天津南区段为特一类特别繁忙第一档，单组动车组 为101.7元/列车公里，重联动车组为152.7元/列车公里； 徐州东-蚌埠南为特一类特别繁忙第二档，单组动车组为 105.5元/列车公里，重联动车组为158.4元/列车公里；其 余线路段为特一类繁忙线路，单组动车组为94.2元/列车公 里，重联动车组为141.4元/列车公里。夜间车按现行标准 40%计算【按照列公里费率计价】"
          ]
        ],
        [
          [
            "北京南-天津南区段为特一类特别繁忙第一档，单组动车组"
          ],
          [
            "为101.7元/列车公里，重联动车组为152.7元/列车公里；"
          ],
          [
            "徐州东-蚌埠南为特一类特别繁忙第二档，单组动车组为"
          ],
          [
            "105.5元/列车公里，重联动车组为158.4元/列车公里；其"
          ],
          [
            "余线路段为特一类繁忙线路，单组动车组为94.2元/列车公"
          ],
          [
            "里，重联动车组为141.4元/列车公里。夜间车按现行标准"
          ],
          [
            "40%计算【按照列公里费率计价】"
          ]
        ],
        [
          [
            "京沪高铁公司利用自有高铁线"
          ],
          [
            "路为其他铁路运输企业担当列"
          ],
          [
            "车提供线路使用服务"
          ]
        ],
        [
          [
            "线路使用"
          ],
          [
            "服务"
          ]
        ],
        [
          [
            "车站旅客 服务",
            "京沪高铁公司24个自有车站向 乘坐其他铁路运输企业担当列 车的旅客提供发送服务等",
            "北京南站和南京南站为繁忙车站第一档，高速动车组的清算 标准为8元/人；上海虹桥站为繁忙车站第二档，高速动车 组的清算标准为9元/人；其余车站为5元/人（高速动车组）、 3元/人（其他）【按照车站分类、人头收费】"
          ]
        ],
        [
          [
            "北京南站和南京南站为繁忙车站第一档，高速动车组的清算"
          ],
          [
            "标准为8元/人；上海虹桥站为繁忙车站第二档，高速动车"
          ],
          [
            "组的清算标准为9元/人；其余车站为5元/人（高速动车组）"
          ],
          [
            "3元/人（其他）【按照车站分类、人头收费】"
          ]
        ],
        [
          [
            "京沪高铁公司24个自有车站向"
          ],
          [
            "乘坐其他铁路运输企业担当列"
          ],
          [
            "车的旅客提供发送服务等"
          ]
        ],
        [
          [
            "车站旅客"
          ],
          [
            "服务"
          ]
        ],
        [
          [
            "车站上水 服务",
            "京沪高铁公司24个自有车站为 其他铁路运输企业担当列车提 供上水服务",
            "始发及上水站停车的旅客列车20.00元/列次，单组动车组 （仅指始发）为24.00元/列次，重联动车组（仅指始发） 为48.00元/列次【按照动车组类别、分列次收费】"
          ]
        ],
        [
          [
            "京沪高铁公司24个自有车站为"
          ],
          [
            "其他铁路运输企业担当列车提"
          ],
          [
            "供上水服务"
          ]
        ],
        [
          [
            "始发及上水站停车的旅客列车20.00元/列次，单组动车组"
          ],
          [
            "（仅指始发）为24.00元/列次，重联动车组（仅指始发）"
          ],
          [
            "为48.00元/列次【按照动车组类别、分列次收费】"
          ]
        ],
        [
          [
            "车站上水"
          ],
          [
            "服务"
          ]
        ]
      ]
    },
    {
      "page_number": 18,
      "width": 595.32,
      "height": 841.92,
      "text": "列车量：跨线车发送列次年均增速超 10%，运营里程快速增长。从跨线车列次看，\n2016~2019 年跨线车发送列次从 10.41 万列增至 15.13 万列，年均复合增速达到 13.3%。\n从跨线车运营里程情况看，2023 年运营里程达到 12764 万列公里，较 2019 年同期增长\n35.4%，运营里程大幅提升。\n图23：2016~2019 年，公司跨线车发送列次年均增速+13.3% 图24：2023 年，公司跨线运营里程超 1.2 亿列公里\n资料来源：iFind，公司公告，信达证券研发中心\n资料来源：iFind，公司招股说明书，公司公告，信达证券研发中心\n注：2023 年为较2019 年同期增速\n2.4 成本情况：多为关联采购交易，收费标准由国铁集团清算定价\n公司营业成本较稳定，其中委托运输管理费、动车组使用费、折旧和能源支出为主要\n成本项，合计占比约 90%。2016~2019 年，公司营业成本稳中略增，整体较稳定。2023\n年，公司营业成本 221 亿元，同比增长 31.9%，较 2019 年同期增长 21.4%。结构上看，委\n托运输管理费、动车组使用费、折旧及能源支出为最主要成本项，合计占比基本在 90%左\n右。委托运输管理费及动车组使用费主要是公司本线的旅客运输业务成本，能源及折旧支出\n则为全线业务成本项。\n图25：公司营业成本稳定，2023 年较 2019 年同期+21.4% 图26：2023 年，公司委托运输管理费成本占比 26.4%\n资料来源：iFind，公司公告，信达证券研发中心\n资料来源：iFind，公司公告，信达证券研发中心\n注：2023 年为较2019 年同期增速\n请阅读最后一页免责声明及信息披露 http://www.cindasc.com 18\n1\n1\n1\n1\n6\n4\n2\n0\n8\n6\n4\n2\n0\n1\n2\n0\n0\n. 4\n1\n1\n6\n2 0\n跨\n. 8\n线\n%\n1\n2\n列\n2\n0\n. 5\n1\n次\n7\n7\n（ 万 列\n1\n6\n2\n）\n3\n. 0\n0\n. 3\n%\n1\n2\n8\n同\n1\n2\n比\n5\n0\n增\n. 1\n1\n3\n9\n速\n1 3 . 5 %\n2\n2\n1\n1\n5\n0\n5\n0\n5\n0\n%\n%\n%\n%\n%\n%\n1\n1\n1\n4\n2\n0\n8\n6\n4\n2\n0\n0\n0\n0\n0\n0\n0\n0\n0\n0\n0\n0\n0\n0\n0\n0\n0\n0\n0\n0\n0\n0\n9 4 2\n跨\n6\n线 运\n-\n营\n9\n1\n2\n.\n里\n5\n8\n%\n1\n程 （ 万\n1 0\n列\n1 9\n公\n2\n里 ）\n7\n- 2\n8\n2\n5\n.\n4\n9 %\n1\n同\n2\n3\n7\n5\n比\n6\n. 4\n4\n%\n增 速\n4\n3\n2\n1\n0\n-\n-\n-\n0\n0\n0\n0\n%\n1\n2\n3\n%\n%\n%\n%\n0\n0\n0\n%\n%\n%\n250 25% 0.6%\n221 2 1.4% 20% 委托运输管理费 6.3% 1.1% 0.1% 1.3%\n200 159 163 182 173 188 167 15% 动车组使用费 18.3% 1. 1 0 . % 1%\n151 折旧支出\n150 5.2% 11.5% 8.4% 10% 能源支出\n5.6% 5% 高铁运输能力保障费\n100 2.3% -4.6% 0% 维管费 26.4%\n54\n-5% 商务旅客服务费\n50 -11.1%\n-10% 路网使用费用\n安全生产费 22.7%\n0 -15%\n运输业务服务费\n其他\n21.0%\n营业成本（亿元） 同比增速-右轴",
      "tables": []
    },
    {
      "page_number": 19,
      "width": 595.32,
      "height": 841.92,
      "text": "营业成本的细项成本服务多通过关联采购模式交易，定价方式较公允。成本细项中委\n托运输管理服务、动车组使用服务、高铁运输能力保障服务、商务旅客服务等，为公司关联\n采购的主要内容，费用定价方式包含清算定价、全网统一定价和协商定价三种。清算定价的\n价格属于行业管理价格，公司细项成本中的动车组使用费、高铁运输能力保障费、路网使用\n费等为纳入清算体系项目。全网统一定价也具有行业价格管理属性，所有参与国家铁路运输\n的企业都参照执行。协商定价的项目中，如公司委托运输管理费、商务旅客服务费等，属于\n单一来源采购，无非关联方市场价格，由公司与受托铁路局集团协商确认。\n表7：公司营业成本细项构成及收费标准\n成本细项构成 内容项目 收费标准 定价方式\n1.动车组列车服务费的综合单价为 0.1329 万\n元/千辆公里 2.基础设施设备维护与车站旅客\n主要包含人工费用、动车组使用费（自\n服务费的综合单价北京局集团为 221.31 万元/\n2019 年起，动车组使用费单独核算，\n1 委托运输管理费 营业公里，济南局集团为 176.38 万元/营业公 协商确定\n不再包含在委托运输管理费中）、基\n里，上海局集团为 215.68 万元/营业公里 3.上\n础设施维护费用、车站直接费用等。\n述综合单价为 2021 年基准单价，此后 22-24\n年协议期间每年增长 6.275%\n公司使用国铁集团及其下属运输企业 时速 300/350 公里动车组 8.69 元/辆公里，时\n2 动车组使用费 清算定价\n动车组用于开行担当列车 速 200/250 公里动车组 7.53 元/辆公里\n京沪高铁线路上房屋、建筑物、线路、\n电气化供电系统、信号设备、通信设\n3 折旧支出 固定资产折旧方法采用年限平均法 -\n备、运输起动设备、机械动力设备及\n仪器仪表的折旧\n主要为保障列车运行、车站运营等使\n用电费支出，包括动车组运行牵引用\n4 能源支出 电费、水费标准收费 -\n电支出、车站生产用电支出、水费等，\n其中主要为动车组运行牵引用电支出\n5 高铁运输能力保障 以旅客运输收入、提供路网服务收入乘以 4%\n向受托运输管理铁路局支付的保障费 清算定价\n费 分配至旅客运输成本、提供路网服务成本\n委托中铁电气化局集团对京沪高速铁\n6 维管费 路沿线电气化设备进行维护管理发生 人力维修管理标准收费 -\n的费用支出\n为商务旅客提供相应服务，车站和列\n7 商务旅客服务费 - 协商确定\n车所产生的商务旅客服务费用\n主要包括为开展旅客运输业务，其他\n铁路运输企业为公司提供路网服务所\n8 路网使用费用 - 清算定价\n涉及的机车牵引费、售票服务费、接\n触网使用费、车站旅客服务费等\n9 安全生产费 - -\n10 运输业务服务费 - -\n主要包括接受服务支出、修理维护支\n11 其他 出、专项清算支出、铁路公安经费、 - -\n上交共同费用等\n资料来源：公司招股说明书，信达证券研发中心\n请阅读最后一页免责声明及信息披露 http://www.cindasc.com 19",
      "tables": [
        [
          [
            "1委托运输管理费",
            "主要包含人工费用、动车组使用费（自 2019年起，动车组使用费单独核算， 不再包含在委托运输管理费中）、基 础设施维护费用、车站直接费用等。",
            "1.动车组列车服务费的综合单价为0.1329万 元/千辆公里2.基础设施设备维护与车站旅客 服务费的综合单价北京局集团为221.31万元/ 营业公里，济南局集团为176.38万元/营业公 里，上海局集团为215.68万元/营业公里3.上 述综合单价为2021年基准单价，此后22-24 年协议期间每年增长6.275%",
            "协商确定"
          ]
        ],
        [
          [
            "1.动车组列车服务费的综合单价为0.1329万"
          ],
          [
            "元/千辆公里2.基础设施设备维护与车站旅客"
          ],
          [
            "服务费的综合单价北京局集团为221.31万元/"
          ],
          [
            "营业公里，济南局集团为176.38万元/营业公"
          ],
          [
            "里，上海局集团为215.68万元/营业公里3.上"
          ],
          [
            "述综合单价为2021年基准单价，此后22-24"
          ],
          [
            "年协议期间每年增长6.275%"
          ]
        ],
        [
          [
            "主要包含人工费用、动车组使用费（自"
          ],
          [
            "2019年起，动车组使用费单独核算，"
          ],
          [
            "不再包含在委托运输管理费中）、基"
          ],
          [
            "础设施维护费用、车站直接费用等。"
          ]
        ],
        [
          [
            "3折旧支出",
            "京沪高铁线路上房屋、建筑物、线路、 电气化供电系统、信号设备、通信设 备、运输起动设备、机械动力设备及 仪器仪表的折旧",
            "固定资产折旧方法采用年限平均法",
            "-"
          ]
        ],
        [
          [
            "京沪高铁线路上房屋、建筑物、线路"
          ],
          [
            "电气化供电系统、信号设备、通信设"
          ],
          [
            "备、运输起动设备、机械动力设备及"
          ],
          [
            "仪器仪表的折旧"
          ]
        ],
        [
          [
            "5高铁运输能力保障 费",
            "向受托运输管理铁路局支付的保障费",
            "以旅客运输收入、提供路网服务收入乘以4% 分配至旅客运输成本、提供路网服务成本",
            "清算定价"
          ]
        ],
        [
          [
            "5高铁运输能力保障"
          ],
          [
            "费"
          ]
        ],
        [
          [
            "以旅客运输收入、提供路网服务收入乘以4%"
          ],
          [
            "分配至旅客运输成本、提供路网服务成本"
          ]
        ],
        [
          [
            "7商务旅客服务费",
            "为商务旅客提供相应服务，车站和列 车所产生的商务旅客服务费用",
            "-",
            "协商确定"
          ]
        ],
        [
          [
            "为商务旅客提供相应服务，车站和列"
          ],
          [
            "车所产生的商务旅客服务费用"
          ]
        ],
        [
          [
            "",
            "9安全生产费",
            "",
            "",
            "-",
            "",
            "",
            "-",
            "",
            "",
            "",
            ""
          ]
        ],
        [
          [
            "11其他",
            "主要包括接受服务支出、修理维护支 出、专项清算支出、铁路公安经费、 上交共同费用等",
            "-",
            "-"
          ]
        ],
        [
          [
            "主要包括接受服务支出、修理维护支"
          ],
          [
            "出、专项清算支出、铁路公安经费、"
          ],
          [
            "上交共同费用等"
          ]
        ]
      ]
    },
    {
      "page_number": 20,
      "width": 595.32,
      "height": 841.92,
      "text": "3 未来展望：票价市场化持续，运量仍有增长\n3.1 旅客运输业务：京沪黄金通道，量价有望双升\n旅客运输业务收入取决于票价及旅客量情况，二者均有进一步提升的可能。\n票价端：实行七档浮动票价，平均票价有望上行。单位客公里收入主要受票价实施机\n制影响，此前京沪高铁已在 2020 年 12 月底上调过一次票价，二等座全票价较之前上涨近\n20%，但与主要竞争对象相比，仍有较为显著的价格优势。后续随着高铁票价市场化机制改\n革持续推进及大众人均收入提升、出行需求增加，票价可能会迎来进一步上涨。此外，由于\n铁路为多站运输而非点对点运输，因而平均运距也会受到市场需求及铁路公司计划安排等因\n素影响，进而出现一定变动。\n图27：旅客运输业务收入增长来源\n资料来源：公司公告，信达证券研发中心\n旅客量端：可通过提升客座率、增加发车频次、增加加长列车车次等方式提升旅客量。\n1）提升客座率：目前京沪线高铁出行需求仍然较强，2019 年前客座率已经达到 80%，\n与航空客运行业平均客座率近 85%对比仍有一定差距。虽然高铁行业受限于多点运输，客\n座率存在隐形天花板，难以达到民航客运水平，但京沪高铁客座率还是存在一定上行空间。\n2）增加发车频次：当前京沪高铁发车最短间隔仅为 4 分钟，国内沪杭高铁 2010 年开\n通运营时设计时速为 350 公里，发车间隔为 3 分钟，京沪高铁列车追踪间隔有进一步压缩\n的空间，进而增加发车频次。从公司全线的日均发车列次情况看，2011 年至 2021 年，公\n司日均发车列次从 131 列增至 615 列，年均复合增速 16.7%。假设不考虑非重叠列车组，\n平均追踪间隔时间从 10.99 分缩减至 2.34 分，间隔时间有较明显下降。\n3）增加动车组长度：公司动车组列车型号存在长短编区别，最长动车组有 17 节，座\n位数从 1283 座到 1440 座不等，以 17 节动车组列车最少座位数 1283 座对比 16 节动车组\n列车最大座位数 1193 座，座位数增加了 90 座，提升了 7.5%；对比 8 节动车组列车最大座\n位数 613 座则增加了 670 座位数，增幅达到 109.3%。若此后公司进一步调整长短编动车组\n结构，动车组平均长度增加，运量有望进一步提升。\n请阅读最后一页免责声明及信息披露 http://www.cindasc.com 20\n旅 客业 运务 输收 服入 务\n（\n（\n人\n旅\n人\n票\n次\n客\n次\n价\n/\n量\n元\n）\n）\n（\n（\n单\n平\n元\n公\n供\n需供\n位\n均\n/\n里\n公\n需\n求给\n费\n运\n/\n里\n人\n关\n较偏\n率\n距\n）\n）\n系\n强紧\n市\n市\n计\n场\n场\n划\n增\n化\n需\n增\n安\n提\n加\n改\n求\n加\n排\n升\n动\n革\n及\n发\n客\n车\n车\n座\n组\n频\n率\n长\n次\n度",
      "tables": []
    },
    {
      "page_number": 21,
      "width": 595.32,
      "height": 841.92,
      "text": "图28：公司客座率已有较大提升，略低于航空客运客座率 图29：2021 年，公司日均发车列次增至 615 列\n资料来源：iFind，公司公告，公司招股说明书，信达证券研发中心 资料来源：iFind，公司招股说明书，公司公告，国铁集团，信达证券研\n注：京沪高铁本线仅披露到19Q1~3客座率，此处航空客运客座率为2019 发中心\n年国内线客座率 注：此处发车间隔计算假设全线列车均有路段重合，不考虑非重叠列车\n3.2 提供路网服务业务：南北大通道价值提升，跨线车稳步增加\n提供路网服务业务收入增长，我们预计主要依托于跨线列车车次、运营里程等量的提\n升。\n价：由国铁集团定价，费率相对稳定。各细项业务收费标准参照国铁集团规定，清算单\n价较为稳定，上行空间有限。\n量：跨线业务服务包含多种细项服务，跨线车周转量与跨线车列次、运营里程正向相\n关。2016~2019 年，公司本线跨线发车列次均有增长，其中跨线车列次增速快于本线车列\n次，较本线车列次倍数由 2.6 增至 4.2，京沪线车次结构上跨线车占比逐渐增加。随路网逐\n步完善，公司本线跨线列车调整，跨线车列次、运营里程等均有望增长，我们预计将带动路\n网服务业务量进一步增加。\n图30：提供路网业务收入增长来源\n资料来源：公司公告，信达证券研发中心\n请阅读最后一页免责声明及信息披露 http://www.cindasc.com 21\n8\n8\n7\n7\n6\n5\n0\n5\n0\n5\n%\n%\n%\n%\n%\n京\n京\n沪\n沪\n2\n高\n高\n0 1\n铁\n铁\n6\n本\n客\n线\n座\n平\n率\n均\n平\n2\n客\n均\n0 1\n座\n值\n7\n率\n提服 供务 路收\n2\n航\n0\n网入\n1\n空\n8\n行 业 平\n2\n均\n0 1\n客\n9 Q\n座\n1\n量\n价\n~\n率\n3\n7\n6\n5\n4\n3\n2\n1\n0\n0\n0\n0\n0\n0\n0\n0\n0\n0\n0\n0\n0\n0\n0\n跨\n营\n各\n线\n里\n细\n全\n1 0\n1\n2 0\n线\n车\n程\n项\n. 9 9\n3 1\n1 1\n日\n列\n、\n服\n标 准\n均\n次\n旅\n务\n列\n3\n3\n2\n、\n客\n收\n9\n. 6\n0 1\n次\n4\n6\n6\n（\n运\n数\n费\n列 ）\n4\n3\n2\n5\n. 1\n0 1\n3\n8\n7\n4\n3\n2\n平\n7 3\n. 0 5\n0 1 8\n均 发 车\n5\n2\n2\n间\n路列\n国清\n1\n. 8\n0 1\n3\n1\n9\n隔\n网次\n铁算\n（\n完增\n集定\n分\n6\n2\n2\n）\n善加\n团价\n1\n. 3\n0 2\n5\n4\n1\n右 - 轴\n1\n1\n8\n6\n4\n2\n0\n2\n0",
      "tables": []
    },
    {
      "page_number": 22,
      "width": 595.32,
      "height": 841.92,
      "text": "3.3 京福安徽：短期业绩承压，长期利润可期\n收购培育期铁路路段，扩大完善公司路网结构。2020 年，公司公开发行股票 62.86 亿\n股（占发行后总股本的比例不超过 12.80%），募集资金总额 306.74 亿元，用于收购京福安\n徽公司 65.0759%的股权；收购完成后，京福安徽成为公司的控股子公司。公司本次收购主\n要是扩大自身网络覆盖，优化路网结构；预期收购完成后，将加强公司与其余“八纵八横”\n主通道的连接，路网协同效应增强，从而进一步提升公司盈利能力。\n收购对象：京福安徽公司主营业务为高铁旅客运输，是合蚌客专、合福铁路安徽段、\n商合杭铁路安徽段、郑阜铁路安徽段的投资、建设、运营主体。\n1）合蚌客专段：收购时处于市场培育期，北起蚌埠市与京沪高铁在蚌埠南站接轨，南\n至合肥枢纽，沿途共有 6 个站点，营业里程约 132 公里，设计时速 350 公里/小时，于 2012\n年 10 月 16 日正式开通运营。合蚌客专与合宁、合武铁路相连接，是京沪通道与沿江通道\n间快速连接线。\n2）合福铁路安徽段：收购时处于市场培育期，线路自安徽省合肥北城引出至合肥南站，\n沿途共设有 12 个站点，营业里程约 388.6 公里，设计时速 350 公里/小时，于 2015 年 6 月\n28 日正式开通运营，合福铁路安徽段向北通过合蚌客专与京沪高铁连接，是京港（台）通\n道的重要组成部分。\n3）商合杭铁路安徽段：线路于 2020 年中旬开通，线路经安徽多地，下行终至浙江杭\n州，沿途共设有 24 个站点，营业里程约 592 公里，设计时速 350 公里/小时。商合杭高速\n铁路是客运专线网的重要干线和华东地区南北向的第二大客运通道，与沪昆通道相连接，是\n有效联系中原、江淮与长三角重要的交通干线。\n4）郑阜铁路安徽段：线路于 2019 年底开通，共设界首南站、临泉站、阜阳西站等 3\n个车站，营业里程约 69 公里，设计时速 350 公里/小时。郑阜铁路与陆桥通道、京港澳通道\n相连，有利于完善中部地区铁路网布局，强化西北与华东地区快速客运通道。\n图31：京福安徽公司管辖线路\n资料来源：公司招股说明书，信达证券研发中心\n请阅读最后一页免责声明及信息披露 http://www.cindasc.com 22",
      "tables": []
    },
    {
      "page_number": 23,
      "width": 595.32,
      "height": 841.92,
      "text": "京福安徽业务模式：公司本身不担当列车，仅提供路网服务，收入绝大部分来自于向其\n他铁路运输企业担当的列车收取的线路使用费、接触网使用费等，因而关联销售占比较高。\n同时，公司通过委托运输管理模式，委托铁路沿线铁路局集团对其运营路段进行运输管理，\n并支付相应关联采购费用。京福安徽公司的关联交易与公司同类交易的定价模式相同，关联\n采购价格也使用清算定价、全网统一定价及协商定价等方式。\n京福安徽业绩表现：公司京福安徽公司收入主要为提供路网业务服务收入，成本主要是\n相关委托运输管理费用及能源、折旧支出等。公司营业收入大体上稳步上升，2018~2023\n年营业收入从 17.7 亿元增至 54.7 亿元，年均复合增速+25.4%，收入增长较快。但公司利\n润端目前仍为亏损，前期主要是市场培育期，盈利仍需时间；2020 至 2022 年则受到疫情\n因素影响，仍有较大亏损；2023 年公司净利润已缩减至-9.7 亿元，我们预计后续公司盈利\n回正加快，实现扭亏为盈。\n图32：2023 年，京福安徽公司营收为 54.7 亿元，同比+53.3% 图33：2023 年，京福安徽公司归母净利亏损收窄至-9.7 亿元\n资料来源：iFind，公司公告，公司招股说明书，信达证券研发中心 资料来源：iFind，公司公告，公司招股说明书，信达证券研发中心\n请阅读最后一页免责声明及信息披露 http://www.cindasc.com 23\n6\n5\n4\n3\n2\n1\n0\n0\n0\n0\n0\n0\n0\n1\n2\n7\n0\n.\n1\n7\n8\n8\n营\n. 4 %\n业\n1\n2\n9\n0\n收\n.\n1\n1\n9\n入 （\n8 4\n3\n2\n亿\n.\n5\n0\n5\n.\n2\n元\n%\n3\n0\n）\n4\n2\n5\n0\n.\n2\n4\n1\n2 8 . 7\n3\n%\n2\n5\n0\n同\n.\n2\n7\n2\n-\n比\n2 1\n增\n. 5\n5\n%\n2\n速\n4\n5\n0\n.\n3\n2\n-\n7\n.\n3\n右\n3 %\n轴\n1\n8\n6\n4\n2\n0\n-\n-\n0\n0\n0\n0\n0\n%\n2\n4\n0\n%\n%\n%\n%\n0\n0\n%\n%\n%\n-\n-\n-\n-\n-\n-\n-\n1\n1\n2\n2\n3\n3\n0\n5\n0\n5\n0\n5\n0\n5\n-\n2\n1\n0\n2\n1\n. 0\n8\n-\n2\n1\n0\n3\n1\n. 4\n9\n净\n- 2\n2\n利\n0\n0 .\n2\n润\n9\n0\n（ 亿\n-\n2\n元\n1\n0\n7\n2\n）\n. 2\n1\n-\n2\n2\n0\n7\n2\n. 9\n2 2\n- 9\n0\n.\n2\n7\n3",
      "tables": []
    },
    {
      "page_number": 24,
      "width": 595.32,
      "height": 841.92,
      "text": "4 盈利预测、估值与投资评级\n4.1 盈利预测：预计公司 2024 年归母净利润 130.54 亿元\n营收预测：公司营业收入分为旅客运输业务收入、提供路网服务收入和其他收入。其\n中本线客票业务量价均有提升空间，跨线业务预计价格维稳，运量增加。最终我们预计，公\n司 2024-2026 年营业收入分别 443/473/504 亿元，同比分别+8.83%/+6.85%/+6.46%。\n1）旅客运输业务收入（本线客票收入）：价格方面，预计未来三年价格微增；旅客量方\n面，预计随发车频次增加、客座率提升、加长列车的增加等，旅客量保持一定增加。预计公\n司 2024~2026 年旅客运输收入分别 169/178/189 亿元，同比分别+5.24%/+5.07%/+6.11%；\n2）提供路网服务收入（跨线业务收入）：考虑到随路网建设完善，跨线列车车次有望增\n加。预计公司 2024~2026 年提供路网服务业务收入分别 270/291/311 亿元，同比分别\n+11.27%/+8.15%/+6.74%；\n3）其他收入：考虑到其他业务收入占比不足 2%影响较小，假设该部分收入相对稳定。\n表8：公司营收拆分及预测表\n单位：百万元 2022 2023 2024E 2025E 2026E\n营业收入 19336 40683 44277 47311 50369\nYOY -34.02% 110.40% 8.83% 6.85% 6.46%\n1 旅客运输业务收入 5096 16082 16925 17783 18870\nYOY -48.89% 215.58% 5.24% 5.07% 6.11%\n2 提供路网服务收入 13876 24223 26953 29148 31114\nYOY -26.50% 74.57% 11.27% 8.15% 6.74%\n3 其他收入 364 377 399 380 385\nYOY -20.18% 3.67% 5.77% -4.75% 1.42%\n资料来源：公司公告，iFind，信达证券研发中心\n成本预测：公司营业成本可拆分为委托运输管理费、动车组使用费、折旧支出、能源\n支出、高铁运输能力保障费、维管费、商务旅客服务费等。其中委托运输管理费、动车组\n使用费、折旧支出及能源支出为最主要成本，四项合计约占总成本 90%；以 2019 年情况为\n例，以上四项成本分别占比为 23.17%、26.85%、22.08%、17.43%。\n其中，委托运输管理费及动车组使用费主要受到本线运营情况影响；折旧支出主要为线\n路及配套建筑物设施等资产折旧；能源支出受到全线运营影响；高铁运输能力保障费按照营\n业收入一定比例计提。\n最终我们预计，公司 2024-2026 年营业成本分别为 236/245/261 亿元，同比分别\n+6.92%/+4.01%/+6.26%。\n请阅读最后一页免责声明及信息披露 http://www.cindasc.com 24",
      "tables": []
    },
    {
      "page_number": 25,
      "width": 595.32,
      "height": 841.92,
      "text": "利润预测：公司利润主要来自本线客票业务利润及跨线路网服务业务利润。\n1）综合毛利率：经测算，最终预计 2024-2026 年公司综合毛利率分别 46.75%、48.16%、48.26%，\n综合毛利率有望持续回升。\n2）归母净利润：我们最终预计 2024-2026 年公司归母净利润分别 130.54/144.02/155.81 亿元，\n同比分别+13.06%、+10.33%、+8.19%。\n表9：简易盈利预测表\n单位：百万元 2022 2023 2024E 2025E 2026E\n营业收入 19336 40683 44277 47311 50369\nYOY -34.02% 110.40% 8.83% 6.85% 6.46%\n营业成本 16718 22052 23579 24524 26059\n毛利率 13.54% 45.80% 46.75% 48.16% 48.26%\n归母净利润 -576 11546 13054 14402 15581\nYOY -111.97% 2103.63% 13.06% 10.33% 8.19%\n资料来源：公司公告，iFind，信达证券研发中心\n4.2 估值方式：绝对估值与相对估值\n根据前文盈利预测，我们预计公司2024-2026年实现归母净利130.54/144.02/155.81亿元，\n同比分别+13.06%、+10.33%、+8.19%，对应每股收益分别为 0.27、0.29、0.32 元，现价对应\nPE 分别为 19.94、18.07、16.70 倍。\n绝对估值法：考虑到公司可比公司较少、毛利率水平高且经营性净现金流较为稳定，\n我们预计公司长期业绩稳健，采用 DCF 方式进行估值。我们使用公司自由现金流量 FCFF\n模型对京沪高铁进行估值，模型公式为 FCFF=（税后净利润+利息费用+非现金支出）-营运\n资本增加-资本性支出。公司价值则为预期 FCFF 的现值，即：公司价值 𝑃 = ∑𝑛\n𝐹𝐶𝐹𝐹𝑡\n𝑡=1 𝑡\n（1+𝑊𝐴𝐶𝐶）\n其中，𝑊𝐴𝐶𝐶为加权平均资本成本，𝐾𝑑为债务资本成本，𝐾𝑒为股权资本成本，𝑊𝑑为债\n务资本比重，𝑇为所得税税率。\n表10：DCF 关键假设说明\n估值假设 假设值 假设说明\n过渡期增长率 1.5% 预期公司未来经营增长较稳定，增速保持稳健\n永续期增长率 1.0% 在过渡期增长率基础上适当下浮\n贝塔值β 0.7 参考历史β值\n无风险利率 Rf 2.3% 参考中债国债到期收益率（10 年期）平均值\n市场预期收益率 Rm 8.0% 参考沪深 300 指数历史收益率情况假设\n股权成本 Ke 6.29% Ke=Rf+β*（Rm-Rf）\n参考公司短期、中长期贷款情况，对应贷款利率近五年人民币短期、中长期贷款利\n债务成本 Kd 4.50%\n率（5 年）平均值\n所得税税率 T 25.0% 参考公司历史所得税税率情况假设\n加权平均资本成本 WACC 5.80% 𝑊𝐴𝐶𝐶 = 𝐾𝑑 ∗ 𝑊𝑑 ∗（1 − 𝑇）+ 𝐾𝑒 ∗（1 − 𝑊𝑑）\n资料来源：iFind，信达证券研发中心\n请阅读最后一页免责声明及信息披露 http://www.cindasc.com 25",
      "tables": []
    },
    {
      "page_number": 26,
      "width": 595.32,
      "height": 841.92,
      "text": "根据以上核心假设，公司加权平均资本成本 WACC=5.80%，永续期增长率 1%，最终可\n计算出 FCFF 估值模型下，公司总价值为 3981 亿元，其中总股权价值为 3245 亿元，对应\n每股价值为 6.61 元。\n此外，对 FCFF 模型进行敏感型分析，假设永续增长率 g 及 WACC 按照 0.5%变动，则\n京沪高铁对应的 FCFF 估值结果也会有相应变动，对应每股价值区间在 5.42~8.41 元。\n表11：FCFF 预测及估值结果（截至 2024.9.18）\n单位：百万元 2024E 2025E 2026E 2027E 2028E 2029E 2030E 2031E 2032E 2033E\nFCFF 20,372 17,850 18,822 19,105 19,391 19,682 19,977 20,277 20,581 20,890\n预测期现值 38,239 -\n过渡期现值 - 98,668\n永续期现值 261,176\n企业价值 398,082\n加：非核心资产价值 6214\n减：付息债务 56922\n减：少数股东权益 22898\n总股权价值 总股本 每股价值\n324,476 49106 6.61\n（百万元） （百万股） （元/股）\n资料来源：iFind，信达证券研发中心\n表12：京沪高铁的 FCFF 估值敏感型分析，对应每股价值情况（单位：元）\n永续增长率 g/WACC 4.30% 4.80% 5.30% 5.80% 6.30% 6.80% 7.30%\n-0.50% 7.47 6.60 5.88 5.28 4.77 4.32 3.94\n0.00% 8.20 7.17 6.34 5.65 5.07 4.57 4.15\n0.50% 9.12 7.87 6.88 6.08 5.42 4.86 4.39\n1.00% 10.32 8.76 7.56 6.61 5.84 5.20 4.66\n1.50% 11.95 9.91 8.41 7.26 6.34 5.60 4.99\n2.00% 14.29 11.48 9.52 8.07 6.97 6.09 5.38\n2.50% 18.24 14.04 11.33 9.45 8.06 7.00 6.15\n资料来源：iFind，信达证券研发中心\n相对估值法：将京沪高铁公司与广深铁路相对比，剔除疫情影响，广深铁路历史估值看，\n2009~2019 年十年 PE 平均值约 24.5 倍，2017~2019 年三年 PE 均值约 29.4 倍。考虑到京沪\n高铁票价、本跨线列车车次仍有较大提升空间，公司业务成长性较强，业绩有望较快增长。\n我们认为当前京沪高铁合理估值可在 22 至 25 倍，对应公司合理市值为 2872~3263 亿元。\n请阅读最后一页免责声明及信息披露 http://www.cindasc.com 26",
      "tables": [
        [
          [
            "6.88",
            "6.08",
            "5.42"
          ],
          [
            "7.56",
            "6.61",
            "5.84"
          ],
          [
            "8.41",
            "7.26",
            "6.34"
          ]
        ]
      ]
    },
    {
      "page_number": 27,
      "width": 595.32,
      "height": 841.92,
      "text": "图34：广深铁路 2010~2019 年间平均 PE 为 24.5 倍\n90\n80\n70\n60\n50\n40\n30\n20\n10\n0\n广深铁路PE\n资料来源：iFind，信达证券研发中心\n4.3 投资评级：首次覆盖给予“增持”评级\n京沪高铁为国内铁路客运上市公司龙头，公司高铁线路连接北京、上海两地，沿线覆\n盖众多省会重点城市及交通枢纽，区位优势明显，客运需求旺盛。未来随着票价市场化持\n续推进以及旅客量、列车量的进一步增加，公司客票业务及路网服务业务收入均有望持续\n增长，公司业绩预期仍有较大增长空间。\n根据 FCFF 模型的估值情况，公司企业价值为 3981 亿元，其中股权价值为 3245 亿元；\n相对估值情况看，公司合理市值在 2872~3263 亿元。综合绝对估值和相对估值情况考虑，\n预计公司合理市值区间在 2872~3245 亿元，首次覆盖，我们给予公司“增持”评级。\n请阅读最后一页免责声明及信息披露 http://www.cindasc.com 27",
      "tables": []
    },
    {
      "page_number": 28,
      "width": 595.32,
      "height": 841.92,
      "text": "5 风险因素\n1、宏观经济波动风险：宏观经济下行，公商务及休闲旅客出行需求可能降低，进而影响铁\n路旅客运输人数，进而影响公司整体业绩。\n2、清算政策调整风险：公司提供路网服务收入的多项细项收入及部分成本细项的收费标准\n由国铁集团清算定价。随着生产要素价格水平提高、路网服务质量提升、行业特点及供求关\n系变化，国铁集团清算项目、清算范围、清算价格可能出现调整，进而对公司经营业绩产生\n一定影响。\n3、委托管理风险：公司与沿线相关铁路局、中铁电气化局集团签署了委托管理协议，服务\n单价逐年增长。若未来营业收入的增长不能覆盖上述成本的增加，可能导致公司经营业绩下\n滑。同时也可能出现受托方不能继续提供服务、不能按照约定的方式提供服务、服务质量不\n达标等不利变化。\n4、行业竞争加剧风险：公司与公路客运、航空客运等运输方式存在差异化竞争，若后续公\n路路网持续扩张完善、航空客运服务质量不断提高，或影响旅客出行方式选择。\n5、京福安徽运量增长不及预期：公司后续跨线业务列车量增长主要源自京福安徽，若相关\n路网路段列车量增长不及预期，可能影响公司后续收入提升。\n请阅读最后一页免责声明及信息披露 http://www.cindasc.com 28",
      "tables": []
    },
    {
      "page_number": 29,
      "width": 595.32,
      "height": 841.92,
      "text": "[资Ta产bl负e_债Fi表na nce] 单位:百万元 利润表 单位:百万元\n会计年度 2022A 2023A 2024E 2025E 2026E 会计年度 2022A 2023A 2024E 2025E 2026E\n流动资产 6,049 14,421 15,056 17,283 24,494 营业总收入 19,336 40,683 44,277 47,311 50,369\n货币资金 5,339 12,903 13,477 15,525 22,561 营业成本 16,718 22,052 23,579 24,524 26,059\n应收票据 营业税金及附\n0 0 0 0 0 2 139 142 170 181\n加\n应收账款 249 982 959 1,051 1,119 销售费用 0 0 0 0 0\n预付账款 0 0 0 0 0 管理费用 791 802 797 994 1,108\n存货 0 0 0 0 0 研发费用 5 11 9 14 10\n其他 461 535 619 707 814 财务费用 2,905 2,365 2,166 1,685 1,396\n非流动资产 282,496 277,799 272,713 268,152 263,876 减值损失合计 0 0 0 0 0\n长期股权投资 0 0 0 0 0 投资净收益 0 0 0 0 0\n固定资产（合计） 223,797 218,847 213,994 209,315 204,986 其他 38 0 44 2 2\n无形资产 57,860 58,376 58,056 58,136 58,216 营业利润 -1,047 15,314 17,629 19,926 21,616\n其他 839 575 662 701 674 营业外收支 2 -5 3 2 2\n资产总计 288,545 292,220 287,769 285,436 288,370 利润总额 -1,045 15,309 17,632 19,928 21,618\n流动负债 9,303 14,736 15,574 13,264 11,228 所得税 507 4,102 4,708 5,381 5,880\n短期借款 0 0 0 0 0 净利润 -1,552 11,207 12,924 14,547 15,738\n应付票据 0 0 0 0 0 少数股东损益 -976 -338 -129 145 157\n应付账款 归属母公司净\n799 1,594 3,275 2,384 1,810 -576 11,546 13,054 14,402 15,581\n利润\n其他 8,504 13,142 12,299 10,880 9,418 EBITDA 7,804 23,605 25,778 27,624 29,080\n非流动负债 EPS (当\n71,962 59,573 46,584 38,594 35,094 -0.01 0.24 0.27 0.29 0.32\n年)(元)\n长期借款\n71,334 58,941 45,941 37,941 34,441\n其他 628 631 643 653 653 现金流量表 单位:百万元\n负债合计\n81,266 74,308 62,158 51,858 46,322\n会计年度\n2022A 2023A 2024E 2025E 2026E\n少数股东权益 23,282 22,941 22,812 22,957 23,115 经营活动现金 6,801 21,081 22,979 21,863 23,221\n流\n归属母公司股东 净利润\n183,997 194,970 202,799 210,620 218,934 -1,552 11,207 12,924 14,547 15,738\n权益\n负债和股东权益 288,545 292,220 287,769 285,436 288,370 折旧摊销 5,946 5,926 5,980 6,011 6,066\n财务费用 3,094 2,587 2,360 1,887 1,629\n单位:百万 投资损失\n重要财务指标 0 0 0 0 0\n元\n会计年度 2022A 2023A 2024E 2025E 2026E 营运资金变动 -676 1,367 1,712 -590 -210\n营业总收入 19,336 40,683 44,277 47,311 50,369 其它 -11 -6 4 8 -2\n投资活动现金\n同比（%） -34.0% 110.4% 8.8% 6.9% 6.5% -1,099 -1,113 -890 -1,448 -1,788\n流\n归属母公司净利\n-576 11,546 13,054 14,402 15,581 资本支出 -1,099 -1,490 -897 -1,448 -1,788\n润\n同比（%） -112.0% 2103.6% 13.1% 10.3% 8.2% 长期投资 0 0 0 0 0\n毛利率（%） 13.5% 45.8% 46.7% 48.2% 48.3% 其他 0 378 6 0 0\n筹资活动现金\nROE% -0.3% 5.9% 6.4% 6.8% 7.1% -9,281 -12,404 -21,515 -18,368 -14,396\n流\nEPS (摊薄)(元) -0.01 0.24 0.27 0.29 0.32 吸收投资 0 0 -5 0 0\nP/E — 22.54 19.94 18.07 16.70 借款 -5,202 -12,393 -13,000 -8,000 -3,500\n支付利息或股\nP/B 1.41 1.33 1.28 1.24 1.19 -5,560 -3,277 -7,839 -8,468 -8,896\n息\n现金流净增加\nEV/EBITDA 40.02 12.52 11.62 10.41 9.46 -3,578 7,564 574 2,048 7,036\n额\n请阅读最后一页免责声明及信息披露 http://www.cindasc.com 29",
      "tables": [
        [
          [
            "[资Ta产bl负e_债Fi表na nce]",
            "",
            "",
            "",
            "单位:百万元",
            ""
          ],
          [
            "会计年度",
            "2022A",
            "2023A",
            "2024E",
            "2025E",
            "2026E"
          ],
          [
            "流动资产",
            "6,049",
            "14,421",
            "15,056",
            "17,283",
            "24,494"
          ],
          [
            "货币资金",
            "5,339",
            "12,903",
            "13,477",
            "15,525",
            "22,561"
          ],
          [
            "应收票据",
            "0",
            "0",
            "0",
            "0",
            "0"
          ],
          [
            "应收账款",
            "249",
            "982",
            "959",
            "1,051",
            "1,119"
          ],
          [
            "预付账款",
            "0",
            "0",
            "0",
            "0",
            "0"
          ],
          [
            "存货",
            "0",
            "0",
            "0",
            "0",
            "0"
          ],
          [
            "其他",
            "461",
            "535",
            "619",
            "707",
            "814"
          ],
          [
            "非流动资产",
            "282,496",
            "277,799",
            "272,713",
            "268,152",
            "263,876"
          ],
          [
            "长期股权投资",
            "0",
            "0",
            "0",
            "0",
            "0"
          ],
          [
            "",
            "",
            "",
            "",
            "",
            ""
          ],
          [
            "固定资产（合计",
            "） 223,797",
            "218,847",
            "213,994",
            "209,315",
            "204,986"
          ],
          [
            "",
            "",
            "",
            "",
            "",
            ""
          ],
          [
            "无形资产",
            "57,860",
            "58,376",
            "58,056",
            "58,136",
            "58,216"
          ],
          [
            "其他",
            "839",
            "575",
            "662",
            "701",
            "674"
          ],
          [
            "资产总计",
            "288,545",
            "292,220",
            "287,769",
            "285,436",
            "288,370"
          ],
          [
            "流动负债",
            "9,303",
            "14,736",
            "15,574",
            "13,264",
            "11,228"
          ],
          [
            "短期借款",
            "0",
            "0",
            "0",
            "0",
            "0"
          ],
          [
            "应付票据",
            "0",
            "0",
            "0",
            "0",
            "0"
          ],
          [
            "应付账款",
            "799",
            "1,594",
            "3,275",
            "2,384",
            "1,810"
          ],
          [
            "其他",
            "8,504",
            "13,142",
            "12,299",
            "10,880",
            "9,418"
          ],
          [
            "非流动负债",
            "71,962",
            "59,573",
            "46,584",
            "38,594",
            "35,094"
          ],
          [
            "长期借款",
            "71,334",
            "58,941",
            "45,941",
            "37,941",
            "34,441"
          ],
          [
            "其他",
            "628",
            "631",
            "643",
            "653",
            "653"
          ],
          [
            "负债合计",
            "81,266",
            "74,308",
            "62,158",
            "51,858",
            "46,322"
          ],
          [
            "少数股东权益",
            "23,282",
            "22,941",
            "22,812",
            "22,957",
            "23,115"
          ],
          [
            "归属母公司股东",
            "183,997",
            "194,970",
            "202,799",
            "210,620",
            "218,934"
          ],
          [
            "权益",
            "",
            "",
            "",
            "",
            ""
          ],
          [
            "负债和股东权益",
            "288,545",
            "292,220",
            "287,769",
            "285,436",
            "288,370"
          ]
        ],
        [
          [
            "利润表",
            "",
            "",
            "",
            "单位:百万元",
            ""
          ],
          [
            "会计年度",
            "2022A",
            "2023A",
            "2024E",
            "2025E",
            "2026E"
          ],
          [
            "营业总收入",
            "19,336",
            "40,683",
            "44,277",
            "47,311",
            "50,369"
          ],
          [
            "营业成本",
            "16,718",
            "22,052",
            "23,579",
            "24,524",
            "26,059"
          ],
          [
            "营业税金及附",
            "",
            "",
            "",
            "",
            ""
          ],
          [
            "",
            "2",
            "139",
            "142",
            "170",
            "181"
          ],
          [
            "加",
            "",
            "",
            "",
            "",
            ""
          ],
          [
            "",
            "",
            "",
            "",
            "",
            ""
          ],
          [
            "销售费用",
            "0",
            "0",
            "0",
            "0",
            "0"
          ],
          [
            "管理费用",
            "791",
            "802",
            "797",
            "994",
            "1,108"
          ],
          [
            "研发费用",
            "5",
            "11",
            "9",
            "14",
            "10"
          ],
          [
            "财务费用",
            "2,905",
            "2,365",
            "2,166",
            "1,685",
            "1,396"
          ],
          [
            "减值损失合计",
            "0",
            "0",
            "0",
            "0",
            "0"
          ],
          [
            "投资净收益",
            "0",
            "0",
            "0",
            "0",
            "0"
          ],
          [
            "",
            "",
            "",
            "",
            "",
            ""
          ],
          [
            "其他",
            "38",
            "0",
            "44",
            "2",
            "2"
          ],
          [
            "",
            "",
            "",
            "",
            "",
            ""
          ],
          [
            "营业利润",
            "-1,047",
            "15,314",
            "17,629",
            "19,926",
            "21,616"
          ],
          [
            "营业外收支",
            "2",
            "-5",
            "3",
            "2",
            "2"
          ],
          [
            "利润总额",
            "-1,045",
            "15,309",
            "17,632",
            "19,928",
            "21,618"
          ],
          [
            "所得税",
            "507",
            "4,102",
            "4,708",
            "5,381",
            "5,880"
          ],
          [
            "净利润",
            "-1,552",
            "11,207",
            "12,924",
            "14,547",
            "15,738"
          ],
          [
            "少数股东损益",
            "-976",
            "-338",
            "-129",
            "145",
            "157"
          ],
          [
            "归属母公司净",
            "",
            "",
            "",
            "",
            ""
          ],
          [
            "",
            "-576",
            "11,546",
            "13,054",
            "14,402",
            "15,581"
          ],
          [
            "利润",
            "",
            "",
            "",
            "",
            ""
          ],
          [
            "",
            "",
            "",
            "",
            "",
            ""
          ],
          [
            "EBITDA",
            "7,804",
            "23,605",
            "25,778",
            "27,624",
            "29,080"
          ],
          [
            "EPS (当",
            "",
            "",
            "",
            "",
            ""
          ],
          [
            "",
            "-0.01",
            "0.24",
            "0.27",
            "0.29",
            "0.32"
          ],
          [
            "年)(元)",
            "",
            "",
            "",
            "",
            ""
          ],
          [
            "",
            "",
            "",
            "",
            "",
            ""
          ]
        ],
        [
          [
            "会计年度",
            "2022A",
            "2023A",
            "2024E",
            "2025E",
            "2026E"
          ],
          [
            "经营活动现金",
            "6,801",
            "21,081",
            "22,979",
            "21,863",
            "23,221"
          ]
        ],
        [
          [
            "折旧摊销",
            "5,946",
            "5,926",
            "5,980",
            "6,011",
            "6,066"
          ]
        ],
        [
          [
            "",
            "",
            "",
            "",
            "",
            "单位:百万"
          ],
          [
            "重要财务指标",
            "",
            "",
            "",
            "",
            ""
          ],
          [
            "",
            "",
            "",
            "",
            "",
            "元"
          ],
          [
            "",
            "",
            "",
            "",
            "",
            ""
          ]
        ],
        [
          [
            "投资损失",
            "",
            "",
            "",
            "",
            ""
          ],
          [
            "",
            "0",
            "0",
            "0",
            "0",
            "0"
          ],
          [
            "",
            "",
            "",
            "",
            "",
            ""
          ]
        ],
        [
          [
            "营业总收入",
            "19,336",
            "40,683",
            "44,277",
            "47,311",
            "50,369"
          ]
        ],
        [
          [
            "其它",
            "-11",
            "-6",
            "4",
            "8",
            "-2"
          ]
        ],
        [
          [
            "归属母公司净利",
            "",
            "",
            "",
            "",
            ""
          ],
          [
            "",
            "-576",
            "11,546",
            "13,054",
            "14,402",
            "15,581"
          ],
          [
            "润",
            "",
            "",
            "",
            "",
            ""
          ],
          [
            "",
            "",
            "",
            "",
            "",
            ""
          ]
        ],
        [
          [
            "",
            "",
            "",
            "",
            "",
            ""
          ],
          [
            "资本支出",
            "-1,099",
            "-1,490",
            "-897",
            "-1,448",
            "-1,788"
          ],
          [
            "",
            "",
            "",
            "",
            "",
            ""
          ]
        ],
        [
          [
            "",
            "",
            "",
            "",
            "",
            ""
          ],
          [
            "毛利率（%）",
            "13.5%",
            "45.8%",
            "46.7%",
            "48.2%",
            "48.3%"
          ],
          [
            "",
            "",
            "",
            "",
            "",
            ""
          ]
        ],
        [
          [
            "",
            "",
            "",
            "",
            "",
            ""
          ],
          [
            "其他",
            "0",
            "378",
            "6",
            "0",
            "0"
          ],
          [
            "",
            "",
            "",
            "",
            "",
            ""
          ]
        ],
        [
          [
            "",
            "",
            "",
            "",
            "",
            ""
          ],
          [
            "EPS (摊薄)(元)",
            "-0.01",
            "0.24",
            "0.27",
            "0.29",
            "0.32"
          ],
          [
            "",
            "",
            "",
            "",
            "",
            ""
          ]
        ],
        [
          [
            "",
            "",
            "",
            "",
            "",
            ""
          ],
          [
            "吸收投资",
            "0",
            "0",
            "-5",
            "0",
            "0"
          ],
          [
            "",
            "",
            "",
            "",
            "",
            ""
          ]
        ],
        [
          [
            "",
            "",
            "",
            "",
            "",
            ""
          ],
          [
            "P/B",
            "1.41",
            "1.33",
            "1.28",
            "1.24",
            "1.19"
          ],
          [
            "",
            "",
            "",
            "",
            "",
            ""
          ],
          [
            "",
            "",
            "",
            "",
            "",
            ""
          ],
          [
            "EV/EBITDA",
            "40.02",
            "12.52",
            "11.62",
            "10.41",
            "9.46"
          ],
          [
            "",
            "",
            "",
            "",
            "",
            ""
          ]
        ],
        [
          [
            "支付利息或股",
            "",
            "",
            "",
            "",
            ""
          ],
          [
            "",
            "-5,560",
            "-3,277",
            "-7,839",
            "-8,468",
            "-8,896"
          ],
          [
            "息",
            "",
            "",
            "",
            "",
            ""
          ],
          [
            "",
            "",
            "",
            "",
            "",
            ""
          ]
        ]
      ]
    },
    {
      "page_number": 30,
      "width": 595.32,
      "height": 841.92,
      "text": "[研Ta究bl团e_I队ntr简od介uc tion]\n匡培钦，现任信达证券交运首席分析师，上海交通大学本硕，先后就职于申万研究所及\n浙商研究所担任交运首席分析师，专注于交通运输物流行业的产业链研究，深耕快递、\n物流、公路、铁路、港口、航空、海运等大交通领域，2021 年/2022 年新财富入围，2022\n年金牌分析师交运行业第一名，2022 年金麒麟新锐分析师第一名。\n请阅读最后一页免责声明及信息披露 http://www.cindasc.com 30",
      "tables": []
    },
    {
      "page_number": 31,
      "width": 595.32,
      "height": 841.92,
      "text": "分析师声明\n负责本报告全部或部分内容的每一位分析师在此申明，本人具有证券投资咨询执业资格，并在中国证券业协会注册登记为证券分析\n师,以勤勉的职业态度,独立、客观地出具本报告；本报告所表述的所有观点准确反映了分析师本人的研究观点；本人薪酬的任何组\n成部分不曾与，不与，也将不会与本报告中的具体分析意见或观点直接或间接相关。\n免责声明\n信达证券股份有限公司(以下简称“信达证券”)具有中国证监会批复的证券投资咨询业务资格。本报告由信达证券制作并发布。\n本报告是针对与信达证券签署服务协议的签约客户的专属研究产品，为该类客户进行投资决策时提供辅助和参考，双方对权利与义\n务均有严格约定。本报告仅提供给上述特定客户，并不面向公众发布。信达证券不会因接收人收到本报告而视其为本公司的当然客\n户。客户应当认识到有关本报告的电话、短信、邮件提示仅为研究观点的简要沟通，对本报告的参考使用须以本报告的完整版本为\n准。\n本报告是基于信达证券认为可靠的已公开信息编制，但信达证券不保证所载信息的准确性和完整性。本报告所载的意见、评估及预\n测仅为本报告最初出具日的观点和判断，本报告所指的证券或投资标的的价格、价值及投资收入可能会出现不同程度的波动，涉及\n证券或投资标的的历史表现不应作为日后表现的保证。在不同时期，或因使用不同假设和标准，采用不同观点和分析方法，致使信\n达证券发出与本报告所载意见、评估及预测不一致的研究报告，对此信达证券可不发出特别通知。\n在任何情况下，本报告中的信息或所表述的意见并不构成对任何人的投资建议，也没有考虑到客户特殊的投资目标、财务状况或需\n求。客户应考虑本报告中的任何意见或建议是否符合其特定状况，若有必要应寻求专家意见。本报告所载的资料、工具、意见及推\n测仅供参考，并非作为或被视为出售或购买证券或其他投资标的的邀请或向人做出邀请。\n在法律允许的情况下，信达证券或其关联机构可能会持有报告中涉及的公司所发行的证券并进行交易，并可能会为这些公司正在提\n供或争取提供投资银行业务服务。\n本报告版权仅为信达证券所有。未经信达证券书面同意，任何机构和个人不得以任何形式翻版、复制、发布、转发或引用本报告的\n任何部分。若信达证券以外的机构向其客户发放本报告，则由该机构独自为此发送行为负责，信达证券对此等行为不承担任何责任。\n本报告同时不构成信达证券向发送本报告的机构之客户提供的投资建议。\n如未经信达证券授权，私自转载或者转发本报告，所引起的一切后果及法律责任由私自转载或转发者承担。信达证券将保留随时追\n究其法律责任的权利。\n评级说明\n投资建议的比较标准 股票投资评级 行业投资评级\n买入：股价相对强于基准 15％以上； 看好：行业指数超越基准；\n本报告采用的基准指数 ：沪深 300 指\n增持：股价相对强于基准 5％～15％； 中性：行业指数与基准基本持平；\n数（以下简称基准）；\n持有：股价相对基准波动在±5% 之间； 看淡：行业指数弱于基准。\n时间段：报告发布之日起 6 个月内。\n卖出：股价相对弱于基准 5％以下。\n风险提示\n证券市场是一个风险无时不在的市场。投资者在进行证券交易时存在赢利的可能，也存在亏损的风险。建议投资者应当充分深入地\n了解证券市场蕴含的各项风险并谨慎行事。\n本报告中所述证券不一定能在所有的国家和地区向所有类型的投资者销售，投资者应当对本报告中的信息和意见进行独立评估，并\n应同时考量各自的投资目的、财务状况和特定需求，必要时就法律、商业、财务、税收等方面咨询专业顾问的意见。在任何情况下，\n信达证券不对任何人因使用本报告中的任何内容所引致的任何损失负任何责任，投资者需自行承担风险。\n请阅读最后一页免责声明及信息披露 http://www.cindasc.com 31",
      "tables": [
        [
          [
            "股票投资评级",
            "",
            "",
            "",
            "",
            ""
          ],
          [
            "买入：股价相对强于基准15％以上；",
            "",
            "",
            "",
            "",
            ""
          ],
          [
            "",
            "增持：股价相对强于基准5％～15％；",
            "",
            "",
            "中性：行业指数与基准基本持平；",
            ""
          ],
          [
            "持有：股价相对基准波动在±5% 之间；",
            "",
            "",
            "",
            "",
            ""
          ],
          [
            "",
            "卖出：股价相对弱于基准5％以下。",
            "",
            "",
            "",
            ""
          ]
        ]
      ]
    }
  ]
}